Workbook

Sheet Cover
B2: Boeing–Spirit Merger Analysis: Collar Valuation and Merger Arbitrage
B3: Collar pricer · Prepared by Alessandro Radice · Educational project, not investment advice · January 2026
B6: Question | C6: On 30 June 2024 Boeing agreed to buy Spirit AeroSystems for $37.25 a share, paid in Boeing stock, with a collar. What was the offer worth to Spirit shareholders, how did it compare with the alternatives, and what did they actually receive?
B7: Inputs | C7: Deal terms from the proxy statement, Boeing and the Treasury rate on 28 June 2024 (last close before signing), and the implied volatility at the two collar strikes from the Boeing surface fitted in Python.
B8: Pricer | C8: The collar as $37.25 paid at closing, minus 0.25 puts at $149.00, plus 0.18 calls at $206.94, all Black-Scholes, plus the small Monte Carlo averaging correction from Python. Compared with a fixed exchange ratio and a fixed value with no collar. Payoff at any Boeing VWAP.
B9: Scenarios | C9: Value per Spirit share for Boeing VWAPs from $100 to $280, under the three structures.
B10: Band grid | C10: Collar value for other floors and caps (as % of Boeing at signing), at a single flat volatility.
B11: Paths | C11: Every trading day from 1 July 2024 to closing: Boeing, Spirit, the 15-day VWAP, the value if the deal had closed that day, the model value from Python, the merger-arbitrage spread and the implied probability of completion.
B12: Checks | C12: Reconciliation with the Python engine (notebook sections 5 to 9).
B13: Switches | C13: Inputs!C6 = Boeing VWAP for the payoff on the Pricer sheet; Inputs!C7 = expected closing date; Inputs!C8 = Spirit price if the deal breaks.
B14: Colour code | C14: Blue = hard-coded input · Black = formula · Green = link to another sheet · Yellow fill = switch.
B15: Where the volatility comes from | C15: Boeing's implied volatility surface is fitted every day in Python (Boeing_Spirit_Collar_Analysis.ipynb) from end-of-day option quotes. This workbook takes the vols at the collar strikes and the daily model values as inputs; every other number is a live formula.
B16: Sources | C16: Boeing option chains and Boeing and Spirit prices: DoltHub post-no-preference/options and /stocks. Treasury yields: FRED. Deal terms: Spirit DEFM14A (20 Dec 2024) and Form 8-K (8 Dec 2025).

Sheet Inputs
B2: Inputs
B3: Per Spirit share unless stated · market on Friday 28 June 2024, the last close before signing
B5: Switches
B6: Boeing VWAP for the payoff (Pricer sheet) | C6: 182.01 | D6: Try 136.59 (April 2025 low), 190.54 (actual VWAP), 237.38 (September 2025 high)
B7: Expected closing date | C7: 45838 | D7: "Mid-2025" at signing. Actual effective time: 8 December 2025
B8: Spirit price if the deal breaks | C8: 28.6 | D8: Unaffected close on 29 February 2024, before reports of talks (Spirit announcement)
B10: Deal terms | C10: Value | D10: Note / source
B11: Value per Spirit share inside the band | C11: 37.25 | D11: Merger agreement, 30 June 2024 (Spirit DEFM14A)
B12: Floor (Boeing VWAP) | C12: 149 | D12: At or below: exchange ratio fixed
B13: Cap (Boeing VWAP) | C13: 206.94 | D13: At or above: exchange ratio fixed
B14: Exchange ratio at or below the floor | C14: 0.25 | D14: Contract figure; = $37.25 / $149.00
B15: Exchange ratio at or above the cap | C15: 0.18 | D15: Contract figure; = $37.25 / $206.94
B16: Check: floor ratio − value / floor | C16: =C14-C11/C12 -> 0 | D16: Should be 0
B17: Check: cap ratio − value / cap | C17: =C15-C11/C13 -> -3.8658548e-06 | D17: Rounding in the contract: 0.18 vs 0.180004
B18: VWAP window | C18: 15 trading days | D18: Ending on the second full trading day before the effective time
B20: Market, 28 June 2024 | C20: Value | D20: Note / source
B21: Valuation date | C21: 45471 | D21: Last close before the Sunday 30 June signing
B22: Years to closing | C22: =(C7-C21)/365 -> 1.0054795 | D22: Calendar days / 365
B23: Boeing close | C23: 182.01 | D23: Sets the fixed-ratio alternative: $37.25 / close
B24: Boeing spot at the quote snapshot | C24: 182.31942 | D24: Put-call parity across near-the-money strikes (Python)
B25: Risk-free rate, continuous | C25: 0.04962713 | D25: FRED Treasury curve at the closing horizon, ln(1 + y)
B26: Dividend yield | C26: 0 | D26: Boeing dividend suspended since 2020
B27: Implied vol at the $149.00 put strike | C27: 0.3358331 | D27: Boeing SVI surface, 28 June 2024, at the closing horizon (Python, section 5)
B28: Implied vol at the $206.94 call strike | C28: 0.32030495 | D28: Same surface; the skew makes the put vol higher
B29: At-the-money implied vol | C29: 0.32204842 | D29: Used for the band grid (flat vol)
B30: Discount factor to closing | C30: =EXP(-C25*C22) -> 0.95132545
B31: Forward to closing | C31: =C24*EXP((C25-C26)*C22) -> 191.64779 | D31: F = S e^((r − q) T)
B33: Closing, 8 December 2025 | C33: Value | D33: Note / source
B34: Exchange ratio applied | C34: 0.1955 | D34: Spirit Form 8-K, 8 December 2025
B35: Boeing close on the closing day | C35: 206.27 | D35: DoltHub, 8 December 2025
B36: Implied Boeing VWAP | C36: =C11/C34 -> 190.53708 | D36: Ratio rounded to four decimals

Sheet Pricer
B2: Pricer
B3: Black-Scholes, per Spirit share · valuation 28 June 2024 · closing on Inputs!C7
B5: Option leg | C5: Strike | D5: Implied vol | E5: d1 | F5: d2 | G5: Price | H5: Quantity | I5: Value
B6: Put on Boeing (Spirit holders are short) | C6: =Inputs!C12 -> 149 | D6: =Inputs!C27 -> 0.3358331 | E6: =(LN(Inputs!$C$24/C6)+(Inputs!$C$25-Inputs!$C$26+D6^2/2)*Inputs!$C$22)/(D6*SQRT(Inputs!$C$22)) -> 0.91584884 | F6: =E6-D6*SQRT(Inputs!$C$22) -> 0.57909691 | G6: =C6*Inputs!$C$30*NORMSDIST(-F6)-Inputs!$C$24*EXP(-Inputs!$C$26*Inputs!$C$22)*NORMSDIST(-E6) -> 7.0738109 | H6: =-Inputs!C14 -> -0.25 | I6: =G6*H6 -> -1.7684527
B7: Call on Boeing (Spirit holders are long) | C7: =Inputs!C13 -> 206.94 | D7: =Inputs!C28 -> 0.32030495 | E7: =(LN(Inputs!$C$24/C7)+(Inputs!$C$25-Inputs!$C$26+D7^2/2)*Inputs!$C$22)/(D7*SQRT(Inputs!$C$22)) -> -0.078432155 | F7: =E7-D7*SQRT(Inputs!$C$22) -> -0.39961345 | G7: =Inputs!$C$24*EXP(-Inputs!$C$26*Inputs!$C$22)*NORMSDIST(E7)-C7*Inputs!$C$30*NORMSDIST(F7) -> 17.596581 | H7: =Inputs!C15 -> 0.18 | I7: =G7*H7 -> 3.1673845
B10: Value of the offer on signing day | C10: Value | D10: vs fixed ratio
B11: $37.25 paid at closing, discounted | C11: =Inputs!C11*Inputs!C30 -> 35.436873
B12: Puts sold at the floor | C12: =I6 -> -1.7684527
B13: Calls kept above the cap | C13: =I7 -> 3.1673845
B14: Averaging and delivery lag (Monte Carlo, Python) | C14: -0.001359
B15: Collar (actual terms) | C15: =SUM(C11:C14) -> 36.834446 | D15: =C15-C16 -> -0.47887912
B16: Fixed exchange ratio (= $37.25 / Boeing close) | C16: =Inputs!C11/Inputs!C23*Inputs!C24*EXP(-Inputs!C26*Inputs!C22) -> 37.313325 | D16: =C16-C16 -> 0
B17: Fixed value, no collar | C17: =C11 -> 35.436873 | D17: =C17-C16 -> -1.8764519
B18: Fixed exchange ratio used | C18: =Inputs!C11/Inputs!C23 -> 0.20465908
B19: Cost of the collar vs fixed ratio, $M on ~126.2M shares | C19: =(C16-C15)*4700/Inputs!C11 -> 60.422332
B20: Shares ≈ $4.7bn equity value / $37.25 (Boeing announcement). The averaging row is the Monte Carlo correction for the 15-day VWAP and the two-day delivery lag at the Inputs!C7 closing date (notebook section 5); −$0.0014 for a mid-2025 closing, about −$0.015 for the actual 8 December 2025 closing. Update it from the notebook if you move Inputs!C7.
B22: Payoff at the VWAP on Inputs!C6 | C22: Value
B23: Boeing VWAP | C23: =Inputs!C6 -> 182.01
B24: Regime | C24: =IF(C23<=Inputs!C12,"Below the band",IF(C23>=Inputs!C13,"Above the band","Inside the band")) -> Inside the band
B25: Boeing shares per Spirit share | C25: =IF(C23<=Inputs!C12,Inputs!C14,IF(C23>=Inputs!C13,Inputs!C15,Inputs!C11/C23)) -> 0.20465908
B26: Collar value per Spirit share | C26: =C25*C23 -> 37.25
B27: Fixed exchange ratio | C27: =C18*C23 -> 37.25
B28: Fixed value, no collar | C28: =Inputs!C11 -> 37.25
B29: Collar vs fixed ratio | C29: =C26-C27 -> 0

Sheet Scenarios
B2: Scenarios
B3: Value per Spirit share at closing, by Boeing VWAP (shares valued at the VWAP)
B5: Boeing VWAP | C5: Regime | D5: Ratio | E5: Collar | F5: Fixed ratio | G5: Fixed value | H5: Collar − fixed ratio
B6: 100 | C6: =IF(B6<=Inputs!$C$12,"Below",IF(B6>=Inputs!$C$13,"Above","Inside")) -> Below | D6: =IF(B6<=Inputs!$C$12,Inputs!$C$14,IF(B6>=Inputs!$C$13,Inputs!$C$15,Inputs!$C$11/B6)) -> 0.25 | E6: =D6*B6 -> 25 | F6: =Pricer!$C$18*B6 -> 20.465908 | G6: =Inputs!$C$11 -> 37.25 | H6: =E6-F6 -> 4.5340915
B7: 105 | C7: =IF(B7<=Inputs!$C$12,"Below",IF(B7>=Inputs!$C$13,"Above","Inside")) -> Below | D7: =IF(B7<=Inputs!$C$12,Inputs!$C$14,IF(B7>=Inputs!$C$13,Inputs!$C$15,Inputs!$C$11/B7)) -> 0.25 | E7: =D7*B7 -> 26.25 | F7: =Pricer!$C$18*B7 -> 21.489204 | G7: =Inputs!$C$11 -> 37.25 | H7: =E7-F7 -> 4.7607961
B8: 110 | C8: =IF(B8<=Inputs!$C$12,"Below",IF(B8>=Inputs!$C$13,"Above","Inside")) -> Below | D8: =IF(B8<=Inputs!$C$12,Inputs!$C$14,IF(B8>=Inputs!$C$13,Inputs!$C$15,Inputs!$C$11/B8)) -> 0.25 | E8: =D8*B8 -> 27.5 | F8: =Pricer!$C$18*B8 -> 22.512499 | G8: =Inputs!$C$11 -> 37.25 | H8: =E8-F8 -> 4.9875007
B9: 115 | C9: =IF(B9<=Inputs!$C$12,"Below",IF(B9>=Inputs!$C$13,"Above","Inside")) -> Below | D9: =IF(B9<=Inputs!$C$12,Inputs!$C$14,IF(B9>=Inputs!$C$13,Inputs!$C$15,Inputs!$C$11/B9)) -> 0.25 | E9: =D9*B9 -> 28.75 | F9: =Pricer!$C$18*B9 -> 23.535795 | G9: =Inputs!$C$11 -> 37.25 | H9: =E9-F9 -> 5.2142053
B10: 120 | C10: =IF(B10<=Inputs!$C$12,"Below",IF(B10>=Inputs!$C$13,"Above","Inside")) -> Below | D10: =IF(B10<=Inputs!$C$12,Inputs!$C$14,IF(B10>=Inputs!$C$13,Inputs!$C$15,Inputs!$C$11/B10)) -> 0.25 | E10: =D10*B10 -> 30 | F10: =Pricer!$C$18*B10 -> 24.55909 | G10: =Inputs!$C$11 -> 37.25 | H10: =E10-F10 -> 5.4409098
B11: 125 | C11: =IF(B11<=Inputs!$C$12,"Below",IF(B11>=Inputs!$C$13,"Above","Inside")) -> Below | D11: =IF(B11<=Inputs!$C$12,Inputs!$C$14,IF(B11>=Inputs!$C$13,Inputs!$C$15,Inputs!$C$11/B11)) -> 0.25 | E11: =D11*B11 -> 31.25 | F11: =Pricer!$C$18*B11 -> 25.582386 | G11: =Inputs!$C$11 -> 37.25 | H11: =E11-F11 -> 5.6676144
B12: 130 | C12: =IF(B12<=Inputs!$C$12,"Below",IF(B12>=Inputs!$C$13,"Above","Inside")) -> Below | D12: =IF(B12<=Inputs!$C$12,Inputs!$C$14,IF(B12>=Inputs!$C$13,Inputs!$C$15,Inputs!$C$11/B12)) -> 0.25 | E12: =D12*B12 -> 32.5 | F12: =Pricer!$C$18*B12 -> 26.605681 | G12: =Inputs!$C$11 -> 37.25 | H12: =E12-F12 -> 5.894319
B13: 135 | C13: =IF(B13<=Inputs!$C$12,"Below",IF(B13>=Inputs!$C$13,"Above","Inside")) -> Below | D13: =IF(B13<=Inputs!$C$12,Inputs!$C$14,IF(B13>=Inputs!$C$13,Inputs!$C$15,Inputs!$C$11/B13)) -> 0.25 | E13: =D13*B13 -> 33.75 | F13: =Pricer!$C$18*B13 -> 27.628976 | G13: =Inputs!$C$11 -> 37.25 | H13: =E13-F13 -> 6.1210236
B14: 140 | C14: =IF(B14<=Inputs!$C$12,"Below",IF(B14>=Inputs!$C$13,"Above","Inside")) -> Below | D14: =IF(B14<=Inputs!$C$12,Inputs!$C$14,IF(B14>=Inputs!$C$13,Inputs!$C$15,Inputs!$C$11/B14)) -> 0.25 | E14: =D14*B14 -> 35 | F14: =Pricer!$C$18*B14 -> 28.652272 | G14: =Inputs!$C$11 -> 37.25 | H14: =E14-F14 -> 6.3477281
B15: 145 | C15: =IF(B15<=Inputs!$C$12,"Below",IF(B15>=Inputs!$C$13,"Above","Inside")) -> Below | D15: =IF(B15<=Inputs!$C$12,Inputs!$C$14,IF(B15>=Inputs!$C$13,Inputs!$C$15,Inputs!$C$11/B15)) -> 0.25 | E15: =D15*B15 -> 36.25 | F15: =Pricer!$C$18*B15 -> 29.675567 | G15: =Inputs!$C$11 -> 37.25 | H15: =E15-F15 -> 6.5744327
B16: 150 | C16: =IF(B16<=Inputs!$C$12,"Below",IF(B16>=Inputs!$C$13,"Above","Inside")) -> Inside | D16: =IF(B16<=Inputs!$C$12,Inputs!$C$14,IF(B16>=Inputs!$C$13,Inputs!$C$15,Inputs!$C$11/B16)) -> 0.24833333 | E16: =D16*B16 -> 37.25 | F16: =Pricer!$C$18*B16 -> 30.698863 | G16: =Inputs!$C$11 -> 37.25 | H16: =E16-F16 -> 6.5511373
B17: 155 | C17: =IF(B17<=Inputs!$C$12,"Below",IF(B17>=Inputs!$C$13,"Above","Inside")) -> Inside | D17: =IF(B17<=Inputs!$C$12,Inputs!$C$14,IF(B17>=Inputs!$C$13,Inputs!$C$15,Inputs!$C$11/B17)) -> 0.24032258 | E17: =D17*B17 -> 37.25 | F17: =Pricer!$C$18*B17 -> 31.722158 | G17: =Inputs!$C$11 -> 37.25 | H17: =E17-F17 -> 5.5278419
... B42: 280 | C42: =IF(B42<=Inputs!$C$12,"Below",IF(B42>=Inputs!$C$13,"Above","Inside")) -> Above | D42: =IF(B42<=Inputs!$C$12,Inputs!$C$14,IF(B42>=Inputs!$C$13,Inputs!$C$15,Inputs!$C$11/B42)) -> 0.18 | E42: =D42*B42 -> 50.4 | F42: =Pricer!$C$18*B42 -> 57.304544 | G42: =Inputs!$C$11 -> 37.25 | H42: =E42-F42 -> -6.9045437

Sheet Band grid
B2: Band grid
B3: Collar value per Spirit share on signing day, for other floors and caps · flat vol = Inputs!C29 · the $37.25 value is kept inside the band
B5: Floor ↓ / Cap → | C5: 1 | D5: 1.025 | E5: 1.05 | F5: 1.075 | G5: 1.1 | H5: 1.125 | I5: 1.15 | J5: 1.175 | K5: 1.2 | L5: 1.225 | M5: 1.25 | N5: 1.275 | O5: 1.3
B6: 0.7 | C6: =Inputs!$C$11*Inputs!$C$30-Inputs!$C$11/($B6*Inputs!$C$23)*(($B6*Inputs!$C$23)*Inputs!$C$30*NORMSDIST(-(((LN(Inputs!$C$24/($B6*Inputs!$C$23))+(Inputs!$C$25+Inputs!$C$29^2/2)*Inputs!$C$22)/(Inputs!$C$29*SQRT(Inputs!$C$22)))-Inputs!$C$29*SQRT(Inputs!$C$22)))-Inputs!$C$24*NORMSDIST(-((LN(Inputs!$C$24/($B6*Inputs!$C$23))+(Inputs!$C$25+Inputs!$C$29^2/2)*Inputs!$C$22)/(Inputs!$C$29*SQRT(Inputs!$C$22)))))+Inputs!$C$11/(C$5*Inputs!$C$23)*(Inputs!$C$24*NORMSDIST(((LN(Inputs!$C$24/(C$5*Inputs!$C$23))+(Inputs!$C$25+Inputs!$C$29^2/2)*Inputs!$C$22)/(Inputs!$C$29*SQRT(Inputs!$C$22))))-(C$5*Inputs!$C$23)*Inputs!$C$30*NORMSDIST(((LN(Inputs!$C$24/(C$5*Inputs!$C$23))+(Inputs!$C$25+Inputs!$C$29^2/2)*Inputs!$C$22)/(Inputs!$C$29*SQRT(Inputs!$C$22)))-Inputs!$C$29*SQRT(Inputs!$C$22))) -> 40.416971 | D6: =Inputs!$C$11*Inputs!$C$30-Inputs!$C$11/($B6*Inputs!$C$23)*(($B6*Inputs!$C$23)*Inputs!$C$30*NORMSDIST(-(((LN(Inputs!$C$24/($B6*Inputs!$C$23))+(Inputs!$C$25+Inputs!$C$29^2/2)*Inputs!$C$22)/(Inputs!$C$29*SQRT(Inputs!$C$22)))-Inputs!$C$29*SQRT(Inputs!$C$22)))-Inputs!$C$24*NORMSDIST(-((LN(Inputs!$C$24/($B6*Inputs!$C$23))+(Inputs!$C$25+Inputs!$C$29^2/2)*Inputs!$C$22)/(Inputs!$C$29*SQRT(Inputs!$C$22)))))+Inputs!$C$11/(D$5*Inputs!$C$23)*(Inputs!$C$24*NORMSDIST(((LN(Inputs!$C$24/(D$5*Inputs!$C$23))+(Inputs!$C$25+Inputs!$C$29^2/2)*Inputs!$C$22)/(Inputs!$C$29*SQRT(Inputs!$C$22))))-(D$5*Inputs!$C$23)*Inputs!$C$30*NORMSDIST(((LN(Inputs!$C$24/(D$5*Inputs!$C$23))+(Inputs!$C$25+Inputs!$C$29^2/2)*Inputs!$C$22)/(Inputs!$C$29*SQRT(Inputs!$C$22)))-Inputs!$C$29*SQRT(Inputs!$C$22))) -> 39.860501 | E6: =Inputs!$C$11*Inputs!$C$30-Inputs!$C$11/($B6*Inputs!$C$23)*(($B6*Inputs!$C$23)*Inputs!$C$30*NORMSDIST(-(((LN(Inputs!$C$24/($B6*Inputs!$C$23))+(Inputs!$C$25+Inputs!$C$29^2/2)*Inputs!$C$22)/(Inputs!$C$29*SQRT(Inputs!$C$22)))-Inputs!$C$29*SQRT(Inputs!$C$22)))-Inputs!$C$24*NORMSDIST(-((LN(Inputs!$C$24/($B6*Inputs!$C$23))+(Inputs!$C$25+Inputs!$C$29^2/2)*Inputs!$C$22)/(Inputs!$C$29*SQRT(Inputs!$C$22)))))+Inputs!$C$11/(E$5*Inputs!$C$23)*(Inputs!$C$24*NORMSDIST(((LN(Inputs!$C$24/(E$5*Inputs!$C$23))+(Inputs!$C$25+Inputs!$C$29^2/2)*Inputs!$C$22)/(Inputs!$C$29*SQRT(Inputs!$C$22))))-(E$5*Inputs!$C$23)*Inputs!$C$30*NORMSDIST(((LN(Inputs!$C$24/(E$5*Inputs!$C$23))+(Inputs!$C$25+Inputs!$C$29^2/2)*Inputs!$C$22)/(Inputs!$C$29*SQRT(Inputs!$C$22)))-Inputs!$C$29*SQRT(Inputs!$C$22))) -> 39.355868 | F6: =Inputs!$C$11*Inputs!$C$30-Inputs!$C$11/($B6*Inputs!$C$23)*(($B6*Inputs!$C$23)*Inputs!$C$30*NORMSDIST(-(((LN(Inputs!$C$24/($B6*Inputs!$C$23))+(Inputs!$C$25+Inputs!$C$29^2/2)*Inputs!$C$22)/(Inputs!$C$29*SQRT(Inputs!$C$22)))-Inputs!$C$29*SQRT(Inputs!$C$22)))-Inputs!$C$24*NORMSDIST(-((LN(Inputs!$C$24/($B6*Inputs!$C$23))+(Inputs!$C$25+Inputs!$C$29^2/2)*Inputs!$C$22)/(Inputs!$C$29*SQRT(Inputs!$C$22)))))+Inputs!$C$11/(F$5*Inputs!$C$23)*(Inputs!$C$24*NORMSDIST(((LN(Inputs!$C$24/(F$5*Inputs!$C$23))+(Inputs!$C$25+Inputs!$C$29^2/2)*Inputs!$C$22)/(Inputs!$C$29*SQRT(Inputs!$C$22))))-(F$5*Inputs!$C$23)*Inputs!$C$30*NORMSDIST(((LN(Inputs!$C$24/(F$5*Inputs!$C$23))+(Inputs!$C$25+Inputs!$C$29^2/2)*Inputs!$C$22)/(Inputs!$C$29*SQRT(Inputs!$C$22)))-Inputs!$C$29*SQRT(Inputs!$C$22))) -> 38.898657 | G6: =Inputs!$C$11*Inputs!$C$30-Inputs!$C$11/($B6*Inputs!$C$23)*(($B6*Inputs!$C$23)*Inputs!$C$30*NORMSDIST(-(((LN(Inputs!$C$24/($B6*Inputs!$C$23))+(Inputs!$C$25+Inputs!$C$29^2/2)*Inputs!$C$22)/(Inputs!$C$29*SQRT(Inputs!$C$22)))-Inputs!$C$29*SQRT(Inputs!$C$22)))-Inputs!$C$24*NORMSDIST(-((LN(Inputs!$C$24/($B6*Inputs!$C$23))+(Inputs!$C$25+Inputs!$C$29^2/2)*Inputs!$C$22)/(Inputs!$C$29*SQRT(Inputs!$C$22)))))+Inputs!$C$11/(G$5*Inputs!$C$23)*(Inputs!$C$24*NORMSDIST(((LN(Inputs!$C$24/(G$5*Inputs!$C$23))+(Inputs!$C$25+Inputs!$C$29^2/2)*Inputs!$C$22)/(Inputs!$C$29*SQRT(Inputs!$C$22))))-(G$5*Inputs!$C$23)*Inputs!$C$30*NORMSDIST(((LN(Inputs!$C$24/(G$5*Inputs!$C$23))+(Inputs!$C$25+Inputs!$C$29^2/2)*Inputs!$C$22)/(Inputs!$C$29*SQRT(Inputs!$C$22)))-Inputs!$C$29*SQRT(Inputs!$C$22))) -> 38.484781 | H6: =Inputs!$C$11*Inputs!$C$30-Inputs!$C$11/($B6*Inputs!$C$23)*(($B6*Inputs!$C$23)*Inputs!$C$30*NORMSDIST(-(((LN(Inputs!$C$24/($B6*Inputs!$C$23))+(Inputs!$C$25+Inputs!$C$29^2/2)*Inputs!$C$22)/(Inputs!$C$29*SQRT(Inputs!$C$22)))-Inputs!$C$29*SQRT(Inputs!$C$22)))-Inputs!$C$24*NORMSDIST(-((LN(Inputs!$C$24/($B6*Inputs!$C$23))+(Inputs!$C$25+Inputs!$C$29^2/2)*Inputs!$C$22)/(Inputs!$C$29*SQRT(Inputs!$C$22)))))+Inputs!$C$11/(H$5*Inputs!$C$23)*(Inputs!$C$24*NORMSDIST(((LN(Inputs!$C$24/(H$5*Inputs!$C$23))+(Inputs!$C$25+Inputs!$C$29^2/2)*Inputs!$C$22)/(Inputs!$C$29*SQRT(Inputs!$C$22))))-(H$5*Inputs!$C$23)*Inputs!$C$30*NORMSDIST(((LN(Inputs!$C$24/(H$5*Inputs!$C$23))+(Inputs!$C$25+Inputs!$C$29^2/2)*Inputs!$C$22)/(Inputs!$C$29*SQRT(Inputs!$C$22)))-Inputs!$C$29*SQRT(Inputs!$C$22))) -> 38.110454 | I6: =Inputs!$C$11*Inputs!$C$30-Inputs!$C$11/($B6*Inputs!$C$23)*(($B6*Inputs!$C$23)*Inputs!$C$30*NORMSDIST(-(((LN(Inputs!$C$24/($B6*Inputs!$C$23))+(Inputs!$C$25+Inputs!$C$29^2/2)*Inputs!$C$22)/(Inputs!$C$29*SQRT(Inputs!$C$22)))-Inputs!$C$29*SQRT(Inputs!$C$22)))-Inputs!$C$24*NORMSDIST(-((LN(Inputs!$C$24/($B6*Inputs!$C$23))+(Inputs!$C$25+Inputs!$C$29^2/2)*Inputs!$C$22)/(Inputs!$C$29*SQRT(Inputs!$C$22)))))+Inputs!$C$11/(I$5*Inputs!$C$23)*(Inputs!$C$24*NORMSDIST(((LN(Inputs!$C$24/(I$5*Inputs!$C$23))+(Inputs!$C$25+Inputs!$C$29^2/2)*Inputs!$C$22)/(Inputs!$C$29*SQRT(Inputs!$C$22))))-(I$5*Inputs!$C$23)*Inputs!$C$30*NORMSDIST(((LN(Inputs!$C$24/(I$5*Inputs!$C$23))+(Inputs!$C$25+Inputs!$C$29^2/2)*Inputs!$C$22)/(Inputs!$C$29*SQRT(Inputs!$C$22)))-Inputs!$C$29*SQRT(Inputs!$C$22))) -> 37.772174 | J6: =Inputs!$C$11*Inputs!$C$30-Inputs!$C$11/($B6*Inputs!$C$23)*(($B6*Inputs!$C$23)*Inputs!$C$30*NORMSDIST(-(((LN(Inputs!$C$24/($B6*Inputs!$C$23))+(Inputs!$C$25+Inputs!$C$29^2/2)*Inputs!$C$22)/(Inputs!$C$29*SQRT(Inputs!$C$22)))-Inputs!$C$29*SQRT(Inputs!$C$22)))-Inputs!$C$24*NORMSDIST(-((LN(Inputs!$C$24/($B6*Inputs!$C$23))+(Inputs!$C$25+Inputs!$C$29^2/2)*Inputs!$C$22)/(Inputs!$C$29*SQRT(Inputs!$C$22)))))+Inputs!$C$11/(J$5*Inputs!$C$23)*(Inputs!$C$24*NORMSDIST(((LN(Inputs!$C$24/(J$5*Inputs!$C$23))+(Inputs!$C$25+Inputs!$C$29^2/2)*Inputs!$C$22)/(Inputs!$C$29*SQRT(Inputs!$C$22))))-(J$5*Inputs!$C$23)*Inputs!$C$30*NORMSDIST(((LN(Inputs!$C$24/(J$5*Inputs!$C$23))+(Inputs!$C$25+Inputs!$C$29^2/2)*Inputs!$C$22)/(Inputs!$C$29*SQRT(Inputs!$C$22)))-Inputs!$C$29*SQRT(Inputs!$C$22))) -> 37.466714 | ... O6: =Inputs!$C$11*Inputs!$C$30-Inputs!$C$11/($B6*Inputs!$C$23)*(($B6*Inputs!$C$23)*Inputs!$C$30*NORMSDIST(-(((LN(Inputs!$C$24/($B6*Inputs!$C$23))+(Inputs!$C$25+Inputs!$C$29^2/2)*Inputs!$C$22)/(Inputs!$C$29*SQRT(Inputs!$C$22)))-Inputs!$C$29*SQRT(Inputs!$C$22)))-Inputs!$C$24*NORMSDIST(-((LN(Inputs!$C$24/($B6*Inputs!$C$23))+(Inputs!$C$25+Inputs!$C$29^2/2)*Inputs!$C$22)/(Inputs!$C$29*SQRT(Inputs!$C$22)))))+Inputs!$C$11/(O$5*Inputs!$C$23)*(Inputs!$C$24*NORMSDIST(((LN(Inputs!$C$24/(O$5*Inputs!$C$23))+(Inputs!$C$25+Inputs!$C$29^2/2)*Inputs!$C$22)/(Inputs!$C$29*SQRT(Inputs!$C$22))))-(O$5*Inputs!$C$23)*Inputs!$C$30*NORMSDIST(((LN(Inputs!$C$24/(O$5*Inputs!$C$23))+(Inputs!$C$25+Inputs!$C$29^2/2)*Inputs!$C$22)/(Inputs!$C$29*SQRT(Inputs!$C$22)))-Inputs!$C$29*SQRT(Inputs!$C$22))) -> 36.335585
B7: 0.725 | C7: =Inputs!$C$11*Inputs!$C$30-Inputs!$C$11/($B7*Inputs!$C$23)*(($B7*Inputs!$C$23)*Inputs!$C$30*NORMSDIST(-(((LN(Inputs!$C$24/($B7*Inputs!$C$23))+(Inputs!$C$25+Inputs!$C$29^2/2)*Inputs!$C$22)/(Inputs!$C$29*SQRT(Inputs!$C$22)))-Inputs!$C$29*SQRT(Inputs!$C$22)))-Inputs!$C$24*NORMSDIST(-((LN(Inputs!$C$24/($B7*Inputs!$C$23))+(Inputs!$C$25+Inputs!$C$29^2/2)*Inputs!$C$22)/(Inputs!$C$29*SQRT(Inputs!$C$22)))))+Inputs!$C$11/(C$5*Inputs!$C$23)*(Inputs!$C$24*NORMSDIST(((LN(Inputs!$C$24/(C$5*Inputs!$C$23))+(Inputs!$C$25+Inputs!$C$29^2/2)*Inputs!$C$22)/(Inputs!$C$29*SQRT(Inputs!$C$22))))-(C$5*Inputs!$C$23)*Inputs!$C$30*NORMSDIST(((LN(Inputs!$C$24/(C$5*Inputs!$C$23))+(Inputs!$C$25+Inputs!$C$29^2/2)*Inputs!$C$22)/(Inputs!$C$29*SQRT(Inputs!$C$22)))-Inputs!$C$29*SQRT(Inputs!$C$22))) -> 40.260403 | D7: =Inputs!$C$11*Inputs!$C$30-Inputs!$C$11/($B7*Inputs!$C$23)*(($B7*Inputs!$C$23)*Inputs!$C$30*NORMSDIST(-(((LN(Inputs!$C$24/($B7*Inputs!$C$23))+(Inputs!$C$25+Inputs!$C$29^2/2)*Inputs!$C$22)/(Inputs!$C$29*SQRT(Inputs!$C$22)))-Inputs!$C$29*SQRT(Inputs!$C$22)))-Inputs!$C$24*NORMSDIST(-((LN(Inputs!$C$24/($B7*Inputs!$C$23))+(Inputs!$C$25+Inputs!$C$29^2/2)*Inputs!$C$22)/(Inputs!$C$29*SQRT(Inputs!$C$22)))))+Inputs!$C$11/(D$5*Inputs!$C$23)*(Inputs!$C$24*NORMSDIST(((LN(Inputs!$C$24/(D$5*Inputs!$C$23))+(Inputs!$C$25+Inputs!$C$29^2/2)*Inputs!$C$22)/(Inputs!$C$29*SQRT(Inputs!$C$22))))-(D$5*Inputs!$C$23)*Inputs!$C$30*NORMSDIST(((LN(Inputs!$C$24/(D$5*Inputs!$C$23))+(Inputs!$C$25+Inputs!$C$29^2/2)*Inputs!$C$22)/(Inputs!$C$29*SQRT(Inputs!$C$22)))-Inputs!$C$29*SQRT(Inputs!$C$22))) -> 39.703934 | E7: =Inputs!$C$11*Inputs!$C$30-Inputs!$C$11/($B7*Inputs!$C$23)*(($B7*Inputs!$C$23)*Inputs!$C$30*NORMSDIST(-(((LN(Inputs!$C$24/($B7*Inputs!$C$23))+(Inputs!$C$25+Inputs!$C$29^2/2)*Inputs!$C$22)/(Inputs!$C$29*SQRT(Inputs!$C$22)))-Inputs!$C$29*SQRT(Inputs!$C$22)))-Inputs!$C$24*NORMSDIST(-((LN(Inputs!$C$24/($B7*Inputs!$C$23))+(Inputs!$C$25+Inputs!$C$29^2/2)*Inputs!$C$22)/(Inputs!$C$29*SQRT(Inputs!$C$22)))))+Inputs!$C$11/(E$5*Inputs!$C$23)*(Inputs!$C$24*NORMSDIST(((LN(Inputs!$C$24/(E$5*Inputs!$C$23))+(Inputs!$C$25+Inputs!$C$29^2/2)*Inputs!$C$22)/(Inputs!$C$29*SQRT(Inputs!$C$22))))-(E$5*Inputs!$C$23)*Inputs!$C$30*NORMSDIST(((LN(Inputs!$C$24/(E$5*Inputs!$C$23))+(Inputs!$C$25+Inputs!$C$29^2/2)*Inputs!$C$22)/(Inputs!$C$29*SQRT(Inputs!$C$22)))-Inputs!$C$29*SQRT(Inputs!$C$22))) -> 39.1993 | F7: =Inputs!$C$11*Inputs!$C$30-Inputs!$C$11/($B7*Inputs!$C$23)*(($B7*Inputs!$C$23)*Inputs!$C$30*NORMSDIST(-(((LN(Inputs!$C$24/($B7*Inputs!$C$23))+(Inputs!$C$25+Inputs!$C$29^2/2)*Inputs!$C$22)/(Inputs!$C$29*SQRT(Inputs!$C$22)))-Inputs!$C$29*SQRT(Inputs!$C$22)))-Inputs!$C$24*NORMSDIST(-((LN(Inputs!$C$24/($B7*Inputs!$C$23))+(Inputs!$C$25+Inputs!$C$29^2/2)*Inputs!$C$22)/(Inputs!$C$29*SQRT(Inputs!$C$22)))))+Inputs!$C$11/(F$5*Inputs!$C$23)*(Inputs!$C$24*NORMSDIST(((LN(Inputs!$C$24/(F$5*Inputs!$C$23))+(Inputs!$C$25+Inputs!$C$29^2/2)*Inputs!$C$22)/(Inputs!$C$29*SQRT(Inputs!$C$22))))-(F$5*Inputs!$C$23)*Inputs!$C$30*NORMSDIST(((LN(Inputs!$C$24/(F$5*Inputs!$C$23))+(Inputs!$C$25+Inputs!$C$29^2/2)*Inputs!$C$22)/(Inputs!$C$29*SQRT(Inputs!$C$22)))-Inputs!$C$29*SQRT(Inputs!$C$22))) -> 38.74209 | G7: =Inputs!$C$11*Inputs!$C$30-Inputs!$C$11/($B7*Inputs!$C$23)*(($B7*Inputs!$C$23)*Inputs!$C$30*NORMSDIST(-(((LN(Inputs!$C$24/($B7*Inputs!$C$23))+(Inputs!$C$25+Inputs!$C$29^2/2)*Inputs!$C$22)/(Inputs!$C$29*SQRT(Inputs!$C$22)))-Inputs!$C$29*SQRT(Inputs!$C$22)))-Inputs!$C$24*NORMSDIST(-((LN(Inputs!$C$24/($B7*Inputs!$C$23))+(Inputs!$C$25+Inputs!$C$29^2/2)*Inputs!$C$22)/(Inputs!$C$29*SQRT(Inputs!$C$22)))))+Inputs!$C$11/(G$5*Inputs!$C$23)*(Inputs!$C$24*NORMSDIST(((LN(Inputs!$C$24/(G$5*Inputs!$C$23))+(Inputs!$C$25+Inputs!$C$29^2/2)*Inputs!$C$22)/(Inputs!$C$29*SQRT(Inputs!$C$22))))-(G$5*Inputs!$C$23)*Inputs!$C$30*NORMSDIST(((LN(Inputs!$C$24/(G$5*Inputs!$C$23))+(Inputs!$C$25+Inputs!$C$29^2/2)*Inputs!$C$22)/(Inputs!$C$29*SQRT(Inputs!$C$22)))-Inputs!$C$29*SQRT(Inputs!$C$22))) -> 38.328214 | H7: =Inputs!$C$11*Inputs!$C$30-Inputs!$C$11/($B7*Inputs!$C$23)*(($B7*Inputs!$C$23)*Inputs!$C$30*NORMSDIST(-(((LN(Inputs!$C$24/($B7*Inputs!$C$23))+(Inputs!$C$25+Inputs!$C$29^2/2)*Inputs!$C$22)/(Inputs!$C$29*SQRT(Inputs!$C$22)))-Inputs!$C$29*SQRT(Inputs!$C$22)))-Inputs!$C$24*NORMSDIST(-((LN(Inputs!$C$24/($B7*Inputs!$C$23))+(Inputs!$C$25+Inputs!$C$29^2/2)*Inputs!$C$22)/(Inputs!$C$29*SQRT(Inputs!$C$22)))))+Inputs!$C$11/(H$5*Inputs!$C$23)*(Inputs!$C$24*NORMSDIST(((LN(Inputs!$C$24/(H$5*Inputs!$C$23))+(Inputs!$C$25+Inputs!$C$29^2/2)*Inputs!$C$22)/(Inputs!$C$29*SQRT(Inputs!$C$22))))-(H$5*Inputs!$C$23)*Inputs!$C$30*NORMSDIST(((LN(Inputs!$C$24/(H$5*Inputs!$C$23))+(Inputs!$C$25+Inputs!$C$29^2/2)*Inputs!$C$22)/(Inputs!$C$29*SQRT(Inputs!$C$22)))-Inputs!$C$29*SQRT(Inputs!$C$22))) -> 37.953886 | I7: =Inputs!$C$11*Inputs!$C$30-Inputs!$C$11/($B7*Inputs!$C$23)*(($B7*Inputs!$C$23)*Inputs!$C$30*NORMSDIST(-(((LN(Inputs!$C$24/($B7*Inputs!$C$23))+(Inputs!$C$25+Inputs!$C$29^2/2)*Inputs!$C$22)/(Inputs!$C$29*SQRT(Inputs!$C$22)))-Inputs!$C$29*SQRT(Inputs!$C$22)))-Inputs!$C$24*NORMSDIST(-((LN(Inputs!$C$24/($B7*Inputs!$C$23))+(Inputs!$C$25+Inputs!$C$29^2/2)*Inputs!$C$22)/(Inputs!$C$29*SQRT(Inputs!$C$22)))))+Inputs!$C$11/(I$5*Inputs!$C$23)*(Inputs!$C$24*NORMSDIST(((LN(Inputs!$C$24/(I$5*Inputs!$C$23))+(Inputs!$C$25+Inputs!$C$29^2/2)*Inputs!$C$22)/(Inputs!$C$29*SQRT(Inputs!$C$22))))-(I$5*Inputs!$C$23)*Inputs!$C$30*NORMSDIST(((LN(Inputs!$C$24/(I$5*Inputs!$C$23))+(Inputs!$C$25+Inputs!$C$29^2/2)*Inputs!$C$22)/(Inputs!$C$29*SQRT(Inputs!$C$22)))-Inputs!$C$29*SQRT(Inputs!$C$22))) -> 37.615607 | J7: =Inputs!$C$11*Inputs!$C$30-Inputs!$C$11/($B7*Inputs!$C$23)*(($B7*Inputs!$C$23)*Inputs!$C$30*NORMSDIST(-(((LN(Inputs!$C$24/($B7*Inputs!$C$23))+(Inputs!$C$25+Inputs!$C$29^2/2)*Inputs!$C$22)/(Inputs!$C$29*SQRT(Inputs!$C$22)))-Inputs!$C$29*SQRT(Inputs!$C$22)))-Inputs!$C$24*NORMSDIST(-((LN(Inputs!$C$24/($B7*Inputs!$C$23))+(Inputs!$C$25+Inputs!$C$29^2/2)*Inputs!$C$22)/(Inputs!$C$29*SQRT(Inputs!$C$22)))))+Inputs!$C$11/(J$5*Inputs!$C$23)*(Inputs!$C$24*NORMSDIST(((LN(Inputs!$C$24/(J$5*Inputs!$C$23))+(Inputs!$C$25+Inputs!$C$29^2/2)*Inputs!$C$22)/(Inputs!$C$29*SQRT(Inputs!$C$22))))-(J$5*Inputs!$C$23)*Inputs!$C$30*NORMSDIST(((LN(Inputs!$C$24/(J$5*Inputs!$C$23))+(Inputs!$C$25+Inputs!$C$29^2/2)*Inputs!$C$22)/(Inputs!$C$29*SQRT(Inputs!$C$22)))-Inputs!$C$29*SQRT(Inputs!$C$22))) -> 37.310146 | ... O7: =Inputs!$C$11*Inputs!$C$30-Inputs!$C$11/($B7*Inputs!$C$23)*(($B7*Inputs!$C$23)*Inputs!$C$30*NORMSDIST(-(((LN(Inputs!$C$24/($B7*Inputs!$C$23))+(Inputs!$C$25+Inputs!$C$29^2/2)*Inputs!$C$22)/(Inputs!$C$29*SQRT(Inputs!$C$22)))-Inputs!$C$29*SQRT(Inputs!$C$22)))-Inputs!$C$24*NORMSDIST(-((LN(Inputs!$C$24/($B7*Inputs!$C$23))+(Inputs!$C$25+Inputs!$C$29^2/2)*Inputs!$C$22)/(Inputs!$C$29*SQRT(Inputs!$C$22)))))+Inputs!$C$11/(O$5*Inputs!$C$23)*(Inputs!$C$24*NORMSDIST(((LN(Inputs!$C$24/(O$5*Inputs!$C$23))+(Inputs!$C$25+Inputs!$C$29^2/2)*Inputs!$C$22)/(Inputs!$C$29*SQRT(Inputs!$C$22))))-(O$5*Inputs!$C$23)*Inputs!$C$30*NORMSDIST(((LN(Inputs!$C$24/(O$5*Inputs!$C$23))+(Inputs!$C$25+Inputs!$C$29^2/2)*Inputs!$C$22)/(Inputs!$C$29*SQRT(Inputs!$C$22)))-Inputs!$C$29*SQRT(Inputs!$C$22))) -> 36.179018
B8: 0.75 | C8: =Inputs!$C$11*Inputs!$C$30-Inputs!$C$11/($B8*Inputs!$C$23)*(($B8*Inputs!$C$23)*Inputs!$C$30*NORMSDIST(-(((LN(Inputs!$C$24/($B8*Inputs!$C$23))+(Inputs!$C$25+Inputs!$C$29^2/2)*Inputs!$C$22)/(Inputs!$C$29*SQRT(Inputs!$C$22)))-Inputs!$C$29*SQRT(Inputs!$C$22)))-Inputs!$C$24*NORMSDIST(-((LN(Inputs!$C$24/($B8*Inputs!$C$23))+(Inputs!$C$25+Inputs!$C$29^2/2)*Inputs!$C$22)/(Inputs!$C$29*SQRT(Inputs!$C$22)))))+Inputs!$C$11/(C$5*Inputs!$C$23)*(Inputs!$C$24*NORMSDIST(((LN(Inputs!$C$24/(C$5*Inputs!$C$23))+(Inputs!$C$25+Inputs!$C$29^2/2)*Inputs!$C$22)/(Inputs!$C$29*SQRT(Inputs!$C$22))))-(C$5*Inputs!$C$23)*Inputs!$C$30*NORMSDIST(((LN(Inputs!$C$24/(C$5*Inputs!$C$23))+(Inputs!$C$25+Inputs!$C$29^2/2)*Inputs!$C$22)/(Inputs!$C$29*SQRT(Inputs!$C$22)))-Inputs!$C$29*SQRT(Inputs!$C$22))) -> 40.083597 | D8: =Inputs!$C$11*Inputs!$C$30-Inputs!$C$11/($B8*Inputs!$C$23)*(($B8*Inputs!$C$23)*Inputs!$C$30*NORMSDIST(-(((LN(Inputs!$C$24/($B8*Inputs!$C$23))+(Inputs!$C$25+Inputs!$C$29^2/2)*Inputs!$C$22)/(Inputs!$C$29*SQRT(Inputs!$C$22)))-Inputs!$C$29*SQRT(Inputs!$C$22)))-Inputs!$C$24*NORMSDIST(-((LN(Inputs!$C$24/($B8*Inputs!$C$23))+(Inputs!$C$25+Inputs!$C$29^2/2)*Inputs!$C$22)/(Inputs!$C$29*SQRT(Inputs!$C$22)))))+Inputs!$C$11/(D$5*Inputs!$C$23)*(Inputs!$C$24*NORMSDIST(((LN(Inputs!$C$24/(D$5*Inputs!$C$23))+(Inputs!$C$25+Inputs!$C$29^2/2)*Inputs!$C$22)/(Inputs!$C$29*SQRT(Inputs!$C$22))))-(D$5*Inputs!$C$23)*Inputs!$C$30*NORMSDIST(((LN(Inputs!$C$24/(D$5*Inputs!$C$23))+(Inputs!$C$25+Inputs!$C$29^2/2)*Inputs!$C$22)/(Inputs!$C$29*SQRT(Inputs!$C$22)))-Inputs!$C$29*SQRT(Inputs!$C$22))) -> 39.527127 | E8: =Inputs!$C$11*Inputs!$C$30-Inputs!$C$11/($B8*Inputs!$C$23)*(($B8*Inputs!$C$23)*Inputs!$C$30*NORMSDIST(-(((LN(Inputs!$C$24/($B8*Inputs!$C$23))+(Inputs!$C$25+Inputs!$C$29^2/2)*Inputs!$C$22)/(Inputs!$C$29*SQRT(Inputs!$C$22)))-Inputs!$C$29*SQRT(Inputs!$C$22)))-Inputs!$C$24*NORMSDIST(-((LN(Inputs!$C$24/($B8*Inputs!$C$23))+(Inputs!$C$25+Inputs!$C$29^2/2)*Inputs!$C$22)/(Inputs!$C$29*SQRT(Inputs!$C$22)))))+Inputs!$C$11/(E$5*Inputs!$C$23)*(Inputs!$C$24*NORMSDIST(((LN(Inputs!$C$24/(E$5*Inputs!$C$23))+(Inputs!$C$25+Inputs!$C$29^2/2)*Inputs!$C$22)/(Inputs!$C$29*SQRT(Inputs!$C$22))))-(E$5*Inputs!$C$23)*Inputs!$C$30*NORMSDIST(((LN(Inputs!$C$24/(E$5*Inputs!$C$23))+(Inputs!$C$25+Inputs!$C$29^2/2)*Inputs!$C$22)/(Inputs!$C$29*SQRT(Inputs!$C$22)))-Inputs!$C$29*SQRT(Inputs!$C$22))) -> 39.022494 | F8: =Inputs!$C$11*Inputs!$C$30-Inputs!$C$11/($B8*Inputs!$C$23)*(($B8*Inputs!$C$23)*Inputs!$C$30*NORMSDIST(-(((LN(Inputs!$C$24/($B8*Inputs!$C$23))+(Inputs!$C$25+Inputs!$C$29^2/2)*Inputs!$C$22)/(Inputs!$C$29*SQRT(Inputs!$C$22)))-Inputs!$C$29*SQRT(Inputs!$C$22)))-Inputs!$C$24*NORMSDIST(-((LN(Inputs!$C$24/($B8*Inputs!$C$23))+(Inputs!$C$25+Inputs!$C$29^2/2)*Inputs!$C$22)/(Inputs!$C$29*SQRT(Inputs!$C$22)))))+Inputs!$C$11/(F$5*Inputs!$C$23)*(Inputs!$C$24*NORMSDIST(((LN(Inputs!$C$24/(F$5*Inputs!$C$23))+(Inputs!$C$25+Inputs!$C$29^2/2)*Inputs!$C$22)/(Inputs!$C$29*SQRT(Inputs!$C$22))))-(F$5*Inputs!$C$23)*Inputs!$C$30*NORMSDIST(((LN(Inputs!$C$24/(F$5*Inputs!$C$23))+(Inputs!$C$25+Inputs!$C$29^2/2)*Inputs!$C$22)/(Inputs!$C$29*SQRT(Inputs!$C$22)))-Inputs!$C$29*SQRT(Inputs!$C$22))) -> 38.565283 | G8: =Inputs!$C$11*Inputs!$C$30-Inputs!$C$11/($B8*Inputs!$C$23)*(($B8*Inputs!$C$23)*Inputs!$C$30*NORMSDIST(-(((LN(Inputs!$C$24/($B8*Inputs!$C$23))+(Inputs!$C$25+Inputs!$C$29^2/2)*Inputs!$C$22)/(Inputs!$C$29*SQRT(Inputs!$C$22)))-Inputs!$C$29*SQRT(Inputs!$C$22)))-Inputs!$C$24*NORMSDIST(-((LN(Inputs!$C$24/($B8*Inputs!$C$23))+(Inputs!$C$25+Inputs!$C$29^2/2)*Inputs!$C$22)/(Inputs!$C$29*SQRT(Inputs!$C$22)))))+Inputs!$C$11/(G$5*Inputs!$C$23)*(Inputs!$C$24*NORMSDIST(((LN(Inputs!$C$24/(G$5*Inputs!$C$23))+(Inputs!$C$25+Inputs!$C$29^2/2)*Inputs!$C$22)/(Inputs!$C$29*SQRT(Inputs!$C$22))))-(G$5*Inputs!$C$23)*Inputs!$C$30*NORMSDIST(((LN(Inputs!$C$24/(G$5*Inputs!$C$23))+(Inputs!$C$25+Inputs!$C$29^2/2)*Inputs!$C$22)/(Inputs!$C$29*SQRT(Inputs!$C$22)))-Inputs!$C$29*SQRT(Inputs!$C$22))) -> 38.151407 | H8: =Inputs!$C$11*Inputs!$C$30-Inputs!$C$11/($B8*Inputs!$C$23)*(($B8*Inputs!$C$23)*Inputs!$C$30*NORMSDIST(-(((LN(Inputs!$C$24/($B8*Inputs!$C$23))+(Inputs!$C$25+Inputs!$C$29^2/2)*Inputs!$C$22)/(Inputs!$C$29*SQRT(Inputs!$C$22)))-Inputs!$C$29*SQRT(Inputs!$C$22)))-Inputs!$C$24*NORMSDIST(-((LN(Inputs!$C$24/($B8*Inputs!$C$23))+(Inputs!$C$25+Inputs!$C$29^2/2)*Inputs!$C$22)/(Inputs!$C$29*SQRT(Inputs!$C$22)))))+Inputs!$C$11/(H$5*Inputs!$C$23)*(Inputs!$C$24*NORMSDIST(((LN(Inputs!$C$24/(H$5*Inputs!$C$23))+(Inputs!$C$25+Inputs!$C$29^2/2)*Inputs!$C$22)/(Inputs!$C$29*SQRT(Inputs!$C$22))))-(H$5*Inputs!$C$23)*Inputs!$C$30*NORMSDIST(((LN(Inputs!$C$24/(H$5*Inputs!$C$23))+(Inputs!$C$25+Inputs!$C$29^2/2)*Inputs!$C$22)/(Inputs!$C$29*SQRT(Inputs!$C$22)))-Inputs!$C$29*SQRT(Inputs!$C$22))) -> 37.77708 | I8: =Inputs!$C$11*Inputs!$C$30-Inputs!$C$11/($B8*Inputs!$C$23)*(($B8*Inputs!$C$23)*Inputs!$C$30*NORMSDIST(-(((LN(Inputs!$C$24/($B8*Inputs!$C$23))+(Inputs!$C$25+Inputs!$C$29^2/2)*Inputs!$C$22)/(Inputs!$C$29*SQRT(Inputs!$C$22)))-Inputs!$C$29*SQRT(Inputs!$C$22)))-Inputs!$C$24*NORMSDIST(-((LN(Inputs!$C$24/($B8*Inputs!$C$23))+(Inputs!$C$25+Inputs!$C$29^2/2)*Inputs!$C$22)/(Inputs!$C$29*SQRT(Inputs!$C$22)))))+Inputs!$C$11/(I$5*Inputs!$C$23)*(Inputs!$C$24*NORMSDIST(((LN(Inputs!$C$24/(I$5*Inputs!$C$23))+(Inputs!$C$25+Inputs!$C$29^2/2)*Inputs!$C$22)/(Inputs!$C$29*SQRT(Inputs!$C$22))))-(I$5*Inputs!$C$23)*Inputs!$C$30*NORMSDIST(((LN(Inputs!$C$24/(I$5*Inputs!$C$23))+(Inputs!$C$25+Inputs!$C$29^2/2)*Inputs!$C$22)/(Inputs!$C$29*SQRT(Inputs!$C$22)))-Inputs!$C$29*SQRT(Inputs!$C$22))) -> 37.4388 | J8: =Inputs!$C$11*Inputs!$C$30-Inputs!$C$11/($B8*Inputs!$C$23)*(($B8*Inputs!$C$23)*Inputs!$C$30*NORMSDIST(-(((LN(Inputs!$C$24/($B8*Inputs!$C$23))+(Inputs!$C$25+Inputs!$C$29^2/2)*Inputs!$C$22)/(Inputs!$C$29*SQRT(Inputs!$C$22)))-Inputs!$C$29*SQRT(Inputs!$C$22)))-Inputs!$C$24*NORMSDIST(-((LN(Inputs!$C$24/($B8*Inputs!$C$23))+(Inputs!$C$25+Inputs!$C$29^2/2)*Inputs!$C$22)/(Inputs!$C$29*SQRT(Inputs!$C$22)))))+Inputs!$C$11/(J$5*Inputs!$C$23)*(Inputs!$C$24*NORMSDIST(((LN(Inputs!$C$24/(J$5*Inputs!$C$23))+(Inputs!$C$25+Inputs!$C$29^2/2)*Inputs!$C$22)/(Inputs!$C$29*SQRT(Inputs!$C$22))))-(J$5*Inputs!$C$23)*Inputs!$C$30*NORMSDIST(((LN(Inputs!$C$24/(J$5*Inputs!$C$23))+(Inputs!$C$25+Inputs!$C$29^2/2)*Inputs!$C$22)/(Inputs!$C$29*SQRT(Inputs!$C$22)))-Inputs!$C$29*SQRT(Inputs!$C$22))) -> 37.13334 | ... O8: =Inputs!$C$11*Inputs!$C$30-Inputs!$C$11/($B8*Inputs!$C$23)*(($B8*Inputs!$C$23)*Inputs!$C$30*NORMSDIST(-(((LN(Inputs!$C$24/($B8*Inputs!$C$23))+(Inputs!$C$25+Inputs!$C$29^2/2)*Inputs!$C$22)/(Inputs!$C$29*SQRT(Inputs!$C$22)))-Inputs!$C$29*SQRT(Inputs!$C$22)))-Inputs!$C$24*NORMSDIST(-((LN(Inputs!$C$24/($B8*Inputs!$C$23))+(Inputs!$C$25+Inputs!$C$29^2/2)*Inputs!$C$22)/(Inputs!$C$29*SQRT(Inputs!$C$22)))))+Inputs!$C$11/(O$5*Inputs!$C$23)*(Inputs!$C$24*NORMSDIST(((LN(Inputs!$C$24/(O$5*Inputs!$C$23))+(Inputs!$C$25+Inputs!$C$29^2/2)*Inputs!$C$22)/(Inputs!$C$29*SQRT(Inputs!$C$22))))-(O$5*Inputs!$C$23)*Inputs!$C$30*NORMSDIST(((LN(Inputs!$C$24/(O$5*Inputs!$C$23))+(Inputs!$C$25+Inputs!$C$29^2/2)*Inputs!$C$22)/(Inputs!$C$29*SQRT(Inputs!$C$22)))-Inputs!$C$29*SQRT(Inputs!$C$22))) -> 36.002211
B9: 0.775 | C9: =Inputs!$C$11*Inputs!$C$30-Inputs!$C$11/($B9*Inputs!$C$23)*(($B9*Inputs!$C$23)*Inputs!$C$30*NORMSDIST(-(((LN(Inputs!$C$24/($B9*Inputs!$C$23))+(Inputs!$C$25+Inputs!$C$29^2/2)*Inputs!$C$22)/(Inputs!$C$29*SQRT(Inputs!$C$22)))-Inputs!$C$29*SQRT(Inputs!$C$22)))-Inputs!$C$24*NORMSDIST(-((LN(Inputs!$C$24/($B9*Inputs!$C$23))+(Inputs!$C$25+Inputs!$C$29^2/2)*Inputs!$C$22)/(Inputs!$C$29*SQRT(Inputs!$C$22)))))+Inputs!$C$11/(C$5*Inputs!$C$23)*(Inputs!$C$24*NORMSDIST(((LN(Inputs!$C$24/(C$5*Inputs!$C$23))+(Inputs!$C$25+Inputs!$C$29^2/2)*Inputs!$C$22)/(Inputs!$C$29*SQRT(Inputs!$C$22))))-(C$5*Inputs!$C$23)*Inputs!$C$30*NORMSDIST(((LN(Inputs!$C$24/(C$5*Inputs!$C$23))+(Inputs!$C$25+Inputs!$C$29^2/2)*Inputs!$C$22)/(Inputs!$C$29*SQRT(Inputs!$C$22)))-Inputs!$C$29*SQRT(Inputs!$C$22))) -> 39.886519 | D9: =Inputs!$C$11*Inputs!$C$30-Inputs!$C$11/($B9*Inputs!$C$23)*(($B9*Inputs!$C$23)*Inputs!$C$30*NORMSDIST(-(((LN(Inputs!$C$24/($B9*Inputs!$C$23))+(Inputs!$C$25+Inputs!$C$29^2/2)*Inputs!$C$22)/(Inputs!$C$29*SQRT(Inputs!$C$22)))-Inputs!$C$29*SQRT(Inputs!$C$22)))-Inputs!$C$24*NORMSDIST(-((LN(Inputs!$C$24/($B9*Inputs!$C$23))+(Inputs!$C$25+Inputs!$C$29^2/2)*Inputs!$C$22)/(Inputs!$C$29*SQRT(Inputs!$C$22)))))+Inputs!$C$11/(D$5*Inputs!$C$23)*(Inputs!$C$24*NORMSDIST(((LN(Inputs!$C$24/(D$5*Inputs!$C$23))+(Inputs!$C$25+Inputs!$C$29^2/2)*Inputs!$C$22)/(Inputs!$C$29*SQRT(Inputs!$C$22))))-(D$5*Inputs!$C$23)*Inputs!$C$30*NORMSDIST(((LN(Inputs!$C$24/(D$5*Inputs!$C$23))+(Inputs!$C$25+Inputs!$C$29^2/2)*Inputs!$C$22)/(Inputs!$C$29*SQRT(Inputs!$C$22)))-Inputs!$C$29*SQRT(Inputs!$C$22))) -> 39.330049 | E9: =Inputs!$C$11*Inputs!$C$30-Inputs!$C$11/($B9*Inputs!$C$23)*(($B9*Inputs!$C$23)*Inputs!$C$30*NORMSDIST(-(((LN(Inputs!$C$24/($B9*Inputs!$C$23))+(Inputs!$C$25+Inputs!$C$29^2/2)*Inputs!$C$22)/(Inputs!$C$29*SQRT(Inputs!$C$22)))-Inputs!$C$29*SQRT(Inputs!$C$22)))-Inputs!$C$24*NORMSDIST(-((LN(Inputs!$C$24/($B9*Inputs!$C$23))+(Inputs!$C$25+Inputs!$C$29^2/2)*Inputs!$C$22)/(Inputs!$C$29*SQRT(Inputs!$C$22)))))+Inputs!$C$11/(E$5*Inputs!$C$23)*(Inputs!$C$24*NORMSDIST(((LN(Inputs!$C$24/(E$5*Inputs!$C$23))+(Inputs!$C$25+Inputs!$C$29^2/2)*Inputs!$C$22)/(Inputs!$C$29*SQRT(Inputs!$C$22))))-(E$5*Inputs!$C$23)*Inputs!$C$30*NORMSDIST(((LN(Inputs!$C$24/(E$5*Inputs!$C$23))+(Inputs!$C$25+Inputs!$C$29^2/2)*Inputs!$C$22)/(Inputs!$C$29*SQRT(Inputs!$C$22)))-Inputs!$C$29*SQRT(Inputs!$C$22))) -> 38.825416 | F9: =Inputs!$C$11*Inputs!$C$30-Inputs!$C$11/($B9*Inputs!$C$23)*(($B9*Inputs!$C$23)*Inputs!$C$30*NORMSDIST(-(((LN(Inputs!$C$24/($B9*Inputs!$C$23))+(Inputs!$C$25+Inputs!$C$29^2/2)*Inputs!$C$22)/(Inputs!$C$29*SQRT(Inputs!$C$22)))-Inputs!$C$29*SQRT(Inputs!$C$22)))-Inputs!$C$24*NORMSDIST(-((LN(Inputs!$C$24/($B9*Inputs!$C$23))+(Inputs!$C$25+Inputs!$C$29^2/2)*Inputs!$C$22)/(Inputs!$C$29*SQRT(Inputs!$C$22)))))+Inputs!$C$11/(F$5*Inputs!$C$23)*(Inputs!$C$24*NORMSDIST(((LN(Inputs!$C$24/(F$5*Inputs!$C$23))+(Inputs!$C$25+Inputs!$C$29^2/2)*Inputs!$C$22)/(Inputs!$C$29*SQRT(Inputs!$C$22))))-(F$5*Inputs!$C$23)*Inputs!$C$30*NORMSDIST(((LN(Inputs!$C$24/(F$5*Inputs!$C$23))+(Inputs!$C$25+Inputs!$C$29^2/2)*Inputs!$C$22)/(Inputs!$C$29*SQRT(Inputs!$C$22)))-Inputs!$C$29*SQRT(Inputs!$C$22))) -> 38.368205 | G9: =Inputs!$C$11*Inputs!$C$30-Inputs!$C$11/($B9*Inputs!$C$23)*(($B9*Inputs!$C$23)*Inputs!$C$30*NORMSDIST(-(((LN(Inputs!$C$24/($B9*Inputs!$C$23))+(Inputs!$C$25+Inputs!$C$29^2/2)*Inputs!$C$22)/(Inputs!$C$29*SQRT(Inputs!$C$22)))-Inputs!$C$29*SQRT(Inputs!$C$22)))-Inputs!$C$24*NORMSDIST(-((LN(Inputs!$C$24/($B9*Inputs!$C$23))+(Inputs!$C$25+Inputs!$C$29^2/2)*Inputs!$C$22)/(Inputs!$C$29*SQRT(Inputs!$C$22)))))+Inputs!$C$11/(G$5*Inputs!$C$23)*(Inputs!$C$24*NORMSDIST(((LN(Inputs!$C$24/(G$5*Inputs!$C$23))+(Inputs!$C$25+Inputs!$C$29^2/2)*Inputs!$C$22)/(Inputs!$C$29*SQRT(Inputs!$C$22))))-(G$5*Inputs!$C$23)*Inputs!$C$30*NORMSDIST(((LN(Inputs!$C$24/(G$5*Inputs!$C$23))+(Inputs!$C$25+Inputs!$C$29^2/2)*Inputs!$C$22)/(Inputs!$C$29*SQRT(Inputs!$C$22)))-Inputs!$C$29*SQRT(Inputs!$C$22))) -> 37.954329 | H9: =Inputs!$C$11*Inputs!$C$30-Inputs!$C$11/($B9*Inputs!$C$23)*(($B9*Inputs!$C$23)*Inputs!$C$30*NORMSDIST(-(((LN(Inputs!$C$24/($B9*Inputs!$C$23))+(Inputs!$C$25+Inputs!$C$29^2/2)*Inputs!$C$22)/(Inputs!$C$29*SQRT(Inputs!$C$22)))-Inputs!$C$29*SQRT(Inputs!$C$22)))-Inputs!$C$24*NORMSDIST(-((LN(Inputs!$C$24/($B9*Inputs!$C$23))+(Inputs!$C$25+Inputs!$C$29^2/2)*Inputs!$C$22)/(Inputs!$C$29*SQRT(Inputs!$C$22)))))+Inputs!$C$11/(H$5*Inputs!$C$23)*(Inputs!$C$24*NORMSDIST(((LN(Inputs!$C$24/(H$5*Inputs!$C$23))+(Inputs!$C$25+Inputs!$C$29^2/2)*Inputs!$C$22)/(Inputs!$C$29*SQRT(Inputs!$C$22))))-(H$5*Inputs!$C$23)*Inputs!$C$30*NORMSDIST(((LN(Inputs!$C$24/(H$5*Inputs!$C$23))+(Inputs!$C$25+Inputs!$C$29^2/2)*Inputs!$C$22)/(Inputs!$C$29*SQRT(Inputs!$C$22)))-Inputs!$C$29*SQRT(Inputs!$C$22))) -> 37.580002 | I9: =Inputs!$C$11*Inputs!$C$30-Inputs!$C$11/($B9*Inputs!$C$23)*(($B9*Inputs!$C$23)*Inputs!$C$30*NORMSDIST(-(((LN(Inputs!$C$24/($B9*Inputs!$C$23))+(Inputs!$C$25+Inputs!$C$29^2/2)*Inputs!$C$22)/(Inputs!$C$29*SQRT(Inputs!$C$22)))-Inputs!$C$29*SQRT(Inputs!$C$22)))-Inputs!$C$24*NORMSDIST(-((LN(Inputs!$C$24/($B9*Inputs!$C$23))+(Inputs!$C$25+Inputs!$C$29^2/2)*Inputs!$C$22)/(Inputs!$C$29*SQRT(Inputs!$C$22)))))+Inputs!$C$11/(I$5*Inputs!$C$23)*(Inputs!$C$24*NORMSDIST(((LN(Inputs!$C$24/(I$5*Inputs!$C$23))+(Inputs!$C$25+Inputs!$C$29^2/2)*Inputs!$C$22)/(Inputs!$C$29*SQRT(Inputs!$C$22))))-(I$5*Inputs!$C$23)*Inputs!$C$30*NORMSDIST(((LN(Inputs!$C$24/(I$5*Inputs!$C$23))+(Inputs!$C$25+Inputs!$C$29^2/2)*Inputs!$C$22)/(Inputs!$C$29*SQRT(Inputs!$C$22)))-Inputs!$C$29*SQRT(Inputs!$C$22))) -> 37.241722 | J9: =Inputs!$C$11*Inputs!$C$30-Inputs!$C$11/($B9*Inputs!$C$23)*(($B9*Inputs!$C$23)*Inputs!$C$30*NORMSDIST(-(((LN(Inputs!$C$24/($B9*Inputs!$C$23))+(Inputs!$C$25+Inputs!$C$29^2/2)*Inputs!$C$22)/(Inputs!$C$29*SQRT(Inputs!$C$22)))-Inputs!$C$29*SQRT(Inputs!$C$22)))-Inputs!$C$24*NORMSDIST(-((LN(Inputs!$C$24/($B9*Inputs!$C$23))+(Inputs!$C$25+Inputs!$C$29^2/2)*Inputs!$C$22)/(Inputs!$C$29*SQRT(Inputs!$C$22)))))+Inputs!$C$11/(J$5*Inputs!$C$23)*(Inputs!$C$24*NORMSDIST(((LN(Inputs!$C$24/(J$5*Inputs!$C$23))+(Inputs!$C$25+Inputs!$C$29^2/2)*Inputs!$C$22)/(Inputs!$C$29*SQRT(Inputs!$C$22))))-(J$5*Inputs!$C$23)*Inputs!$C$30*NORMSDIST(((LN(Inputs!$C$24/(J$5*Inputs!$C$23))+(Inputs!$C$25+Inputs!$C$29^2/2)*Inputs!$C$22)/(Inputs!$C$29*SQRT(Inputs!$C$22)))-Inputs!$C$29*SQRT(Inputs!$C$22))) -> 36.936262 | ... O9: =Inputs!$C$11*Inputs!$C$30-Inputs!$C$11/($B9*Inputs!$C$23)*(($B9*Inputs!$C$23)*Inputs!$C$30*NORMSDIST(-(((LN(Inputs!$C$24/($B9*Inputs!$C$23))+(Inputs!$C$25+Inputs!$C$29^2/2)*Inputs!$C$22)/(Inputs!$C$29*SQRT(Inputs!$C$22)))-Inputs!$C$29*SQRT(Inputs!$C$22)))-Inputs!$C$24*NORMSDIST(-((LN(Inputs!$C$24/($B9*Inputs!$C$23))+(Inputs!$C$25+Inputs!$C$29^2/2)*Inputs!$C$22)/(Inputs!$C$29*SQRT(Inputs!$C$22)))))+Inputs!$C$11/(O$5*Inputs!$C$23)*(Inputs!$C$24*NORMSDIST(((LN(Inputs!$C$24/(O$5*Inputs!$C$23))+(Inputs!$C$25+Inputs!$C$29^2/2)*Inputs!$C$22)/(Inputs!$C$29*SQRT(Inputs!$C$22))))-(O$5*Inputs!$C$23)*Inputs!$C$30*NORMSDIST(((LN(Inputs!$C$24/(O$5*Inputs!$C$23))+(Inputs!$C$25+Inputs!$C$29^2/2)*Inputs!$C$22)/(Inputs!$C$29*SQRT(Inputs!$C$22)))-Inputs!$C$29*SQRT(Inputs!$C$22))) -> 35.805133
B10: 0.8 | C10: =Inputs!$C$11*Inputs!$C$30-Inputs!$C$11/($B10*Inputs!$C$23)*(($B10*Inputs!$C$23)*Inputs!$C$30*NORMSDIST(-(((LN(Inputs!$C$24/($B10*Inputs!$C$23))+(Inputs!$C$25+Inputs!$C$29^2/2)*Inputs!$C$22)/(Inputs!$C$29*SQRT(Inputs!$C$22)))-Inputs!$C$29*SQRT(Inputs!$C$22)))-Inputs!$C$24*NORMSDIST(-((LN(Inputs!$C$24/($B10*Inputs!$C$23))+(Inputs!$C$25+Inputs!$C$29^2/2)*Inputs!$C$22)/(Inputs!$C$29*SQRT(Inputs!$C$22)))))+Inputs!$C$11/(C$5*Inputs!$C$23)*(Inputs!$C$24*NORMSDIST(((LN(Inputs!$C$24/(C$5*Inputs!$C$23))+(Inputs!$C$25+Inputs!$C$29^2/2)*Inputs!$C$22)/(Inputs!$C$29*SQRT(Inputs!$C$22))))-(C$5*Inputs!$C$23)*Inputs!$C$30*NORMSDIST(((LN(Inputs!$C$24/(C$5*Inputs!$C$23))+(Inputs!$C$25+Inputs!$C$29^2/2)*Inputs!$C$22)/(Inputs!$C$29*SQRT(Inputs!$C$22)))-Inputs!$C$29*SQRT(Inputs!$C$22))) -> 39.669421 | D10: =Inputs!$C$11*Inputs!$C$30-Inputs!$C$11/($B10*Inputs!$C$23)*(($B10*Inputs!$C$23)*Inputs!$C$30*NORMSDIST(-(((LN(Inputs!$C$24/($B10*Inputs!$C$23))+(Inputs!$C$25+Inputs!$C$29^2/2)*Inputs!$C$22)/(Inputs!$C$29*SQRT(Inputs!$C$22)))-Inputs!$C$29*SQRT(Inputs!$C$22)))-Inputs!$C$24*NORMSDIST(-((LN(Inputs!$C$24/($B10*Inputs!$C$23))+(Inputs!$C$25+Inputs!$C$29^2/2)*Inputs!$C$22)/(Inputs!$C$29*SQRT(Inputs!$C$22)))))+Inputs!$C$11/(D$5*Inputs!$C$23)*(Inputs!$C$24*NORMSDIST(((LN(Inputs!$C$24/(D$5*Inputs!$C$23))+(Inputs!$C$25+Inputs!$C$29^2/2)*Inputs!$C$22)/(Inputs!$C$29*SQRT(Inputs!$C$22))))-(D$5*Inputs!$C$23)*Inputs!$C$30*NORMSDIST(((LN(Inputs!$C$24/(D$5*Inputs!$C$23))+(Inputs!$C$25+Inputs!$C$29^2/2)*Inputs!$C$22)/(Inputs!$C$29*SQRT(Inputs!$C$22)))-Inputs!$C$29*SQRT(Inputs!$C$22))) -> 39.112952 | E10: =Inputs!$C$11*Inputs!$C$30-Inputs!$C$11/($B10*Inputs!$C$23)*(($B10*Inputs!$C$23)*Inputs!$C$30*NORMSDIST(-(((LN(Inputs!$C$24/($B10*Inputs!$C$23))+(Inputs!$C$25+Inputs!$C$29^2/2)*Inputs!$C$22)/(Inputs!$C$29*SQRT(Inputs!$C$22)))-Inputs!$C$29*SQRT(Inputs!$C$22)))-Inputs!$C$24*NORMSDIST(-((LN(Inputs!$C$24/($B10*Inputs!$C$23))+(Inputs!$C$25+Inputs!$C$29^2/2)*Inputs!$C$22)/(Inputs!$C$29*SQRT(Inputs!$C$22)))))+Inputs!$C$11/(E$5*Inputs!$C$23)*(Inputs!$C$24*NORMSDIST(((LN(Inputs!$C$24/(E$5*Inputs!$C$23))+(Inputs!$C$25+Inputs!$C$29^2/2)*Inputs!$C$22)/(Inputs!$C$29*SQRT(Inputs!$C$22))))-(E$5*Inputs!$C$23)*Inputs!$C$30*NORMSDIST(((LN(Inputs!$C$24/(E$5*Inputs!$C$23))+(Inputs!$C$25+Inputs!$C$29^2/2)*Inputs!$C$22)/(Inputs!$C$29*SQRT(Inputs!$C$22)))-Inputs!$C$29*SQRT(Inputs!$C$22))) -> 38.608318 | F10: =Inputs!$C$11*Inputs!$C$30-Inputs!$C$11/($B10*Inputs!$C$23)*(($B10*Inputs!$C$23)*Inputs!$C$30*NORMSDIST(-(((LN(Inputs!$C$24/($B10*Inputs!$C$23))+(Inputs!$C$25+Inputs!$C$29^2/2)*Inputs!$C$22)/(Inputs!$C$29*SQRT(Inputs!$C$22)))-Inputs!$C$29*SQRT(Inputs!$C$22)))-Inputs!$C$24*NORMSDIST(-((LN(Inputs!$C$24/($B10*Inputs!$C$23))+(Inputs!$C$25+Inputs!$C$29^2/2)*Inputs!$C$22)/(Inputs!$C$29*SQRT(Inputs!$C$22)))))+Inputs!$C$11/(F$5*Inputs!$C$23)*(Inputs!$C$24*NORMSDIST(((LN(Inputs!$C$24/(F$5*Inputs!$C$23))+(Inputs!$C$25+Inputs!$C$29^2/2)*Inputs!$C$22)/(Inputs!$C$29*SQRT(Inputs!$C$22))))-(F$5*Inputs!$C$23)*Inputs!$C$30*NORMSDIST(((LN(Inputs!$C$24/(F$5*Inputs!$C$23))+(Inputs!$C$25+Inputs!$C$29^2/2)*Inputs!$C$22)/(Inputs!$C$29*SQRT(Inputs!$C$22)))-Inputs!$C$29*SQRT(Inputs!$C$22))) -> 38.151108 | G10: =Inputs!$C$11*Inputs!$C$30-Inputs!$C$11/($B10*Inputs!$C$23)*(($B10*Inputs!$C$23)*Inputs!$C$30*NORMSDIST(-(((LN(Inputs!$C$24/($B10*Inputs!$C$23))+(Inputs!$C$25+Inputs!$C$29^2/2)*Inputs!$C$22)/(Inputs!$C$29*SQRT(Inputs!$C$22)))-Inputs!$C$29*SQRT(Inputs!$C$22)))-Inputs!$C$24*NORMSDIST(-((LN(Inputs!$C$24/($B10*Inputs!$C$23))+(Inputs!$C$25+Inputs!$C$29^2/2)*Inputs!$C$22)/(Inputs!$C$29*SQRT(Inputs!$C$22)))))+Inputs!$C$11/(G$5*Inputs!$C$23)*(Inputs!$C$24*NORMSDIST(((LN(Inputs!$C$24/(G$5*Inputs!$C$23))+(Inputs!$C$25+Inputs!$C$29^2/2)*Inputs!$C$22)/(Inputs!$C$29*SQRT(Inputs!$C$22))))-(G$5*Inputs!$C$23)*Inputs!$C$30*NORMSDIST(((LN(Inputs!$C$24/(G$5*Inputs!$C$23))+(Inputs!$C$25+Inputs!$C$29^2/2)*Inputs!$C$22)/(Inputs!$C$29*SQRT(Inputs!$C$22)))-Inputs!$C$29*SQRT(Inputs!$C$22))) -> 37.737232 | H10: =Inputs!$C$11*Inputs!$C$30-Inputs!$C$11/($B10*Inputs!$C$23)*(($B10*Inputs!$C$23)*Inputs!$C$30*NORMSDIST(-(((LN(Inputs!$C$24/($B10*Inputs!$C$23))+(Inputs!$C$25+Inputs!$C$29^2/2)*Inputs!$C$22)/(Inputs!$C$29*SQRT(Inputs!$C$22)))-Inputs!$C$29*SQRT(Inputs!$C$22)))-Inputs!$C$24*NORMSDIST(-((LN(Inputs!$C$24/($B10*Inputs!$C$23))+(Inputs!$C$25+Inputs!$C$29^2/2)*Inputs!$C$22)/(Inputs!$C$29*SQRT(Inputs!$C$22)))))+Inputs!$C$11/(H$5*Inputs!$C$23)*(Inputs!$C$24*NORMSDIST(((LN(Inputs!$C$24/(H$5*Inputs!$C$23))+(Inputs!$C$25+Inputs!$C$29^2/2)*Inputs!$C$22)/(Inputs!$C$29*SQRT(Inputs!$C$22))))-(H$5*Inputs!$C$23)*Inputs!$C$30*NORMSDIST(((LN(Inputs!$C$24/(H$5*Inputs!$C$23))+(Inputs!$C$25+Inputs!$C$29^2/2)*Inputs!$C$22)/(Inputs!$C$29*SQRT(Inputs!$C$22)))-Inputs!$C$29*SQRT(Inputs!$C$22))) -> 37.362904 | I10: =Inputs!$C$11*Inputs!$C$30-Inputs!$C$11/($B10*Inputs!$C$23)*(($B10*Inputs!$C$23)*Inputs!$C$30*NORMSDIST(-(((LN(Inputs!$C$24/($B10*Inputs!$C$23))+(Inputs!$C$25+Inputs!$C$29^2/2)*Inputs!$C$22)/(Inputs!$C$29*SQRT(Inputs!$C$22)))-Inputs!$C$29*SQRT(Inputs!$C$22)))-Inputs!$C$24*NORMSDIST(-((LN(Inputs!$C$24/($B10*Inputs!$C$23))+(Inputs!$C$25+Inputs!$C$29^2/2)*Inputs!$C$22)/(Inputs!$C$29*SQRT(Inputs!$C$22)))))+Inputs!$C$11/(I$5*Inputs!$C$23)*(Inputs!$C$24*NORMSDIST(((LN(Inputs!$C$24/(I$5*Inputs!$C$23))+(Inputs!$C$25+Inputs!$C$29^2/2)*Inputs!$C$22)/(Inputs!$C$29*SQRT(Inputs!$C$22))))-(I$5*Inputs!$C$23)*Inputs!$C$30*NORMSDIST(((LN(Inputs!$C$24/(I$5*Inputs!$C$23))+(Inputs!$C$25+Inputs!$C$29^2/2)*Inputs!$C$22)/(Inputs!$C$29*SQRT(Inputs!$C$22)))-Inputs!$C$29*SQRT(Inputs!$C$22))) -> 37.024625 | J10: =Inputs!$C$11*Inputs!$C$30-Inputs!$C$11/($B10*Inputs!$C$23)*(($B10*Inputs!$C$23)*Inputs!$C$30*NORMSDIST(-(((LN(Inputs!$C$24/($B10*Inputs!$C$23))+(Inputs!$C$25+Inputs!$C$29^2/2)*Inputs!$C$22)/(Inputs!$C$29*SQRT(Inputs!$C$22)))-Inputs!$C$29*SQRT(Inputs!$C$22)))-Inputs!$C$24*NORMSDIST(-((LN(Inputs!$C$24/($B10*Inputs!$C$23))+(Inputs!$C$25+Inputs!$C$29^2/2)*Inputs!$C$22)/(Inputs!$C$29*SQRT(Inputs!$C$22)))))+Inputs!$C$11/(J$5*Inputs!$C$23)*(Inputs!$C$24*NORMSDIST(((LN(Inputs!$C$24/(J$5*Inputs!$C$23))+(Inputs!$C$25+Inputs!$C$29^2/2)*Inputs!$C$22)/(Inputs!$C$29*SQRT(Inputs!$C$22))))-(J$5*Inputs!$C$23)*Inputs!$C$30*NORMSDIST(((LN(Inputs!$C$24/(J$5*Inputs!$C$23))+(Inputs!$C$25+Inputs!$C$29^2/2)*Inputs!$C$22)/(Inputs!$C$29*SQRT(Inputs!$C$22)))-Inputs!$C$29*SQRT(Inputs!$C$22))) -> 36.719164 | ... O10: =Inputs!$C$11*Inputs!$C$30-Inputs!$C$11/($B10*Inputs!$C$23)*(($B10*Inputs!$C$23)*Inputs!$C$30*NORMSDIST(-(((LN(Inputs!$C$24/($B10*Inputs!$C$23))+(Inputs!$C$25+Inputs!$C$29^2/2)*Inputs!$C$22)/(Inputs!$C$29*SQRT(Inputs!$C$22)))-Inputs!$C$29*SQRT(Inputs!$C$22)))-Inputs!$C$24*NORMSDIST(-((LN(Inputs!$C$24/($B10*Inputs!$C$23))+(Inputs!$C$25+Inputs!$C$29^2/2)*Inputs!$C$22)/(Inputs!$C$29*SQRT(Inputs!$C$22)))))+Inputs!$C$11/(O$5*Inputs!$C$23)*(Inputs!$C$24*NORMSDIST(((LN(Inputs!$C$24/(O$5*Inputs!$C$23))+(Inputs!$C$25+Inputs!$C$29^2/2)*Inputs!$C$22)/(Inputs!$C$29*SQRT(Inputs!$C$22))))-(O$5*Inputs!$C$23)*Inputs!$C$30*NORMSDIST(((LN(Inputs!$C$24/(O$5*Inputs!$C$23))+(Inputs!$C$25+Inputs!$C$29^2/2)*Inputs!$C$22)/(Inputs!$C$29*SQRT(Inputs!$C$22)))-Inputs!$C$29*SQRT(Inputs!$C$22))) -> 35.588036
B11: 0.825 | C11: =Inputs!$C$11*Inputs!$C$30-Inputs!$C$11/($B11*Inputs!$C$23)*(($B11*Inputs!$C$23)*Inputs!$C$30*NORMSDIST(-(((LN(Inputs!$C$24/($B11*Inputs!$C$23))+(Inputs!$C$25+Inputs!$C$29^2/2)*Inputs!$C$22)/(Inputs!$C$29*SQRT(Inputs!$C$22)))-Inputs!$C$29*SQRT(Inputs!$C$22)))-Inputs!$C$24*NORMSDIST(-((LN(Inputs!$C$24/($B11*Inputs!$C$23))+(Inputs!$C$25+Inputs!$C$29^2/2)*Inputs!$C$22)/(Inputs!$C$29*SQRT(Inputs!$C$22)))))+Inputs!$C$11/(C$5*Inputs!$C$23)*(Inputs!$C$24*NORMSDIST(((LN(Inputs!$C$24/(C$5*Inputs!$C$23))+(Inputs!$C$25+Inputs!$C$29^2/2)*Inputs!$C$22)/(Inputs!$C$29*SQRT(Inputs!$C$22))))-(C$5*Inputs!$C$23)*Inputs!$C$30*NORMSDIST(((LN(Inputs!$C$24/(C$5*Inputs!$C$23))+(Inputs!$C$25+Inputs!$C$29^2/2)*Inputs!$C$22)/(Inputs!$C$29*SQRT(Inputs!$C$22)))-Inputs!$C$29*SQRT(Inputs!$C$22))) -> 39.432816 | D11: =Inputs!$C$11*Inputs!$C$30-Inputs!$C$11/($B11*Inputs!$C$23)*(($B11*Inputs!$C$23)*Inputs!$C$30*NORMSDIST(-(((LN(Inputs!$C$24/($B11*Inputs!$C$23))+(Inputs!$C$25+Inputs!$C$29^2/2)*Inputs!$C$22)/(Inputs!$C$29*SQRT(Inputs!$C$22)))-Inputs!$C$29*SQRT(Inputs!$C$22)))-Inputs!$C$24*NORMSDIST(-((LN(Inputs!$C$24/($B11*Inputs!$C$23))+(Inputs!$C$25+Inputs!$C$29^2/2)*Inputs!$C$22)/(Inputs!$C$29*SQRT(Inputs!$C$22)))))+Inputs!$C$11/(D$5*Inputs!$C$23)*(Inputs!$C$24*NORMSDIST(((LN(Inputs!$C$24/(D$5*Inputs!$C$23))+(Inputs!$C$25+Inputs!$C$29^2/2)*Inputs!$C$22)/(Inputs!$C$29*SQRT(Inputs!$C$22))))-(D$5*Inputs!$C$23)*Inputs!$C$30*NORMSDIST(((LN(Inputs!$C$24/(D$5*Inputs!$C$23))+(Inputs!$C$25+Inputs!$C$29^2/2)*Inputs!$C$22)/(Inputs!$C$29*SQRT(Inputs!$C$22)))-Inputs!$C$29*SQRT(Inputs!$C$22))) -> 38.876347 | E11: =Inputs!$C$11*Inputs!$C$30-Inputs!$C$11/($B11*Inputs!$C$23)*(($B11*Inputs!$C$23)*Inputs!$C$30*NORMSDIST(-(((LN(Inputs!$C$24/($B11*Inputs!$C$23))+(Inputs!$C$25+Inputs!$C$29^2/2)*Inputs!$C$22)/(Inputs!$C$29*SQRT(Inputs!$C$22)))-Inputs!$C$29*SQRT(Inputs!$C$22)))-Inputs!$C$24*NORMSDIST(-((LN(Inputs!$C$24/($B11*Inputs!$C$23))+(Inputs!$C$25+Inputs!$C$29^2/2)*Inputs!$C$22)/(Inputs!$C$29*SQRT(Inputs!$C$22)))))+Inputs!$C$11/(E$5*Inputs!$C$23)*(Inputs!$C$24*NORMSDIST(((LN(Inputs!$C$24/(E$5*Inputs!$C$23))+(Inputs!$C$25+Inputs!$C$29^2/2)*Inputs!$C$22)/(Inputs!$C$29*SQRT(Inputs!$C$22))))-(E$5*Inputs!$C$23)*Inputs!$C$30*NORMSDIST(((LN(Inputs!$C$24/(E$5*Inputs!$C$23))+(Inputs!$C$25+Inputs!$C$29^2/2)*Inputs!$C$22)/(Inputs!$C$29*SQRT(Inputs!$C$22)))-Inputs!$C$29*SQRT(Inputs!$C$22))) -> 38.371713 | F11: =Inputs!$C$11*Inputs!$C$30-Inputs!$C$11/($B11*Inputs!$C$23)*(($B11*Inputs!$C$23)*Inputs!$C$30*NORMSDIST(-(((LN(Inputs!$C$24/($B11*Inputs!$C$23))+(Inputs!$C$25+Inputs!$C$29^2/2)*Inputs!$C$22)/(Inputs!$C$29*SQRT(Inputs!$C$22)))-Inputs!$C$29*SQRT(Inputs!$C$22)))-Inputs!$C$24*NORMSDIST(-((LN(Inputs!$C$24/($B11*Inputs!$C$23))+(Inputs!$C$25+Inputs!$C$29^2/2)*Inputs!$C$22)/(Inputs!$C$29*SQRT(Inputs!$C$22)))))+Inputs!$C$11/(F$5*Inputs!$C$23)*(Inputs!$C$24*NORMSDIST(((LN(Inputs!$C$24/(F$5*Inputs!$C$23))+(Inputs!$C$25+Inputs!$C$29^2/2)*Inputs!$C$22)/(Inputs!$C$29*SQRT(Inputs!$C$22))))-(F$5*Inputs!$C$23)*Inputs!$C$30*NORMSDIST(((LN(Inputs!$C$24/(F$5*Inputs!$C$23))+(Inputs!$C$25+Inputs!$C$29^2/2)*Inputs!$C$22)/(Inputs!$C$29*SQRT(Inputs!$C$22)))-Inputs!$C$29*SQRT(Inputs!$C$22))) -> 37.914503 | G11: =Inputs!$C$11*Inputs!$C$30-Inputs!$C$11/($B11*Inputs!$C$23)*(($B11*Inputs!$C$23)*Inputs!$C$30*NORMSDIST(-(((LN(Inputs!$C$24/($B11*Inputs!$C$23))+(Inputs!$C$25+Inputs!$C$29^2/2)*Inputs!$C$22)/(Inputs!$C$29*SQRT(Inputs!$C$22)))-Inputs!$C$29*SQRT(Inputs!$C$22)))-Inputs!$C$24*NORMSDIST(-((LN(Inputs!$C$24/($B11*Inputs!$C$23))+(Inputs!$C$25+Inputs!$C$29^2/2)*Inputs!$C$22)/(Inputs!$C$29*SQRT(Inputs!$C$22)))))+Inputs!$C$11/(G$5*Inputs!$C$23)*(Inputs!$C$24*NORMSDIST(((LN(Inputs!$C$24/(G$5*Inputs!$C$23))+(Inputs!$C$25+Inputs!$C$29^2/2)*Inputs!$C$22)/(Inputs!$C$29*SQRT(Inputs!$C$22))))-(G$5*Inputs!$C$23)*Inputs!$C$30*NORMSDIST(((LN(Inputs!$C$24/(G$5*Inputs!$C$23))+(Inputs!$C$25+Inputs!$C$29^2/2)*Inputs!$C$22)/(Inputs!$C$29*SQRT(Inputs!$C$22)))-Inputs!$C$29*SQRT(Inputs!$C$22))) -> 37.500627 | H11: =Inputs!$C$11*Inputs!$C$30-Inputs!$C$11/($B11*Inputs!$C$23)*(($B11*Inputs!$C$23)*Inputs!$C$30*NORMSDIST(-(((LN(Inputs!$C$24/($B11*Inputs!$C$23))+(Inputs!$C$25+Inputs!$C$29^2/2)*Inputs!$C$22)/(Inputs!$C$29*SQRT(Inputs!$C$22)))-Inputs!$C$29*SQRT(Inputs!$C$22)))-Inputs!$C$24*NORMSDIST(-((LN(Inputs!$C$24/($B11*Inputs!$C$23))+(Inputs!$C$25+Inputs!$C$29^2/2)*Inputs!$C$22)/(Inputs!$C$29*SQRT(Inputs!$C$22)))))+Inputs!$C$11/(H$5*Inputs!$C$23)*(Inputs!$C$24*NORMSDIST(((LN(Inputs!$C$24/(H$5*Inputs!$C$23))+(Inputs!$C$25+Inputs!$C$29^2/2)*Inputs!$C$22)/(Inputs!$C$29*SQRT(Inputs!$C$22))))-(H$5*Inputs!$C$23)*Inputs!$C$30*NORMSDIST(((LN(Inputs!$C$24/(H$5*Inputs!$C$23))+(Inputs!$C$25+Inputs!$C$29^2/2)*Inputs!$C$22)/(Inputs!$C$29*SQRT(Inputs!$C$22)))-Inputs!$C$29*SQRT(Inputs!$C$22))) -> 37.126299 | I11: =Inputs!$C$11*Inputs!$C$30-Inputs!$C$11/($B11*Inputs!$C$23)*(($B11*Inputs!$C$23)*Inputs!$C$30*NORMSDIST(-(((LN(Inputs!$C$24/($B11*Inputs!$C$23))+(Inputs!$C$25+Inputs!$C$29^2/2)*Inputs!$C$22)/(Inputs!$C$29*SQRT(Inputs!$C$22)))-Inputs!$C$29*SQRT(Inputs!$C$22)))-Inputs!$C$24*NORMSDIST(-((LN(Inputs!$C$24/($B11*Inputs!$C$23))+(Inputs!$C$25+Inputs!$C$29^2/2)*Inputs!$C$22)/(Inputs!$C$29*SQRT(Inputs!$C$22)))))+Inputs!$C$11/(I$5*Inputs!$C$23)*(Inputs!$C$24*NORMSDIST(((LN(Inputs!$C$24/(I$5*Inputs!$C$23))+(Inputs!$C$25+Inputs!$C$29^2/2)*Inputs!$C$22)/(Inputs!$C$29*SQRT(Inputs!$C$22))))-(I$5*Inputs!$C$23)*Inputs!$C$30*NORMSDIST(((LN(Inputs!$C$24/(I$5*Inputs!$C$23))+(Inputs!$C$25+Inputs!$C$29^2/2)*Inputs!$C$22)/(Inputs!$C$29*SQRT(Inputs!$C$22)))-Inputs!$C$29*SQRT(Inputs!$C$22))) -> 36.78802 | J11: =Inputs!$C$11*Inputs!$C$30-Inputs!$C$11/($B11*Inputs!$C$23)*(($B11*Inputs!$C$23)*Inputs!$C$30*NORMSDIST(-(((LN(Inputs!$C$24/($B11*Inputs!$C$23))+(Inputs!$C$25+Inputs!$C$29^2/2)*Inputs!$C$22)/(Inputs!$C$29*SQRT(Inputs!$C$22)))-Inputs!$C$29*SQRT(Inputs!$C$22)))-Inputs!$C$24*NORMSDIST(-((LN(Inputs!$C$24/($B11*Inputs!$C$23))+(Inputs!$C$25+Inputs!$C$29^2/2)*Inputs!$C$22)/(Inputs!$C$29*SQRT(Inputs!$C$22)))))+Inputs!$C$11/(J$5*Inputs!$C$23)*(Inputs!$C$24*NORMSDIST(((LN(Inputs!$C$24/(J$5*Inputs!$C$23))+(Inputs!$C$25+Inputs!$C$29^2/2)*Inputs!$C$22)/(Inputs!$C$29*SQRT(Inputs!$C$22))))-(J$5*Inputs!$C$23)*Inputs!$C$30*NORMSDIST(((LN(Inputs!$C$24/(J$5*Inputs!$C$23))+(Inputs!$C$25+Inputs!$C$29^2/2)*Inputs!$C$22)/(Inputs!$C$29*SQRT(Inputs!$C$22)))-Inputs!$C$29*SQRT(Inputs!$C$22))) -> 36.482559 | ... O11: =Inputs!$C$11*Inputs!$C$30-Inputs!$C$11/($B11*Inputs!$C$23)*(($B11*Inputs!$C$23)*Inputs!$C$30*NORMSDIST(-(((LN(Inputs!$C$24/($B11*Inputs!$C$23))+(Inputs!$C$25+Inputs!$C$29^2/2)*Inputs!$C$22)/(Inputs!$C$29*SQRT(Inputs!$C$22)))-Inputs!$C$29*SQRT(Inputs!$C$22)))-Inputs!$C$24*NORMSDIST(-((LN(Inputs!$C$24/($B11*Inputs!$C$23))+(Inputs!$C$25+Inputs!$C$29^2/2)*Inputs!$C$22)/(Inputs!$C$29*SQRT(Inputs!$C$22)))))+Inputs!$C$11/(O$5*Inputs!$C$23)*(Inputs!$C$24*NORMSDIST(((LN(Inputs!$C$24/(O$5*Inputs!$C$23))+(Inputs!$C$25+Inputs!$C$29^2/2)*Inputs!$C$22)/(Inputs!$C$29*SQRT(Inputs!$C$22))))-(O$5*Inputs!$C$23)*Inputs!$C$30*NORMSDIST(((LN(Inputs!$C$24/(O$5*Inputs!$C$23))+(Inputs!$C$25+Inputs!$C$29^2/2)*Inputs!$C$22)/(Inputs!$C$29*SQRT(Inputs!$C$22)))-Inputs!$C$29*SQRT(Inputs!$C$22))) -> 35.351431
B12: 0.85 | C12: =Inputs!$C$11*Inputs!$C$30-Inputs!$C$11/($B12*Inputs!$C$23)*(($B12*Inputs!$C$23)*Inputs!$C$30*NORMSDIST(-(((LN(Inputs!$C$24/($B12*Inputs!$C$23))+(Inputs!$C$25+Inputs!$C$29^2/2)*Inputs!$C$22)/(Inputs!$C$29*SQRT(Inputs!$C$22)))-Inputs!$C$29*SQRT(Inputs!$C$22)))-Inputs!$C$24*NORMSDIST(-((LN(Inputs!$C$24/($B12*Inputs!$C$23))+(Inputs!$C$25+Inputs!$C$29^2/2)*Inputs!$C$22)/(Inputs!$C$29*SQRT(Inputs!$C$22)))))+Inputs!$C$11/(C$5*Inputs!$C$23)*(Inputs!$C$24*NORMSDIST(((LN(Inputs!$C$24/(C$5*Inputs!$C$23))+(Inputs!$C$25+Inputs!$C$29^2/2)*Inputs!$C$22)/(Inputs!$C$29*SQRT(Inputs!$C$22))))-(C$5*Inputs!$C$23)*Inputs!$C$30*NORMSDIST(((LN(Inputs!$C$24/(C$5*Inputs!$C$23))+(Inputs!$C$25+Inputs!$C$29^2/2)*Inputs!$C$22)/(Inputs!$C$29*SQRT(Inputs!$C$22)))-Inputs!$C$29*SQRT(Inputs!$C$22))) -> 39.177446 | D12: =Inputs!$C$11*Inputs!$C$30-Inputs!$C$11/($B12*Inputs!$C$23)*(($B12*Inputs!$C$23)*Inputs!$C$30*NORMSDIST(-(((LN(Inputs!$C$24/($B12*Inputs!$C$23))+(Inputs!$C$25+Inputs!$C$29^2/2)*Inputs!$C$22)/(Inputs!$C$29*SQRT(Inputs!$C$22)))-Inputs!$C$29*SQRT(Inputs!$C$22)))-Inputs!$C$24*NORMSDIST(-((LN(Inputs!$C$24/($B12*Inputs!$C$23))+(Inputs!$C$25+Inputs!$C$29^2/2)*Inputs!$C$22)/(Inputs!$C$29*SQRT(Inputs!$C$22)))))+Inputs!$C$11/(D$5*Inputs!$C$23)*(Inputs!$C$24*NORMSDIST(((LN(Inputs!$C$24/(D$5*Inputs!$C$23))+(Inputs!$C$25+Inputs!$C$29^2/2)*Inputs!$C$22)/(Inputs!$C$29*SQRT(Inputs!$C$22))))-(D$5*Inputs!$C$23)*Inputs!$C$30*NORMSDIST(((LN(Inputs!$C$24/(D$5*Inputs!$C$23))+(Inputs!$C$25+Inputs!$C$29^2/2)*Inputs!$C$22)/(Inputs!$C$29*SQRT(Inputs!$C$22)))-Inputs!$C$29*SQRT(Inputs!$C$22))) -> 38.620977 | E12: =Inputs!$C$11*Inputs!$C$30-Inputs!$C$11/($B12*Inputs!$C$23)*(($B12*Inputs!$C$23)*Inputs!$C$30*NORMSDIST(-(((LN(Inputs!$C$24/($B12*Inputs!$C$23))+(Inputs!$C$25+Inputs!$C$29^2/2)*Inputs!$C$22)/(Inputs!$C$29*SQRT(Inputs!$C$22)))-Inputs!$C$29*SQRT(Inputs!$C$22)))-Inputs!$C$24*NORMSDIST(-((LN(Inputs!$C$24/($B12*Inputs!$C$23))+(Inputs!$C$25+Inputs!$C$29^2/2)*Inputs!$C$22)/(Inputs!$C$29*SQRT(Inputs!$C$22)))))+Inputs!$C$11/(E$5*Inputs!$C$23)*(Inputs!$C$24*NORMSDIST(((LN(Inputs!$C$24/(E$5*Inputs!$C$23))+(Inputs!$C$25+Inputs!$C$29^2/2)*Inputs!$C$22)/(Inputs!$C$29*SQRT(Inputs!$C$22))))-(E$5*Inputs!$C$23)*Inputs!$C$30*NORMSDIST(((LN(Inputs!$C$24/(E$5*Inputs!$C$23))+(Inputs!$C$25+Inputs!$C$29^2/2)*Inputs!$C$22)/(Inputs!$C$29*SQRT(Inputs!$C$22)))-Inputs!$C$29*SQRT(Inputs!$C$22))) -> 38.116343 | F12: =Inputs!$C$11*Inputs!$C$30-Inputs!$C$11/($B12*Inputs!$C$23)*(($B12*Inputs!$C$23)*Inputs!$C$30*NORMSDIST(-(((LN(Inputs!$C$24/($B12*Inputs!$C$23))+(Inputs!$C$25+Inputs!$C$29^2/2)*Inputs!$C$22)/(Inputs!$C$29*SQRT(Inputs!$C$22)))-Inputs!$C$29*SQRT(Inputs!$C$22)))-Inputs!$C$24*NORMSDIST(-((LN(Inputs!$C$24/($B12*Inputs!$C$23))+(Inputs!$C$25+Inputs!$C$29^2/2)*Inputs!$C$22)/(Inputs!$C$29*SQRT(Inputs!$C$22)))))+Inputs!$C$11/(F$5*Inputs!$C$23)*(Inputs!$C$24*NORMSDIST(((LN(Inputs!$C$24/(F$5*Inputs!$C$23))+(Inputs!$C$25+Inputs!$C$29^2/2)*Inputs!$C$22)/(Inputs!$C$29*SQRT(Inputs!$C$22))))-(F$5*Inputs!$C$23)*Inputs!$C$30*NORMSDIST(((LN(Inputs!$C$24/(F$5*Inputs!$C$23))+(Inputs!$C$25+Inputs!$C$29^2/2)*Inputs!$C$22)/(Inputs!$C$29*SQRT(Inputs!$C$22)))-Inputs!$C$29*SQRT(Inputs!$C$22))) -> 37.659133 | G12: =Inputs!$C$11*Inputs!$C$30-Inputs!$C$11/($B12*Inputs!$C$23)*(($B12*Inputs!$C$23)*Inputs!$C$30*NORMSDIST(-(((LN(Inputs!$C$24/($B12*Inputs!$C$23))+(Inputs!$C$25+Inputs!$C$29^2/2)*Inputs!$C$22)/(Inputs!$C$29*SQRT(Inputs!$C$22)))-Inputs!$C$29*SQRT(Inputs!$C$22)))-Inputs!$C$24*NORMSDIST(-((LN(Inputs!$C$24/($B12*Inputs!$C$23))+(Inputs!$C$25+Inputs!$C$29^2/2)*Inputs!$C$22)/(Inputs!$C$29*SQRT(Inputs!$C$22)))))+Inputs!$C$11/(G$5*Inputs!$C$23)*(Inputs!$C$24*NORMSDIST(((LN(Inputs!$C$24/(G$5*Inputs!$C$23))+(Inputs!$C$25+Inputs!$C$29^2/2)*Inputs!$C$22)/(Inputs!$C$29*SQRT(Inputs!$C$22))))-(G$5*Inputs!$C$23)*Inputs!$C$30*NORMSDIST(((LN(Inputs!$C$24/(G$5*Inputs!$C$23))+(Inputs!$C$25+Inputs!$C$29^2/2)*Inputs!$C$22)/(Inputs!$C$29*SQRT(Inputs!$C$22)))-Inputs!$C$29*SQRT(Inputs!$C$22))) -> 37.245257 | H12: =Inputs!$C$11*Inputs!$C$30-Inputs!$C$11/($B12*Inputs!$C$23)*(($B12*Inputs!$C$23)*Inputs!$C$30*NORMSDIST(-(((LN(Inputs!$C$24/($B12*Inputs!$C$23))+(Inputs!$C$25+Inputs!$C$29^2/2)*Inputs!$C$22)/(Inputs!$C$29*SQRT(Inputs!$C$22)))-Inputs!$C$29*SQRT(Inputs!$C$22)))-Inputs!$C$24*NORMSDIST(-((LN(Inputs!$C$24/($B12*Inputs!$C$23))+(Inputs!$C$25+Inputs!$C$29^2/2)*Inputs!$C$22)/(Inputs!$C$29*SQRT(Inputs!$C$22)))))+Inputs!$C$11/(H$5*Inputs!$C$23)*(Inputs!$C$24*NORMSDIST(((LN(Inputs!$C$24/(H$5*Inputs!$C$23))+(Inputs!$C$25+Inputs!$C$29^2/2)*Inputs!$C$22)/(Inputs!$C$29*SQRT(Inputs!$C$22))))-(H$5*Inputs!$C$23)*Inputs!$C$30*NORMSDIST(((LN(Inputs!$C$24/(H$5*Inputs!$C$23))+(Inputs!$C$25+Inputs!$C$29^2/2)*Inputs!$C$22)/(Inputs!$C$29*SQRT(Inputs!$C$22)))-Inputs!$C$29*SQRT(Inputs!$C$22))) -> 36.870929 | I12: =Inputs!$C$11*Inputs!$C$30-Inputs!$C$11/($B12*Inputs!$C$23)*(($B12*Inputs!$C$23)*Inputs!$C$30*NORMSDIST(-(((LN(Inputs!$C$24/($B12*Inputs!$C$23))+(Inputs!$C$25+Inputs!$C$29^2/2)*Inputs!$C$22)/(Inputs!$C$29*SQRT(Inputs!$C$22)))-Inputs!$C$29*SQRT(Inputs!$C$22)))-Inputs!$C$24*NORMSDIST(-((LN(Inputs!$C$24/($B12*Inputs!$C$23))+(Inputs!$C$25+Inputs!$C$29^2/2)*Inputs!$C$22)/(Inputs!$C$29*SQRT(Inputs!$C$22)))))+Inputs!$C$11/(I$5*Inputs!$C$23)*(Inputs!$C$24*NORMSDIST(((LN(Inputs!$C$24/(I$5*Inputs!$C$23))+(Inputs!$C$25+Inputs!$C$29^2/2)*Inputs!$C$22)/(Inputs!$C$29*SQRT(Inputs!$C$22))))-(I$5*Inputs!$C$23)*Inputs!$C$30*NORMSDIST(((LN(Inputs!$C$24/(I$5*Inputs!$C$23))+(Inputs!$C$25+Inputs!$C$29^2/2)*Inputs!$C$22)/(Inputs!$C$29*SQRT(Inputs!$C$22)))-Inputs!$C$29*SQRT(Inputs!$C$22))) -> 36.53265 | J12: =Inputs!$C$11*Inputs!$C$30-Inputs!$C$11/($B12*Inputs!$C$23)*(($B12*Inputs!$C$23)*Inputs!$C$30*NORMSDIST(-(((LN(Inputs!$C$24/($B12*Inputs!$C$23))+(Inputs!$C$25+Inputs!$C$29^2/2)*Inputs!$C$22)/(Inputs!$C$29*SQRT(Inputs!$C$22)))-Inputs!$C$29*SQRT(Inputs!$C$22)))-Inputs!$C$24*NORMSDIST(-((LN(Inputs!$C$24/($B12*Inputs!$C$23))+(Inputs!$C$25+Inputs!$C$29^2/2)*Inputs!$C$22)/(Inputs!$C$29*SQRT(Inputs!$C$22)))))+Inputs!$C$11/(J$5*Inputs!$C$23)*(Inputs!$C$24*NORMSDIST(((LN(Inputs!$C$24/(J$5*Inputs!$C$23))+(Inputs!$C$25+Inputs!$C$29^2/2)*Inputs!$C$22)/(Inputs!$C$29*SQRT(Inputs!$C$22))))-(J$5*Inputs!$C$23)*Inputs!$C$30*NORMSDIST(((LN(Inputs!$C$24/(J$5*Inputs!$C$23))+(Inputs!$C$25+Inputs!$C$29^2/2)*Inputs!$C$22)/(Inputs!$C$29*SQRT(Inputs!$C$22)))-Inputs!$C$29*SQRT(Inputs!$C$22))) -> 36.227189 | ... O12: =Inputs!$C$11*Inputs!$C$30-Inputs!$C$11/($B12*Inputs!$C$23)*(($B12*Inputs!$C$23)*Inputs!$C$30*NORMSDIST(-(((LN(Inputs!$C$24/($B12*Inputs!$C$23))+(Inputs!$C$25+Inputs!$C$29^2/2)*Inputs!$C$22)/(Inputs!$C$29*SQRT(Inputs!$C$22)))-Inputs!$C$29*SQRT(Inputs!$C$22)))-Inputs!$C$24*NORMSDIST(-((LN(Inputs!$C$24/($B12*Inputs!$C$23))+(Inputs!$C$25+Inputs!$C$29^2/2)*Inputs!$C$22)/(Inputs!$C$29*SQRT(Inputs!$C$22)))))+Inputs!$C$11/(O$5*Inputs!$C$23)*(Inputs!$C$24*NORMSDIST(((LN(Inputs!$C$24/(O$5*Inputs!$C$23))+(Inputs!$C$25+Inputs!$C$29^2/2)*Inputs!$C$22)/(Inputs!$C$29*SQRT(Inputs!$C$22))))-(O$5*Inputs!$C$23)*Inputs!$C$30*NORMSDIST(((LN(Inputs!$C$24/(O$5*Inputs!$C$23))+(Inputs!$C$25+Inputs!$C$29^2/2)*Inputs!$C$22)/(Inputs!$C$29*SQRT(Inputs!$C$22)))-Inputs!$C$29*SQRT(Inputs!$C$22))) -> 35.096061
B13: 0.875 | C13: =Inputs!$C$11*Inputs!$C$30-Inputs!$C$11/($B13*Inputs!$C$23)*(($B13*Inputs!$C$23)*Inputs!$C$30*NORMSDIST(-(((LN(Inputs!$C$24/($B13*Inputs!$C$23))+(Inputs!$C$25+Inputs!$C$29^2/2)*Inputs!$C$22)/(Inputs!$C$29*SQRT(Inputs!$C$22)))-Inputs!$C$29*SQRT(Inputs!$C$22)))-Inputs!$C$24*NORMSDIST(-((LN(Inputs!$C$24/($B13*Inputs!$C$23))+(Inputs!$C$25+Inputs!$C$29^2/2)*Inputs!$C$22)/(Inputs!$C$29*SQRT(Inputs!$C$22)))))+Inputs!$C$11/(C$5*Inputs!$C$23)*(Inputs!$C$24*NORMSDIST(((LN(Inputs!$C$24/(C$5*Inputs!$C$23))+(Inputs!$C$25+Inputs!$C$29^2/2)*Inputs!$C$22)/(Inputs!$C$29*SQRT(Inputs!$C$22))))-(C$5*Inputs!$C$23)*Inputs!$C$30*NORMSDIST(((LN(Inputs!$C$24/(C$5*Inputs!$C$23))+(Inputs!$C$25+Inputs!$C$29^2/2)*Inputs!$C$22)/(Inputs!$C$29*SQRT(Inputs!$C$22)))-Inputs!$C$29*SQRT(Inputs!$C$22))) -> 38.904252 | D13: =Inputs!$C$11*Inputs!$C$30-Inputs!$C$11/($B13*Inputs!$C$23)*(($B13*Inputs!$C$23)*Inputs!$C$30*NORMSDIST(-(((LN(Inputs!$C$24/($B13*Inputs!$C$23))+(Inputs!$C$25+Inputs!$C$29^2/2)*Inputs!$C$22)/(Inputs!$C$29*SQRT(Inputs!$C$22)))-Inputs!$C$29*SQRT(Inputs!$C$22)))-Inputs!$C$24*NORMSDIST(-((LN(Inputs!$C$24/($B13*Inputs!$C$23))+(Inputs!$C$25+Inputs!$C$29^2/2)*Inputs!$C$22)/(Inputs!$C$29*SQRT(Inputs!$C$22)))))+Inputs!$C$11/(D$5*Inputs!$C$23)*(Inputs!$C$24*NORMSDIST(((LN(Inputs!$C$24/(D$5*Inputs!$C$23))+(Inputs!$C$25+Inputs!$C$29^2/2)*Inputs!$C$22)/(Inputs!$C$29*SQRT(Inputs!$C$22))))-(D$5*Inputs!$C$23)*Inputs!$C$30*NORMSDIST(((LN(Inputs!$C$24/(D$5*Inputs!$C$23))+(Inputs!$C$25+Inputs!$C$29^2/2)*Inputs!$C$22)/(Inputs!$C$29*SQRT(Inputs!$C$22)))-Inputs!$C$29*SQRT(Inputs!$C$22))) -> 38.347782 | E13: =Inputs!$C$11*Inputs!$C$30-Inputs!$C$11/($B13*Inputs!$C$23)*(($B13*Inputs!$C$23)*Inputs!$C$30*NORMSDIST(-(((LN(Inputs!$C$24/($B13*Inputs!$C$23))+(Inputs!$C$25+Inputs!$C$29^2/2)*Inputs!$C$22)/(Inputs!$C$29*SQRT(Inputs!$C$22)))-Inputs!$C$29*SQRT(Inputs!$C$22)))-Inputs!$C$24*NORMSDIST(-((LN(Inputs!$C$24/($B13*Inputs!$C$23))+(Inputs!$C$25+Inputs!$C$29^2/2)*Inputs!$C$22)/(Inputs!$C$29*SQRT(Inputs!$C$22)))))+Inputs!$C$11/(E$5*Inputs!$C$23)*(Inputs!$C$24*NORMSDIST(((LN(Inputs!$C$24/(E$5*Inputs!$C$23))+(Inputs!$C$25+Inputs!$C$29^2/2)*Inputs!$C$22)/(Inputs!$C$29*SQRT(Inputs!$C$22))))-(E$5*Inputs!$C$23)*Inputs!$C$30*NORMSDIST(((LN(Inputs!$C$24/(E$5*Inputs!$C$23))+(Inputs!$C$25+Inputs!$C$29^2/2)*Inputs!$C$22)/(Inputs!$C$29*SQRT(Inputs!$C$22)))-Inputs!$C$29*SQRT(Inputs!$C$22))) -> 37.843148 | F13: =Inputs!$C$11*Inputs!$C$30-Inputs!$C$11/($B13*Inputs!$C$23)*(($B13*Inputs!$C$23)*Inputs!$C$30*NORMSDIST(-(((LN(Inputs!$C$24/($B13*Inputs!$C$23))+(Inputs!$C$25+Inputs!$C$29^2/2)*Inputs!$C$22)/(Inputs!$C$29*SQRT(Inputs!$C$22)))-Inputs!$C$29*SQRT(Inputs!$C$22)))-Inputs!$C$24*NORMSDIST(-((LN(Inputs!$C$24/($B13*Inputs!$C$23))+(Inputs!$C$25+Inputs!$C$29^2/2)*Inputs!$C$22)/(Inputs!$C$29*SQRT(Inputs!$C$22)))))+Inputs!$C$11/(F$5*Inputs!$C$23)*(Inputs!$C$24*NORMSDIST(((LN(Inputs!$C$24/(F$5*Inputs!$C$23))+(Inputs!$C$25+Inputs!$C$29^2/2)*Inputs!$C$22)/(Inputs!$C$29*SQRT(Inputs!$C$22))))-(F$5*Inputs!$C$23)*Inputs!$C$30*NORMSDIST(((LN(Inputs!$C$24/(F$5*Inputs!$C$23))+(Inputs!$C$25+Inputs!$C$29^2/2)*Inputs!$C$22)/(Inputs!$C$29*SQRT(Inputs!$C$22)))-Inputs!$C$29*SQRT(Inputs!$C$22))) -> 37.385938 | G13: =Inputs!$C$11*Inputs!$C$30-Inputs!$C$11/($B13*Inputs!$C$23)*(($B13*Inputs!$C$23)*Inputs!$C$30*NORMSDIST(-(((LN(Inputs!$C$24/($B13*Inputs!$C$23))+(Inputs!$C$25+Inputs!$C$29^2/2)*Inputs!$C$22)/(Inputs!$C$29*SQRT(Inputs!$C$22)))-Inputs!$C$29*SQRT(Inputs!$C$22)))-Inputs!$C$24*NORMSDIST(-((LN(Inputs!$C$24/($B13*Inputs!$C$23))+(Inputs!$C$25+Inputs!$C$29^2/2)*Inputs!$C$22)/(Inputs!$C$29*SQRT(Inputs!$C$22)))))+Inputs!$C$11/(G$5*Inputs!$C$23)*(Inputs!$C$24*NORMSDIST(((LN(Inputs!$C$24/(G$5*Inputs!$C$23))+(Inputs!$C$25+Inputs!$C$29^2/2)*Inputs!$C$22)/(Inputs!$C$29*SQRT(Inputs!$C$22))))-(G$5*Inputs!$C$23)*Inputs!$C$30*NORMSDIST(((LN(Inputs!$C$24/(G$5*Inputs!$C$23))+(Inputs!$C$25+Inputs!$C$29^2/2)*Inputs!$C$22)/(Inputs!$C$29*SQRT(Inputs!$C$22)))-Inputs!$C$29*SQRT(Inputs!$C$22))) -> 36.972062 | H13: =Inputs!$C$11*Inputs!$C$30-Inputs!$C$11/($B13*Inputs!$C$23)*(($B13*Inputs!$C$23)*Inputs!$C$30*NORMSDIST(-(((LN(Inputs!$C$24/($B13*Inputs!$C$23))+(Inputs!$C$25+Inputs!$C$29^2/2)*Inputs!$C$22)/(Inputs!$C$29*SQRT(Inputs!$C$22)))-Inputs!$C$29*SQRT(Inputs!$C$22)))-Inputs!$C$24*NORMSDIST(-((LN(Inputs!$C$24/($B13*Inputs!$C$23))+(Inputs!$C$25+Inputs!$C$29^2/2)*Inputs!$C$22)/(Inputs!$C$29*SQRT(Inputs!$C$22)))))+Inputs!$C$11/(H$5*Inputs!$C$23)*(Inputs!$C$24*NORMSDIST(((LN(Inputs!$C$24/(H$5*Inputs!$C$23))+(Inputs!$C$25+Inputs!$C$29^2/2)*Inputs!$C$22)/(Inputs!$C$29*SQRT(Inputs!$C$22))))-(H$5*Inputs!$C$23)*Inputs!$C$30*NORMSDIST(((LN(Inputs!$C$24/(H$5*Inputs!$C$23))+(Inputs!$C$25+Inputs!$C$29^2/2)*Inputs!$C$22)/(Inputs!$C$29*SQRT(Inputs!$C$22)))-Inputs!$C$29*SQRT(Inputs!$C$22))) -> 36.597735 | I13: =Inputs!$C$11*Inputs!$C$30-Inputs!$C$11/($B13*Inputs!$C$23)*(($B13*Inputs!$C$23)*Inputs!$C$30*NORMSDIST(-(((LN(Inputs!$C$24/($B13*Inputs!$C$23))+(Inputs!$C$25+Inputs!$C$29^2/2)*Inputs!$C$22)/(Inputs!$C$29*SQRT(Inputs!$C$22)))-Inputs!$C$29*SQRT(Inputs!$C$22)))-Inputs!$C$24*NORMSDIST(-((LN(Inputs!$C$24/($B13*Inputs!$C$23))+(Inputs!$C$25+Inputs!$C$29^2/2)*Inputs!$C$22)/(Inputs!$C$29*SQRT(Inputs!$C$22)))))+Inputs!$C$11/(I$5*Inputs!$C$23)*(Inputs!$C$24*NORMSDIST(((LN(Inputs!$C$24/(I$5*Inputs!$C$23))+(Inputs!$C$25+Inputs!$C$29^2/2)*Inputs!$C$22)/(Inputs!$C$29*SQRT(Inputs!$C$22))))-(I$5*Inputs!$C$23)*Inputs!$C$30*NORMSDIST(((LN(Inputs!$C$24/(I$5*Inputs!$C$23))+(Inputs!$C$25+Inputs!$C$29^2/2)*Inputs!$C$22)/(Inputs!$C$29*SQRT(Inputs!$C$22)))-Inputs!$C$29*SQRT(Inputs!$C$22))) -> 36.259455 | J13: =Inputs!$C$11*Inputs!$C$30-Inputs!$C$11/($B13*Inputs!$C$23)*(($B13*Inputs!$C$23)*Inputs!$C$30*NORMSDIST(-(((LN(Inputs!$C$24/($B13*Inputs!$C$23))+(Inputs!$C$25+Inputs!$C$29^2/2)*Inputs!$C$22)/(Inputs!$C$29*SQRT(Inputs!$C$22)))-Inputs!$C$29*SQRT(Inputs!$C$22)))-Inputs!$C$24*NORMSDIST(-((LN(Inputs!$C$24/($B13*Inputs!$C$23))+(Inputs!$C$25+Inputs!$C$29^2/2)*Inputs!$C$22)/(Inputs!$C$29*SQRT(Inputs!$C$22)))))+Inputs!$C$11/(J$5*Inputs!$C$23)*(Inputs!$C$24*NORMSDIST(((LN(Inputs!$C$24/(J$5*Inputs!$C$23))+(Inputs!$C$25+Inputs!$C$29^2/2)*Inputs!$C$22)/(Inputs!$C$29*SQRT(Inputs!$C$22))))-(J$5*Inputs!$C$23)*Inputs!$C$30*NORMSDIST(((LN(Inputs!$C$24/(J$5*Inputs!$C$23))+(Inputs!$C$25+Inputs!$C$29^2/2)*Inputs!$C$22)/(Inputs!$C$29*SQRT(Inputs!$C$22)))-Inputs!$C$29*SQRT(Inputs!$C$22))) -> 35.953995 | ... O13: =Inputs!$C$11*Inputs!$C$30-Inputs!$C$11/($B13*Inputs!$C$23)*(($B13*Inputs!$C$23)*Inputs!$C$30*NORMSDIST(-(((LN(Inputs!$C$24/($B13*Inputs!$C$23))+(Inputs!$C$25+Inputs!$C$29^2/2)*Inputs!$C$22)/(Inputs!$C$29*SQRT(Inputs!$C$22)))-Inputs!$C$29*SQRT(Inputs!$C$22)))-Inputs!$C$24*NORMSDIST(-((LN(Inputs!$C$24/($B13*Inputs!$C$23))+(Inputs!$C$25+Inputs!$C$29^2/2)*Inputs!$C$22)/(Inputs!$C$29*SQRT(Inputs!$C$22)))))+Inputs!$C$11/(O$5*Inputs!$C$23)*(Inputs!$C$24*NORMSDIST(((LN(Inputs!$C$24/(O$5*Inputs!$C$23))+(Inputs!$C$25+Inputs!$C$29^2/2)*Inputs!$C$22)/(Inputs!$C$29*SQRT(Inputs!$C$22))))-(O$5*Inputs!$C$23)*Inputs!$C$30*NORMSDIST(((LN(Inputs!$C$24/(O$5*Inputs!$C$23))+(Inputs!$C$25+Inputs!$C$29^2/2)*Inputs!$C$22)/(Inputs!$C$29*SQRT(Inputs!$C$22)))-Inputs!$C$29*SQRT(Inputs!$C$22))) -> 34.822866
B14: 0.9 | C14: =Inputs!$C$11*Inputs!$C$30-Inputs!$C$11/($B14*Inputs!$C$23)*(($B14*Inputs!$C$23)*Inputs!$C$30*NORMSDIST(-(((LN(Inputs!$C$24/($B14*Inputs!$C$23))+(Inputs!$C$25+Inputs!$C$29^2/2)*Inputs!$C$22)/(Inputs!$C$29*SQRT(Inputs!$C$22)))-Inputs!$C$29*SQRT(Inputs!$C$22)))-Inputs!$C$24*NORMSDIST(-((LN(Inputs!$C$24/($B14*Inputs!$C$23))+(Inputs!$C$25+Inputs!$C$29^2/2)*Inputs!$C$22)/(Inputs!$C$29*SQRT(Inputs!$C$22)))))+Inputs!$C$11/(C$5*Inputs!$C$23)*(Inputs!$C$24*NORMSDIST(((LN(Inputs!$C$24/(C$5*Inputs!$C$23))+(Inputs!$C$25+Inputs!$C$29^2/2)*Inputs!$C$22)/(Inputs!$C$29*SQRT(Inputs!$C$22))))-(C$5*Inputs!$C$23)*Inputs!$C$30*NORMSDIST(((LN(Inputs!$C$24/(C$5*Inputs!$C$23))+(Inputs!$C$25+Inputs!$C$29^2/2)*Inputs!$C$22)/(Inputs!$C$29*SQRT(Inputs!$C$22)))-Inputs!$C$29*SQRT(Inputs!$C$22))) -> 38.614336 | D14: =Inputs!$C$11*Inputs!$C$30-Inputs!$C$11/($B14*Inputs!$C$23)*(($B14*Inputs!$C$23)*Inputs!$C$30*NORMSDIST(-(((LN(Inputs!$C$24/($B14*Inputs!$C$23))+(Inputs!$C$25+Inputs!$C$29^2/2)*Inputs!$C$22)/(Inputs!$C$29*SQRT(Inputs!$C$22)))-Inputs!$C$29*SQRT(Inputs!$C$22)))-Inputs!$C$24*NORMSDIST(-((LN(Inputs!$C$24/($B14*Inputs!$C$23))+(Inputs!$C$25+Inputs!$C$29^2/2)*Inputs!$C$22)/(Inputs!$C$29*SQRT(Inputs!$C$22)))))+Inputs!$C$11/(D$5*Inputs!$C$23)*(Inputs!$C$24*NORMSDIST(((LN(Inputs!$C$24/(D$5*Inputs!$C$23))+(Inputs!$C$25+Inputs!$C$29^2/2)*Inputs!$C$22)/(Inputs!$C$29*SQRT(Inputs!$C$22))))-(D$5*Inputs!$C$23)*Inputs!$C$30*NORMSDIST(((LN(Inputs!$C$24/(D$5*Inputs!$C$23))+(Inputs!$C$25+Inputs!$C$29^2/2)*Inputs!$C$22)/(Inputs!$C$29*SQRT(Inputs!$C$22)))-Inputs!$C$29*SQRT(Inputs!$C$22))) -> 38.057867 | E14: =Inputs!$C$11*Inputs!$C$30-Inputs!$C$11/($B14*Inputs!$C$23)*(($B14*Inputs!$C$23)*Inputs!$C$30*NORMSDIST(-(((LN(Inputs!$C$24/($B14*Inputs!$C$23))+(Inputs!$C$25+Inputs!$C$29^2/2)*Inputs!$C$22)/(Inputs!$C$29*SQRT(Inputs!$C$22)))-Inputs!$C$29*SQRT(Inputs!$C$22)))-Inputs!$C$24*NORMSDIST(-((LN(Inputs!$C$24/($B14*Inputs!$C$23))+(Inputs!$C$25+Inputs!$C$29^2/2)*Inputs!$C$22)/(Inputs!$C$29*SQRT(Inputs!$C$22)))))+Inputs!$C$11/(E$5*Inputs!$C$23)*(Inputs!$C$24*NORMSDIST(((LN(Inputs!$C$24/(E$5*Inputs!$C$23))+(Inputs!$C$25+Inputs!$C$29^2/2)*Inputs!$C$22)/(Inputs!$C$29*SQRT(Inputs!$C$22))))-(E$5*Inputs!$C$23)*Inputs!$C$30*NORMSDIST(((LN(Inputs!$C$24/(E$5*Inputs!$C$23))+(Inputs!$C$25+Inputs!$C$29^2/2)*Inputs!$C$22)/(Inputs!$C$29*SQRT(Inputs!$C$22)))-Inputs!$C$29*SQRT(Inputs!$C$22))) -> 37.553233 | F14: =Inputs!$C$11*Inputs!$C$30-Inputs!$C$11/($B14*Inputs!$C$23)*(($B14*Inputs!$C$23)*Inputs!$C$30*NORMSDIST(-(((LN(Inputs!$C$24/($B14*Inputs!$C$23))+(Inputs!$C$25+Inputs!$C$29^2/2)*Inputs!$C$22)/(Inputs!$C$29*SQRT(Inputs!$C$22)))-Inputs!$C$29*SQRT(Inputs!$C$22)))-Inputs!$C$24*NORMSDIST(-((LN(Inputs!$C$24/($B14*Inputs!$C$23))+(Inputs!$C$25+Inputs!$C$29^2/2)*Inputs!$C$22)/(Inputs!$C$29*SQRT(Inputs!$C$22)))))+Inputs!$C$11/(F$5*Inputs!$C$23)*(Inputs!$C$24*NORMSDIST(((LN(Inputs!$C$24/(F$5*Inputs!$C$23))+(Inputs!$C$25+Inputs!$C$29^2/2)*Inputs!$C$22)/(Inputs!$C$29*SQRT(Inputs!$C$22))))-(F$5*Inputs!$C$23)*Inputs!$C$30*NORMSDIST(((LN(Inputs!$C$24/(F$5*Inputs!$C$23))+(Inputs!$C$25+Inputs!$C$29^2/2)*Inputs!$C$22)/(Inputs!$C$29*SQRT(Inputs!$C$22)))-Inputs!$C$29*SQRT(Inputs!$C$22))) -> 37.096023 | G14: =Inputs!$C$11*Inputs!$C$30-Inputs!$C$11/($B14*Inputs!$C$23)*(($B14*Inputs!$C$23)*Inputs!$C$30*NORMSDIST(-(((LN(Inputs!$C$24/($B14*Inputs!$C$23))+(Inputs!$C$25+Inputs!$C$29^2/2)*Inputs!$C$22)/(Inputs!$C$29*SQRT(Inputs!$C$22)))-Inputs!$C$29*SQRT(Inputs!$C$22)))-Inputs!$C$24*NORMSDIST(-((LN(Inputs!$C$24/($B14*Inputs!$C$23))+(Inputs!$C$25+Inputs!$C$29^2/2)*Inputs!$C$22)/(Inputs!$C$29*SQRT(Inputs!$C$22)))))+Inputs!$C$11/(G$5*Inputs!$C$23)*(Inputs!$C$24*NORMSDIST(((LN(Inputs!$C$24/(G$5*Inputs!$C$23))+(Inputs!$C$25+Inputs!$C$29^2/2)*Inputs!$C$22)/(Inputs!$C$29*SQRT(Inputs!$C$22))))-(G$5*Inputs!$C$23)*Inputs!$C$30*NORMSDIST(((LN(Inputs!$C$24/(G$5*Inputs!$C$23))+(Inputs!$C$25+Inputs!$C$29^2/2)*Inputs!$C$22)/(Inputs!$C$29*SQRT(Inputs!$C$22)))-Inputs!$C$29*SQRT(Inputs!$C$22))) -> 36.682147 | H14: =Inputs!$C$11*Inputs!$C$30-Inputs!$C$11/($B14*Inputs!$C$23)*(($B14*Inputs!$C$23)*Inputs!$C$30*NORMSDIST(-(((LN(Inputs!$C$24/($B14*Inputs!$C$23))+(Inputs!$C$25+Inputs!$C$29^2/2)*Inputs!$C$22)/(Inputs!$C$29*SQRT(Inputs!$C$22)))-Inputs!$C$29*SQRT(Inputs!$C$22)))-Inputs!$C$24*NORMSDIST(-((LN(Inputs!$C$24/($B14*Inputs!$C$23))+(Inputs!$C$25+Inputs!$C$29^2/2)*Inputs!$C$22)/(Inputs!$C$29*SQRT(Inputs!$C$22)))))+Inputs!$C$11/(H$5*Inputs!$C$23)*(Inputs!$C$24*NORMSDIST(((LN(Inputs!$C$24/(H$5*Inputs!$C$23))+(Inputs!$C$25+Inputs!$C$29^2/2)*Inputs!$C$22)/(Inputs!$C$29*SQRT(Inputs!$C$22))))-(H$5*Inputs!$C$23)*Inputs!$C$30*NORMSDIST(((LN(Inputs!$C$24/(H$5*Inputs!$C$23))+(Inputs!$C$25+Inputs!$C$29^2/2)*Inputs!$C$22)/(Inputs!$C$29*SQRT(Inputs!$C$22)))-Inputs!$C$29*SQRT(Inputs!$C$22))) -> 36.307819 | I14: =Inputs!$C$11*Inputs!$C$30-Inputs!$C$11/($B14*Inputs!$C$23)*(($B14*Inputs!$C$23)*Inputs!$C$30*NORMSDIST(-(((LN(Inputs!$C$24/($B14*Inputs!$C$23))+(Inputs!$C$25+Inputs!$C$29^2/2)*Inputs!$C$22)/(Inputs!$C$29*SQRT(Inputs!$C$22)))-Inputs!$C$29*SQRT(Inputs!$C$22)))-Inputs!$C$24*NORMSDIST(-((LN(Inputs!$C$24/($B14*Inputs!$C$23))+(Inputs!$C$25+Inputs!$C$29^2/2)*Inputs!$C$22)/(Inputs!$C$29*SQRT(Inputs!$C$22)))))+Inputs!$C$11/(I$5*Inputs!$C$23)*(Inputs!$C$24*NORMSDIST(((LN(Inputs!$C$24/(I$5*Inputs!$C$23))+(Inputs!$C$25+Inputs!$C$29^2/2)*Inputs!$C$22)/(Inputs!$C$29*SQRT(Inputs!$C$22))))-(I$5*Inputs!$C$23)*Inputs!$C$30*NORMSDIST(((LN(Inputs!$C$24/(I$5*Inputs!$C$23))+(Inputs!$C$25+Inputs!$C$29^2/2)*Inputs!$C$22)/(Inputs!$C$29*SQRT(Inputs!$C$22)))-Inputs!$C$29*SQRT(Inputs!$C$22))) -> 35.96954 | J14: =Inputs!$C$11*Inputs!$C$30-Inputs!$C$11/($B14*Inputs!$C$23)*(($B14*Inputs!$C$23)*Inputs!$C$30*NORMSDIST(-(((LN(Inputs!$C$24/($B14*Inputs!$C$23))+(Inputs!$C$25+Inputs!$C$29^2/2)*Inputs!$C$22)/(Inputs!$C$29*SQRT(Inputs!$C$22)))-Inputs!$C$29*SQRT(Inputs!$C$22)))-Inputs!$C$24*NORMSDIST(-((LN(Inputs!$C$24/($B14*Inputs!$C$23))+(Inputs!$C$25+Inputs!$C$29^2/2)*Inputs!$C$22)/(Inputs!$C$29*SQRT(Inputs!$C$22)))))+Inputs!$C$11/(J$5*Inputs!$C$23)*(Inputs!$C$24*NORMSDIST(((LN(Inputs!$C$24/(J$5*Inputs!$C$23))+(Inputs!$C$25+Inputs!$C$29^2/2)*Inputs!$C$22)/(Inputs!$C$29*SQRT(Inputs!$C$22))))-(J$5*Inputs!$C$23)*Inputs!$C$30*NORMSDIST(((LN(Inputs!$C$24/(J$5*Inputs!$C$23))+(Inputs!$C$25+Inputs!$C$29^2/2)*Inputs!$C$22)/(Inputs!$C$29*SQRT(Inputs!$C$22)))-Inputs!$C$29*SQRT(Inputs!$C$22))) -> 35.664079 | ... O14: =Inputs!$C$11*Inputs!$C$30-Inputs!$C$11/($B14*Inputs!$C$23)*(($B14*Inputs!$C$23)*Inputs!$C$30*NORMSDIST(-(((LN(Inputs!$C$24/($B14*Inputs!$C$23))+(Inputs!$C$25+Inputs!$C$29^2/2)*Inputs!$C$22)/(Inputs!$C$29*SQRT(Inputs!$C$22)))-Inputs!$C$29*SQRT(Inputs!$C$22)))-Inputs!$C$24*NORMSDIST(-((LN(Inputs!$C$24/($B14*Inputs!$C$23))+(Inputs!$C$25+Inputs!$C$29^2/2)*Inputs!$C$22)/(Inputs!$C$29*SQRT(Inputs!$C$22)))))+Inputs!$C$11/(O$5*Inputs!$C$23)*(Inputs!$C$24*NORMSDIST(((LN(Inputs!$C$24/(O$5*Inputs!$C$23))+(Inputs!$C$25+Inputs!$C$29^2/2)*Inputs!$C$22)/(Inputs!$C$29*SQRT(Inputs!$C$22))))-(O$5*Inputs!$C$23)*Inputs!$C$30*NORMSDIST(((LN(Inputs!$C$24/(O$5*Inputs!$C$23))+(Inputs!$C$25+Inputs!$C$29^2/2)*Inputs!$C$22)/(Inputs!$C$29*SQRT(Inputs!$C$22)))-Inputs!$C$29*SQRT(Inputs!$C$22))) -> 34.532951
B15: 0.925 | C15: =Inputs!$C$11*Inputs!$C$30-Inputs!$C$11/($B15*Inputs!$C$23)*(($B15*Inputs!$C$23)*Inputs!$C$30*NORMSDIST(-(((LN(Inputs!$C$24/($B15*Inputs!$C$23))+(Inputs!$C$25+Inputs!$C$29^2/2)*Inputs!$C$22)/(Inputs!$C$29*SQRT(Inputs!$C$22)))-Inputs!$C$29*SQRT(Inputs!$C$22)))-Inputs!$C$24*NORMSDIST(-((LN(Inputs!$C$24/($B15*Inputs!$C$23))+(Inputs!$C$25+Inputs!$C$29^2/2)*Inputs!$C$22)/(Inputs!$C$29*SQRT(Inputs!$C$22)))))+Inputs!$C$11/(C$5*Inputs!$C$23)*(Inputs!$C$24*NORMSDIST(((LN(Inputs!$C$24/(C$5*Inputs!$C$23))+(Inputs!$C$25+Inputs!$C$29^2/2)*Inputs!$C$22)/(Inputs!$C$29*SQRT(Inputs!$C$22))))-(C$5*Inputs!$C$23)*Inputs!$C$30*NORMSDIST(((LN(Inputs!$C$24/(C$5*Inputs!$C$23))+(Inputs!$C$25+Inputs!$C$29^2/2)*Inputs!$C$22)/(Inputs!$C$29*SQRT(Inputs!$C$22)))-Inputs!$C$29*SQRT(Inputs!$C$22))) -> 38.308931 | D15: =Inputs!$C$11*Inputs!$C$30-Inputs!$C$11/($B15*Inputs!$C$23)*(($B15*Inputs!$C$23)*Inputs!$C$30*NORMSDIST(-(((LN(Inputs!$C$24/($B15*Inputs!$C$23))+(Inputs!$C$25+Inputs!$C$29^2/2)*Inputs!$C$22)/(Inputs!$C$29*SQRT(Inputs!$C$22)))-Inputs!$C$29*SQRT(Inputs!$C$22)))-Inputs!$C$24*NORMSDIST(-((LN(Inputs!$C$24/($B15*Inputs!$C$23))+(Inputs!$C$25+Inputs!$C$29^2/2)*Inputs!$C$22)/(Inputs!$C$29*SQRT(Inputs!$C$22)))))+Inputs!$C$11/(D$5*Inputs!$C$23)*(Inputs!$C$24*NORMSDIST(((LN(Inputs!$C$24/(D$5*Inputs!$C$23))+(Inputs!$C$25+Inputs!$C$29^2/2)*Inputs!$C$22)/(Inputs!$C$29*SQRT(Inputs!$C$22))))-(D$5*Inputs!$C$23)*Inputs!$C$30*NORMSDIST(((LN(Inputs!$C$24/(D$5*Inputs!$C$23))+(Inputs!$C$25+Inputs!$C$29^2/2)*Inputs!$C$22)/(Inputs!$C$29*SQRT(Inputs!$C$22)))-Inputs!$C$29*SQRT(Inputs!$C$22))) -> 37.752462 | E15: =Inputs!$C$11*Inputs!$C$30-Inputs!$C$11/($B15*Inputs!$C$23)*(($B15*Inputs!$C$23)*Inputs!$C$30*NORMSDIST(-(((LN(Inputs!$C$24/($B15*Inputs!$C$23))+(Inputs!$C$25+Inputs!$C$29^2/2)*Inputs!$C$22)/(Inputs!$C$29*SQRT(Inputs!$C$22)))-Inputs!$C$29*SQRT(Inputs!$C$22)))-Inputs!$C$24*NORMSDIST(-((LN(Inputs!$C$24/($B15*Inputs!$C$23))+(Inputs!$C$25+Inputs!$C$29^2/2)*Inputs!$C$22)/(Inputs!$C$29*SQRT(Inputs!$C$22)))))+Inputs!$C$11/(E$5*Inputs!$C$23)*(Inputs!$C$24*NORMSDIST(((LN(Inputs!$C$24/(E$5*Inputs!$C$23))+(Inputs!$C$25+Inputs!$C$29^2/2)*Inputs!$C$22)/(Inputs!$C$29*SQRT(Inputs!$C$22))))-(E$5*Inputs!$C$23)*Inputs!$C$30*NORMSDIST(((LN(Inputs!$C$24/(E$5*Inputs!$C$23))+(Inputs!$C$25+Inputs!$C$29^2/2)*Inputs!$C$22)/(Inputs!$C$29*SQRT(Inputs!$C$22)))-Inputs!$C$29*SQRT(Inputs!$C$22))) -> 37.247828 | F15: =Inputs!$C$11*Inputs!$C$30-Inputs!$C$11/($B15*Inputs!$C$23)*(($B15*Inputs!$C$23)*Inputs!$C$30*NORMSDIST(-(((LN(Inputs!$C$24/($B15*Inputs!$C$23))+(Inputs!$C$25+Inputs!$C$29^2/2)*Inputs!$C$22)/(Inputs!$C$29*SQRT(Inputs!$C$22)))-Inputs!$C$29*SQRT(Inputs!$C$22)))-Inputs!$C$24*NORMSDIST(-((LN(Inputs!$C$24/($B15*Inputs!$C$23))+(Inputs!$C$25+Inputs!$C$29^2/2)*Inputs!$C$22)/(Inputs!$C$29*SQRT(Inputs!$C$22)))))+Inputs!$C$11/(F$5*Inputs!$C$23)*(Inputs!$C$24*NORMSDIST(((LN(Inputs!$C$24/(F$5*Inputs!$C$23))+(Inputs!$C$25+Inputs!$C$29^2/2)*Inputs!$C$22)/(Inputs!$C$29*SQRT(Inputs!$C$22))))-(F$5*Inputs!$C$23)*Inputs!$C$30*NORMSDIST(((LN(Inputs!$C$24/(F$5*Inputs!$C$23))+(Inputs!$C$25+Inputs!$C$29^2/2)*Inputs!$C$22)/(Inputs!$C$29*SQRT(Inputs!$C$22)))-Inputs!$C$29*SQRT(Inputs!$C$22))) -> 36.790618 | G15: =Inputs!$C$11*Inputs!$C$30-Inputs!$C$11/($B15*Inputs!$C$23)*(($B15*Inputs!$C$23)*Inputs!$C$30*NORMSDIST(-(((LN(Inputs!$C$24/($B15*Inputs!$C$23))+(Inputs!$C$25+Inputs!$C$29^2/2)*Inputs!$C$22)/(Inputs!$C$29*SQRT(Inputs!$C$22)))-Inputs!$C$29*SQRT(Inputs!$C$22)))-Inputs!$C$24*NORMSDIST(-((LN(Inputs!$C$24/($B15*Inputs!$C$23))+(Inputs!$C$25+Inputs!$C$29^2/2)*Inputs!$C$22)/(Inputs!$C$29*SQRT(Inputs!$C$22)))))+Inputs!$C$11/(G$5*Inputs!$C$23)*(Inputs!$C$24*NORMSDIST(((LN(Inputs!$C$24/(G$5*Inputs!$C$23))+(Inputs!$C$25+Inputs!$C$29^2/2)*Inputs!$C$22)/(Inputs!$C$29*SQRT(Inputs!$C$22))))-(G$5*Inputs!$C$23)*Inputs!$C$30*NORMSDIST(((LN(Inputs!$C$24/(G$5*Inputs!$C$23))+(Inputs!$C$25+Inputs!$C$29^2/2)*Inputs!$C$22)/(Inputs!$C$29*SQRT(Inputs!$C$22)))-Inputs!$C$29*SQRT(Inputs!$C$22))) -> 36.376742 | H15: =Inputs!$C$11*Inputs!$C$30-Inputs!$C$11/($B15*Inputs!$C$23)*(($B15*Inputs!$C$23)*Inputs!$C$30*NORMSDIST(-(((LN(Inputs!$C$24/($B15*Inputs!$C$23))+(Inputs!$C$25+Inputs!$C$29^2/2)*Inputs!$C$22)/(Inputs!$C$29*SQRT(Inputs!$C$22)))-Inputs!$C$29*SQRT(Inputs!$C$22)))-Inputs!$C$24*NORMSDIST(-((LN(Inputs!$C$24/($B15*Inputs!$C$23))+(Inputs!$C$25+Inputs!$C$29^2/2)*Inputs!$C$22)/(Inputs!$C$29*SQRT(Inputs!$C$22)))))+Inputs!$C$11/(H$5*Inputs!$C$23)*(Inputs!$C$24*NORMSDIST(((LN(Inputs!$C$24/(H$5*Inputs!$C$23))+(Inputs!$C$25+Inputs!$C$29^2/2)*Inputs!$C$22)/(Inputs!$C$29*SQRT(Inputs!$C$22))))-(H$5*Inputs!$C$23)*Inputs!$C$30*NORMSDIST(((LN(Inputs!$C$24/(H$5*Inputs!$C$23))+(Inputs!$C$25+Inputs!$C$29^2/2)*Inputs!$C$22)/(Inputs!$C$29*SQRT(Inputs!$C$22)))-Inputs!$C$29*SQRT(Inputs!$C$22))) -> 36.002414 | I15: =Inputs!$C$11*Inputs!$C$30-Inputs!$C$11/($B15*Inputs!$C$23)*(($B15*Inputs!$C$23)*Inputs!$C$30*NORMSDIST(-(((LN(Inputs!$C$24/($B15*Inputs!$C$23))+(Inputs!$C$25+Inputs!$C$29^2/2)*Inputs!$C$22)/(Inputs!$C$29*SQRT(Inputs!$C$22)))-Inputs!$C$29*SQRT(Inputs!$C$22)))-Inputs!$C$24*NORMSDIST(-((LN(Inputs!$C$24/($B15*Inputs!$C$23))+(Inputs!$C$25+Inputs!$C$29^2/2)*Inputs!$C$22)/(Inputs!$C$29*SQRT(Inputs!$C$22)))))+Inputs!$C$11/(I$5*Inputs!$C$23)*(Inputs!$C$24*NORMSDIST(((LN(Inputs!$C$24/(I$5*Inputs!$C$23))+(Inputs!$C$25+Inputs!$C$29^2/2)*Inputs!$C$22)/(Inputs!$C$29*SQRT(Inputs!$C$22))))-(I$5*Inputs!$C$23)*Inputs!$C$30*NORMSDIST(((LN(Inputs!$C$24/(I$5*Inputs!$C$23))+(Inputs!$C$25+Inputs!$C$29^2/2)*Inputs!$C$22)/(Inputs!$C$29*SQRT(Inputs!$C$22)))-Inputs!$C$29*SQRT(Inputs!$C$22))) -> 35.664135 | J15: =Inputs!$C$11*Inputs!$C$30-Inputs!$C$11/($B15*Inputs!$C$23)*(($B15*Inputs!$C$23)*Inputs!$C$30*NORMSDIST(-(((LN(Inputs!$C$24/($B15*Inputs!$C$23))+(Inputs!$C$25+Inputs!$C$29^2/2)*Inputs!$C$22)/(Inputs!$C$29*SQRT(Inputs!$C$22)))-Inputs!$C$29*SQRT(Inputs!$C$22)))-Inputs!$C$24*NORMSDIST(-((LN(Inputs!$C$24/($B15*Inputs!$C$23))+(Inputs!$C$25+Inputs!$C$29^2/2)*Inputs!$C$22)/(Inputs!$C$29*SQRT(Inputs!$C$22)))))+Inputs!$C$11/(J$5*Inputs!$C$23)*(Inputs!$C$24*NORMSDIST(((LN(Inputs!$C$24/(J$5*Inputs!$C$23))+(Inputs!$C$25+Inputs!$C$29^2/2)*Inputs!$C$22)/(Inputs!$C$29*SQRT(Inputs!$C$22))))-(J$5*Inputs!$C$23)*Inputs!$C$30*NORMSDIST(((LN(Inputs!$C$24/(J$5*Inputs!$C$23))+(Inputs!$C$25+Inputs!$C$29^2/2)*Inputs!$C$22)/(Inputs!$C$29*SQRT(Inputs!$C$22)))-Inputs!$C$29*SQRT(Inputs!$C$22))) -> 35.358674 | ... O15: =Inputs!$C$11*Inputs!$C$30-Inputs!$C$11/($B15*Inputs!$C$23)*(($B15*Inputs!$C$23)*Inputs!$C$30*NORMSDIST(-(((LN(Inputs!$C$24/($B15*Inputs!$C$23))+(Inputs!$C$25+Inputs!$C$29^2/2)*Inputs!$C$22)/(Inputs!$C$29*SQRT(Inputs!$C$22)))-Inputs!$C$29*SQRT(Inputs!$C$22)))-Inputs!$C$24*NORMSDIST(-((LN(Inputs!$C$24/($B15*Inputs!$C$23))+(Inputs!$C$25+Inputs!$C$29^2/2)*Inputs!$C$22)/(Inputs!$C$29*SQRT(Inputs!$C$22)))))+Inputs!$C$11/(O$5*Inputs!$C$23)*(Inputs!$C$24*NORMSDIST(((LN(Inputs!$C$24/(O$5*Inputs!$C$23))+(Inputs!$C$25+Inputs!$C$29^2/2)*Inputs!$C$22)/(Inputs!$C$29*SQRT(Inputs!$C$22))))-(O$5*Inputs!$C$23)*Inputs!$C$30*NORMSDIST(((LN(Inputs!$C$24/(O$5*Inputs!$C$23))+(Inputs!$C$25+Inputs!$C$29^2/2)*Inputs!$C$22)/(Inputs!$C$29*SQRT(Inputs!$C$22)))-Inputs!$C$29*SQRT(Inputs!$C$22))) -> 34.227546
B16: 0.95 | C16: =Inputs!$C$11*Inputs!$C$30-Inputs!$C$11/($B16*Inputs!$C$23)*(($B16*Inputs!$C$23)*Inputs!$C$30*NORMSDIST(-(((LN(Inputs!$C$24/($B16*Inputs!$C$23))+(Inputs!$C$25+Inputs!$C$29^2/2)*Inputs!$C$22)/(Inputs!$C$29*SQRT(Inputs!$C$22)))-Inputs!$C$29*SQRT(Inputs!$C$22)))-Inputs!$C$24*NORMSDIST(-((LN(Inputs!$C$24/($B16*Inputs!$C$23))+(Inputs!$C$25+Inputs!$C$29^2/2)*Inputs!$C$22)/(Inputs!$C$29*SQRT(Inputs!$C$22)))))+Inputs!$C$11/(C$5*Inputs!$C$23)*(Inputs!$C$24*NORMSDIST(((LN(Inputs!$C$24/(C$5*Inputs!$C$23))+(Inputs!$C$25+Inputs!$C$29^2/2)*Inputs!$C$22)/(Inputs!$C$29*SQRT(Inputs!$C$22))))-(C$5*Inputs!$C$23)*Inputs!$C$30*NORMSDIST(((LN(Inputs!$C$24/(C$5*Inputs!$C$23))+(Inputs!$C$25+Inputs!$C$29^2/2)*Inputs!$C$22)/(Inputs!$C$29*SQRT(Inputs!$C$22)))-Inputs!$C$29*SQRT(Inputs!$C$22))) -> 37.989362 | D16: =Inputs!$C$11*Inputs!$C$30-Inputs!$C$11/($B16*Inputs!$C$23)*(($B16*Inputs!$C$23)*Inputs!$C$30*NORMSDIST(-(((LN(Inputs!$C$24/($B16*Inputs!$C$23))+(Inputs!$C$25+Inputs!$C$29^2/2)*Inputs!$C$22)/(Inputs!$C$29*SQRT(Inputs!$C$22)))-Inputs!$C$29*SQRT(Inputs!$C$22)))-Inputs!$C$24*NORMSDIST(-((LN(Inputs!$C$24/($B16*Inputs!$C$23))+(Inputs!$C$25+Inputs!$C$29^2/2)*Inputs!$C$22)/(Inputs!$C$29*SQRT(Inputs!$C$22)))))+Inputs!$C$11/(D$5*Inputs!$C$23)*(Inputs!$C$24*NORMSDIST(((LN(Inputs!$C$24/(D$5*Inputs!$C$23))+(Inputs!$C$25+Inputs!$C$29^2/2)*Inputs!$C$22)/(Inputs!$C$29*SQRT(Inputs!$C$22))))-(D$5*Inputs!$C$23)*Inputs!$C$30*NORMSDIST(((LN(Inputs!$C$24/(D$5*Inputs!$C$23))+(Inputs!$C$25+Inputs!$C$29^2/2)*Inputs!$C$22)/(Inputs!$C$29*SQRT(Inputs!$C$22)))-Inputs!$C$29*SQRT(Inputs!$C$22))) -> 37.432893 | E16: =Inputs!$C$11*Inputs!$C$30-Inputs!$C$11/($B16*Inputs!$C$23)*(($B16*Inputs!$C$23)*Inputs!$C$30*NORMSDIST(-(((LN(Inputs!$C$24/($B16*Inputs!$C$23))+(Inputs!$C$25+Inputs!$C$29^2/2)*Inputs!$C$22)/(Inputs!$C$29*SQRT(Inputs!$C$22)))-Inputs!$C$29*SQRT(Inputs!$C$22)))-Inputs!$C$24*NORMSDIST(-((LN(Inputs!$C$24/($B16*Inputs!$C$23))+(Inputs!$C$25+Inputs!$C$29^2/2)*Inputs!$C$22)/(Inputs!$C$29*SQRT(Inputs!$C$22)))))+Inputs!$C$11/(E$5*Inputs!$C$23)*(Inputs!$C$24*NORMSDIST(((LN(Inputs!$C$24/(E$5*Inputs!$C$23))+(Inputs!$C$25+Inputs!$C$29^2/2)*Inputs!$C$22)/(Inputs!$C$29*SQRT(Inputs!$C$22))))-(E$5*Inputs!$C$23)*Inputs!$C$30*NORMSDIST(((LN(Inputs!$C$24/(E$5*Inputs!$C$23))+(Inputs!$C$25+Inputs!$C$29^2/2)*Inputs!$C$22)/(Inputs!$C$29*SQRT(Inputs!$C$22)))-Inputs!$C$29*SQRT(Inputs!$C$22))) -> 36.928259 | F16: =Inputs!$C$11*Inputs!$C$30-Inputs!$C$11/($B16*Inputs!$C$23)*(($B16*Inputs!$C$23)*Inputs!$C$30*NORMSDIST(-(((LN(Inputs!$C$24/($B16*Inputs!$C$23))+(Inputs!$C$25+Inputs!$C$29^2/2)*Inputs!$C$22)/(Inputs!$C$29*SQRT(Inputs!$C$22)))-Inputs!$C$29*SQRT(Inputs!$C$22)))-Inputs!$C$24*NORMSDIST(-((LN(Inputs!$C$24/($B16*Inputs!$C$23))+(Inputs!$C$25+Inputs!$C$29^2/2)*Inputs!$C$22)/(Inputs!$C$29*SQRT(Inputs!$C$22)))))+Inputs!$C$11/(F$5*Inputs!$C$23)*(Inputs!$C$24*NORMSDIST(((LN(Inputs!$C$24/(F$5*Inputs!$C$23))+(Inputs!$C$25+Inputs!$C$29^2/2)*Inputs!$C$22)/(Inputs!$C$29*SQRT(Inputs!$C$22))))-(F$5*Inputs!$C$23)*Inputs!$C$30*NORMSDIST(((LN(Inputs!$C$24/(F$5*Inputs!$C$23))+(Inputs!$C$25+Inputs!$C$29^2/2)*Inputs!$C$22)/(Inputs!$C$29*SQRT(Inputs!$C$22)))-Inputs!$C$29*SQRT(Inputs!$C$22))) -> 36.471049 | G16: =Inputs!$C$11*Inputs!$C$30-Inputs!$C$11/($B16*Inputs!$C$23)*(($B16*Inputs!$C$23)*Inputs!$C$30*NORMSDIST(-(((LN(Inputs!$C$24/($B16*Inputs!$C$23))+(Inputs!$C$25+Inputs!$C$29^2/2)*Inputs!$C$22)/(Inputs!$C$29*SQRT(Inputs!$C$22)))-Inputs!$C$29*SQRT(Inputs!$C$22)))-Inputs!$C$24*NORMSDIST(-((LN(Inputs!$C$24/($B16*Inputs!$C$23))+(Inputs!$C$25+Inputs!$C$29^2/2)*Inputs!$C$22)/(Inputs!$C$29*SQRT(Inputs!$C$22)))))+Inputs!$C$11/(G$5*Inputs!$C$23)*(Inputs!$C$24*NORMSDIST(((LN(Inputs!$C$24/(G$5*Inputs!$C$23))+(Inputs!$C$25+Inputs!$C$29^2/2)*Inputs!$C$22)/(Inputs!$C$29*SQRT(Inputs!$C$22))))-(G$5*Inputs!$C$23)*Inputs!$C$30*NORMSDIST(((LN(Inputs!$C$24/(G$5*Inputs!$C$23))+(Inputs!$C$25+Inputs!$C$29^2/2)*Inputs!$C$22)/(Inputs!$C$29*SQRT(Inputs!$C$22)))-Inputs!$C$29*SQRT(Inputs!$C$22))) -> 36.057173 | H16: =Inputs!$C$11*Inputs!$C$30-Inputs!$C$11/($B16*Inputs!$C$23)*(($B16*Inputs!$C$23)*Inputs!$C$30*NORMSDIST(-(((LN(Inputs!$C$24/($B16*Inputs!$C$23))+(Inputs!$C$25+Inputs!$C$29^2/2)*Inputs!$C$22)/(Inputs!$C$29*SQRT(Inputs!$C$22)))-Inputs!$C$29*SQRT(Inputs!$C$22)))-Inputs!$C$24*NORMSDIST(-((LN(Inputs!$C$24/($B16*Inputs!$C$23))+(Inputs!$C$25+Inputs!$C$29^2/2)*Inputs!$C$22)/(Inputs!$C$29*SQRT(Inputs!$C$22)))))+Inputs!$C$11/(H$5*Inputs!$C$23)*(Inputs!$C$24*NORMSDIST(((LN(Inputs!$C$24/(H$5*Inputs!$C$23))+(Inputs!$C$25+Inputs!$C$29^2/2)*Inputs!$C$22)/(Inputs!$C$29*SQRT(Inputs!$C$22))))-(H$5*Inputs!$C$23)*Inputs!$C$30*NORMSDIST(((LN(Inputs!$C$24/(H$5*Inputs!$C$23))+(Inputs!$C$25+Inputs!$C$29^2/2)*Inputs!$C$22)/(Inputs!$C$29*SQRT(Inputs!$C$22)))-Inputs!$C$29*SQRT(Inputs!$C$22))) -> 35.682845 | I16: =Inputs!$C$11*Inputs!$C$30-Inputs!$C$11/($B16*Inputs!$C$23)*(($B16*Inputs!$C$23)*Inputs!$C$30*NORMSDIST(-(((LN(Inputs!$C$24/($B16*Inputs!$C$23))+(Inputs!$C$25+Inputs!$C$29^2/2)*Inputs!$C$22)/(Inputs!$C$29*SQRT(Inputs!$C$22)))-Inputs!$C$29*SQRT(Inputs!$C$22)))-Inputs!$C$24*NORMSDIST(-((LN(Inputs!$C$24/($B16*Inputs!$C$23))+(Inputs!$C$25+Inputs!$C$29^2/2)*Inputs!$C$22)/(Inputs!$C$29*SQRT(Inputs!$C$22)))))+Inputs!$C$11/(I$5*Inputs!$C$23)*(Inputs!$C$24*NORMSDIST(((LN(Inputs!$C$24/(I$5*Inputs!$C$23))+(Inputs!$C$25+Inputs!$C$29^2/2)*Inputs!$C$22)/(Inputs!$C$29*SQRT(Inputs!$C$22))))-(I$5*Inputs!$C$23)*Inputs!$C$30*NORMSDIST(((LN(Inputs!$C$24/(I$5*Inputs!$C$23))+(Inputs!$C$25+Inputs!$C$29^2/2)*Inputs!$C$22)/(Inputs!$C$29*SQRT(Inputs!$C$22)))-Inputs!$C$29*SQRT(Inputs!$C$22))) -> 35.344566 | J16: =Inputs!$C$11*Inputs!$C$30-Inputs!$C$11/($B16*Inputs!$C$23)*(($B16*Inputs!$C$23)*Inputs!$C$30*NORMSDIST(-(((LN(Inputs!$C$24/($B16*Inputs!$C$23))+(Inputs!$C$25+Inputs!$C$29^2/2)*Inputs!$C$22)/(Inputs!$C$29*SQRT(Inputs!$C$22)))-Inputs!$C$29*SQRT(Inputs!$C$22)))-Inputs!$C$24*NORMSDIST(-((LN(Inputs!$C$24/($B16*Inputs!$C$23))+(Inputs!$C$25+Inputs!$C$29^2/2)*Inputs!$C$22)/(Inputs!$C$29*SQRT(Inputs!$C$22)))))+Inputs!$C$11/(J$5*Inputs!$C$23)*(Inputs!$C$24*NORMSDIST(((LN(Inputs!$C$24/(J$5*Inputs!$C$23))+(Inputs!$C$25+Inputs!$C$29^2/2)*Inputs!$C$22)/(Inputs!$C$29*SQRT(Inputs!$C$22))))-(J$5*Inputs!$C$23)*Inputs!$C$30*NORMSDIST(((LN(Inputs!$C$24/(J$5*Inputs!$C$23))+(Inputs!$C$25+Inputs!$C$29^2/2)*Inputs!$C$22)/(Inputs!$C$29*SQRT(Inputs!$C$22)))-Inputs!$C$29*SQRT(Inputs!$C$22))) -> 35.039105 | ... O16: =Inputs!$C$11*Inputs!$C$30-Inputs!$C$11/($B16*Inputs!$C$23)*(($B16*Inputs!$C$23)*Inputs!$C$30*NORMSDIST(-(((LN(Inputs!$C$24/($B16*Inputs!$C$23))+(Inputs!$C$25+Inputs!$C$29^2/2)*Inputs!$C$22)/(Inputs!$C$29*SQRT(Inputs!$C$22)))-Inputs!$C$29*SQRT(Inputs!$C$22)))-Inputs!$C$24*NORMSDIST(-((LN(Inputs!$C$24/($B16*Inputs!$C$23))+(Inputs!$C$25+Inputs!$C$29^2/2)*Inputs!$C$22)/(Inputs!$C$29*SQRT(Inputs!$C$22)))))+Inputs!$C$11/(O$5*Inputs!$C$23)*(Inputs!$C$24*NORMSDIST(((LN(Inputs!$C$24/(O$5*Inputs!$C$23))+(Inputs!$C$25+Inputs!$C$29^2/2)*Inputs!$C$22)/(Inputs!$C$29*SQRT(Inputs!$C$22))))-(O$5*Inputs!$C$23)*Inputs!$C$30*NORMSDIST(((LN(Inputs!$C$24/(O$5*Inputs!$C$23))+(Inputs!$C$25+Inputs!$C$29^2/2)*Inputs!$C$22)/(Inputs!$C$29*SQRT(Inputs!$C$22)))-Inputs!$C$29*SQRT(Inputs!$C$22))) -> 33.907977
B17: 0.975 | C17: =Inputs!$C$11*Inputs!$C$30-Inputs!$C$11/($B17*Inputs!$C$23)*(($B17*Inputs!$C$23)*Inputs!$C$30*NORMSDIST(-(((LN(Inputs!$C$24/($B17*Inputs!$C$23))+(Inputs!$C$25+Inputs!$C$29^2/2)*Inputs!$C$22)/(Inputs!$C$29*SQRT(Inputs!$C$22)))-Inputs!$C$29*SQRT(Inputs!$C$22)))-Inputs!$C$24*NORMSDIST(-((LN(Inputs!$C$24/($B17*Inputs!$C$23))+(Inputs!$C$25+Inputs!$C$29^2/2)*Inputs!$C$22)/(Inputs!$C$29*SQRT(Inputs!$C$22)))))+Inputs!$C$11/(C$5*Inputs!$C$23)*(Inputs!$C$24*NORMSDIST(((LN(Inputs!$C$24/(C$5*Inputs!$C$23))+(Inputs!$C$25+Inputs!$C$29^2/2)*Inputs!$C$22)/(Inputs!$C$29*SQRT(Inputs!$C$22))))-(C$5*Inputs!$C$23)*Inputs!$C$30*NORMSDIST(((LN(Inputs!$C$24/(C$5*Inputs!$C$23))+(Inputs!$C$25+Inputs!$C$29^2/2)*Inputs!$C$22)/(Inputs!$C$29*SQRT(Inputs!$C$22)))-Inputs!$C$29*SQRT(Inputs!$C$22))) -> 37.657019 | D17: =Inputs!$C$11*Inputs!$C$30-Inputs!$C$11/($B17*Inputs!$C$23)*(($B17*Inputs!$C$23)*Inputs!$C$30*NORMSDIST(-(((LN(Inputs!$C$24/($B17*Inputs!$C$23))+(Inputs!$C$25+Inputs!$C$29^2/2)*Inputs!$C$22)/(Inputs!$C$29*SQRT(Inputs!$C$22)))-Inputs!$C$29*SQRT(Inputs!$C$22)))-Inputs!$C$24*NORMSDIST(-((LN(Inputs!$C$24/($B17*Inputs!$C$23))+(Inputs!$C$25+Inputs!$C$29^2/2)*Inputs!$C$22)/(Inputs!$C$29*SQRT(Inputs!$C$22)))))+Inputs!$C$11/(D$5*Inputs!$C$23)*(Inputs!$C$24*NORMSDIST(((LN(Inputs!$C$24/(D$5*Inputs!$C$23))+(Inputs!$C$25+Inputs!$C$29^2/2)*Inputs!$C$22)/(Inputs!$C$29*SQRT(Inputs!$C$22))))-(D$5*Inputs!$C$23)*Inputs!$C$30*NORMSDIST(((LN(Inputs!$C$24/(D$5*Inputs!$C$23))+(Inputs!$C$25+Inputs!$C$29^2/2)*Inputs!$C$22)/(Inputs!$C$29*SQRT(Inputs!$C$22)))-Inputs!$C$29*SQRT(Inputs!$C$22))) -> 37.100549 | E17: =Inputs!$C$11*Inputs!$C$30-Inputs!$C$11/($B17*Inputs!$C$23)*(($B17*Inputs!$C$23)*Inputs!$C$30*NORMSDIST(-(((LN(Inputs!$C$24/($B17*Inputs!$C$23))+(Inputs!$C$25+Inputs!$C$29^2/2)*Inputs!$C$22)/(Inputs!$C$29*SQRT(Inputs!$C$22)))-Inputs!$C$29*SQRT(Inputs!$C$22)))-Inputs!$C$24*NORMSDIST(-((LN(Inputs!$C$24/($B17*Inputs!$C$23))+(Inputs!$C$25+Inputs!$C$29^2/2)*Inputs!$C$22)/(Inputs!$C$29*SQRT(Inputs!$C$22)))))+Inputs!$C$11/(E$5*Inputs!$C$23)*(Inputs!$C$24*NORMSDIST(((LN(Inputs!$C$24/(E$5*Inputs!$C$23))+(Inputs!$C$25+Inputs!$C$29^2/2)*Inputs!$C$22)/(Inputs!$C$29*SQRT(Inputs!$C$22))))-(E$5*Inputs!$C$23)*Inputs!$C$30*NORMSDIST(((LN(Inputs!$C$24/(E$5*Inputs!$C$23))+(Inputs!$C$25+Inputs!$C$29^2/2)*Inputs!$C$22)/(Inputs!$C$29*SQRT(Inputs!$C$22)))-Inputs!$C$29*SQRT(Inputs!$C$22))) -> 36.595916 | F17: =Inputs!$C$11*Inputs!$C$30-Inputs!$C$11/($B17*Inputs!$C$23)*(($B17*Inputs!$C$23)*Inputs!$C$30*NORMSDIST(-(((LN(Inputs!$C$24/($B17*Inputs!$C$23))+(Inputs!$C$25+Inputs!$C$29^2/2)*Inputs!$C$22)/(Inputs!$C$29*SQRT(Inputs!$C$22)))-Inputs!$C$29*SQRT(Inputs!$C$22)))-Inputs!$C$24*NORMSDIST(-((LN(Inputs!$C$24/($B17*Inputs!$C$23))+(Inputs!$C$25+Inputs!$C$29^2/2)*Inputs!$C$22)/(Inputs!$C$29*SQRT(Inputs!$C$22)))))+Inputs!$C$11/(F$5*Inputs!$C$23)*(Inputs!$C$24*NORMSDIST(((LN(Inputs!$C$24/(F$5*Inputs!$C$23))+(Inputs!$C$25+Inputs!$C$29^2/2)*Inputs!$C$22)/(Inputs!$C$29*SQRT(Inputs!$C$22))))-(F$5*Inputs!$C$23)*Inputs!$C$30*NORMSDIST(((LN(Inputs!$C$24/(F$5*Inputs!$C$23))+(Inputs!$C$25+Inputs!$C$29^2/2)*Inputs!$C$22)/(Inputs!$C$29*SQRT(Inputs!$C$22)))-Inputs!$C$29*SQRT(Inputs!$C$22))) -> 36.138705 | G17: =Inputs!$C$11*Inputs!$C$30-Inputs!$C$11/($B17*Inputs!$C$23)*(($B17*Inputs!$C$23)*Inputs!$C$30*NORMSDIST(-(((LN(Inputs!$C$24/($B17*Inputs!$C$23))+(Inputs!$C$25+Inputs!$C$29^2/2)*Inputs!$C$22)/(Inputs!$C$29*SQRT(Inputs!$C$22)))-Inputs!$C$29*SQRT(Inputs!$C$22)))-Inputs!$C$24*NORMSDIST(-((LN(Inputs!$C$24/($B17*Inputs!$C$23))+(Inputs!$C$25+Inputs!$C$29^2/2)*Inputs!$C$22)/(Inputs!$C$29*SQRT(Inputs!$C$22)))))+Inputs!$C$11/(G$5*Inputs!$C$23)*(Inputs!$C$24*NORMSDIST(((LN(Inputs!$C$24/(G$5*Inputs!$C$23))+(Inputs!$C$25+Inputs!$C$29^2/2)*Inputs!$C$22)/(Inputs!$C$29*SQRT(Inputs!$C$22))))-(G$5*Inputs!$C$23)*Inputs!$C$30*NORMSDIST(((LN(Inputs!$C$24/(G$5*Inputs!$C$23))+(Inputs!$C$25+Inputs!$C$29^2/2)*Inputs!$C$22)/(Inputs!$C$29*SQRT(Inputs!$C$22)))-Inputs!$C$29*SQRT(Inputs!$C$22))) -> 35.724829 | H17: =Inputs!$C$11*Inputs!$C$30-Inputs!$C$11/($B17*Inputs!$C$23)*(($B17*Inputs!$C$23)*Inputs!$C$30*NORMSDIST(-(((LN(Inputs!$C$24/($B17*Inputs!$C$23))+(Inputs!$C$25+Inputs!$C$29^2/2)*Inputs!$C$22)/(Inputs!$C$29*SQRT(Inputs!$C$22)))-Inputs!$C$29*SQRT(Inputs!$C$22)))-Inputs!$C$24*NORMSDIST(-((LN(Inputs!$C$24/($B17*Inputs!$C$23))+(Inputs!$C$25+Inputs!$C$29^2/2)*Inputs!$C$22)/(Inputs!$C$29*SQRT(Inputs!$C$22)))))+Inputs!$C$11/(H$5*Inputs!$C$23)*(Inputs!$C$24*NORMSDIST(((LN(Inputs!$C$24/(H$5*Inputs!$C$23))+(Inputs!$C$25+Inputs!$C$29^2/2)*Inputs!$C$22)/(Inputs!$C$29*SQRT(Inputs!$C$22))))-(H$5*Inputs!$C$23)*Inputs!$C$30*NORMSDIST(((LN(Inputs!$C$24/(H$5*Inputs!$C$23))+(Inputs!$C$25+Inputs!$C$29^2/2)*Inputs!$C$22)/(Inputs!$C$29*SQRT(Inputs!$C$22)))-Inputs!$C$29*SQRT(Inputs!$C$22))) -> 35.350502 | I17: =Inputs!$C$11*Inputs!$C$30-Inputs!$C$11/($B17*Inputs!$C$23)*(($B17*Inputs!$C$23)*Inputs!$C$30*NORMSDIST(-(((LN(Inputs!$C$24/($B17*Inputs!$C$23))+(Inputs!$C$25+Inputs!$C$29^2/2)*Inputs!$C$22)/(Inputs!$C$29*SQRT(Inputs!$C$22)))-Inputs!$C$29*SQRT(Inputs!$C$22)))-Inputs!$C$24*NORMSDIST(-((LN(Inputs!$C$24/($B17*Inputs!$C$23))+(Inputs!$C$25+Inputs!$C$29^2/2)*Inputs!$C$22)/(Inputs!$C$29*SQRT(Inputs!$C$22)))))+Inputs!$C$11/(I$5*Inputs!$C$23)*(Inputs!$C$24*NORMSDIST(((LN(Inputs!$C$24/(I$5*Inputs!$C$23))+(Inputs!$C$25+Inputs!$C$29^2/2)*Inputs!$C$22)/(Inputs!$C$29*SQRT(Inputs!$C$22))))-(I$5*Inputs!$C$23)*Inputs!$C$30*NORMSDIST(((LN(Inputs!$C$24/(I$5*Inputs!$C$23))+(Inputs!$C$25+Inputs!$C$29^2/2)*Inputs!$C$22)/(Inputs!$C$29*SQRT(Inputs!$C$22)))-Inputs!$C$29*SQRT(Inputs!$C$22))) -> 35.012222 | J17: =Inputs!$C$11*Inputs!$C$30-Inputs!$C$11/($B17*Inputs!$C$23)*(($B17*Inputs!$C$23)*Inputs!$C$30*NORMSDIST(-(((LN(Inputs!$C$24/($B17*Inputs!$C$23))+(Inputs!$C$25+Inputs!$C$29^2/2)*Inputs!$C$22)/(Inputs!$C$29*SQRT(Inputs!$C$22)))-Inputs!$C$29*SQRT(Inputs!$C$22)))-Inputs!$C$24*NORMSDIST(-((LN(Inputs!$C$24/($B17*Inputs!$C$23))+(Inputs!$C$25+Inputs!$C$29^2/2)*Inputs!$C$22)/(Inputs!$C$29*SQRT(Inputs!$C$22)))))+Inputs!$C$11/(J$5*Inputs!$C$23)*(Inputs!$C$24*NORMSDIST(((LN(Inputs!$C$24/(J$5*Inputs!$C$23))+(Inputs!$C$25+Inputs!$C$29^2/2)*Inputs!$C$22)/(Inputs!$C$29*SQRT(Inputs!$C$22))))-(J$5*Inputs!$C$23)*Inputs!$C$30*NORMSDIST(((LN(Inputs!$C$24/(J$5*Inputs!$C$23))+(Inputs!$C$25+Inputs!$C$29^2/2)*Inputs!$C$22)/(Inputs!$C$29*SQRT(Inputs!$C$22)))-Inputs!$C$29*SQRT(Inputs!$C$22))) -> 34.706762 | ... O17: =Inputs!$C$11*Inputs!$C$30-Inputs!$C$11/($B17*Inputs!$C$23)*(($B17*Inputs!$C$23)*Inputs!$C$30*NORMSDIST(-(((LN(Inputs!$C$24/($B17*Inputs!$C$23))+(Inputs!$C$25+Inputs!$C$29^2/2)*Inputs!$C$22)/(Inputs!$C$29*SQRT(Inputs!$C$22)))-Inputs!$C$29*SQRT(Inputs!$C$22)))-Inputs!$C$24*NORMSDIST(-((LN(Inputs!$C$24/($B17*Inputs!$C$23))+(Inputs!$C$25+Inputs!$C$29^2/2)*Inputs!$C$22)/(Inputs!$C$29*SQRT(Inputs!$C$22)))))+Inputs!$C$11/(O$5*Inputs!$C$23)*(Inputs!$C$24*NORMSDIST(((LN(Inputs!$C$24/(O$5*Inputs!$C$23))+(Inputs!$C$25+Inputs!$C$29^2/2)*Inputs!$C$22)/(Inputs!$C$29*SQRT(Inputs!$C$22))))-(O$5*Inputs!$C$23)*Inputs!$C$30*NORMSDIST(((LN(Inputs!$C$24/(O$5*Inputs!$C$23))+(Inputs!$C$25+Inputs!$C$29^2/2)*Inputs!$C$22)/(Inputs!$C$29*SQRT(Inputs!$C$22)))-Inputs!$C$29*SQRT(Inputs!$C$22))) -> 33.575633
B18: 1 | C18: =Inputs!$C$11*Inputs!$C$30-Inputs!$C$11/($B18*Inputs!$C$23)*(($B18*Inputs!$C$23)*Inputs!$C$30*NORMSDIST(-(((LN(Inputs!$C$24/($B18*Inputs!$C$23))+(Inputs!$C$25+Inputs!$C$29^2/2)*Inputs!$C$22)/(Inputs!$C$29*SQRT(Inputs!$C$22)))-Inputs!$C$29*SQRT(Inputs!$C$22)))-Inputs!$C$24*NORMSDIST(-((LN(Inputs!$C$24/($B18*Inputs!$C$23))+(Inputs!$C$25+Inputs!$C$29^2/2)*Inputs!$C$22)/(Inputs!$C$29*SQRT(Inputs!$C$22)))))+Inputs!$C$11/(C$5*Inputs!$C$23)*(Inputs!$C$24*NORMSDIST(((LN(Inputs!$C$24/(C$5*Inputs!$C$23))+(Inputs!$C$25+Inputs!$C$29^2/2)*Inputs!$C$22)/(Inputs!$C$29*SQRT(Inputs!$C$22))))-(C$5*Inputs!$C$23)*Inputs!$C$30*NORMSDIST(((LN(Inputs!$C$24/(C$5*Inputs!$C$23))+(Inputs!$C$25+Inputs!$C$29^2/2)*Inputs!$C$22)/(Inputs!$C$29*SQRT(Inputs!$C$22)))-Inputs!$C$29*SQRT(Inputs!$C$22))) -> 37.313325 | D18: =Inputs!$C$11*Inputs!$C$30-Inputs!$C$11/($B18*Inputs!$C$23)*(($B18*Inputs!$C$23)*Inputs!$C$30*NORMSDIST(-(((LN(Inputs!$C$24/($B18*Inputs!$C$23))+(Inputs!$C$25+Inputs!$C$29^2/2)*Inputs!$C$22)/(Inputs!$C$29*SQRT(Inputs!$C$22)))-Inputs!$C$29*SQRT(Inputs!$C$22)))-Inputs!$C$24*NORMSDIST(-((LN(Inputs!$C$24/($B18*Inputs!$C$23))+(Inputs!$C$25+Inputs!$C$29^2/2)*Inputs!$C$22)/(Inputs!$C$29*SQRT(Inputs!$C$22)))))+Inputs!$C$11/(D$5*Inputs!$C$23)*(Inputs!$C$24*NORMSDIST(((LN(Inputs!$C$24/(D$5*Inputs!$C$23))+(Inputs!$C$25+Inputs!$C$29^2/2)*Inputs!$C$22)/(Inputs!$C$29*SQRT(Inputs!$C$22))))-(D$5*Inputs!$C$23)*Inputs!$C$30*NORMSDIST(((LN(Inputs!$C$24/(D$5*Inputs!$C$23))+(Inputs!$C$25+Inputs!$C$29^2/2)*Inputs!$C$22)/(Inputs!$C$29*SQRT(Inputs!$C$22)))-Inputs!$C$29*SQRT(Inputs!$C$22))) -> 36.756856 | E18: =Inputs!$C$11*Inputs!$C$30-Inputs!$C$11/($B18*Inputs!$C$23)*(($B18*Inputs!$C$23)*Inputs!$C$30*NORMSDIST(-(((LN(Inputs!$C$24/($B18*Inputs!$C$23))+(Inputs!$C$25+Inputs!$C$29^2/2)*Inputs!$C$22)/(Inputs!$C$29*SQRT(Inputs!$C$22)))-Inputs!$C$29*SQRT(Inputs!$C$22)))-Inputs!$C$24*NORMSDIST(-((LN(Inputs!$C$24/($B18*Inputs!$C$23))+(Inputs!$C$25+Inputs!$C$29^2/2)*Inputs!$C$22)/(Inputs!$C$29*SQRT(Inputs!$C$22)))))+Inputs!$C$11/(E$5*Inputs!$C$23)*(Inputs!$C$24*NORMSDIST(((LN(Inputs!$C$24/(E$5*Inputs!$C$23))+(Inputs!$C$25+Inputs!$C$29^2/2)*Inputs!$C$22)/(Inputs!$C$29*SQRT(Inputs!$C$22))))-(E$5*Inputs!$C$23)*Inputs!$C$30*NORMSDIST(((LN(Inputs!$C$24/(E$5*Inputs!$C$23))+(Inputs!$C$25+Inputs!$C$29^2/2)*Inputs!$C$22)/(Inputs!$C$29*SQRT(Inputs!$C$22)))-Inputs!$C$29*SQRT(Inputs!$C$22))) -> 36.252222 | F18: =Inputs!$C$11*Inputs!$C$30-Inputs!$C$11/($B18*Inputs!$C$23)*(($B18*Inputs!$C$23)*Inputs!$C$30*NORMSDIST(-(((LN(Inputs!$C$24/($B18*Inputs!$C$23))+(Inputs!$C$25+Inputs!$C$29^2/2)*Inputs!$C$22)/(Inputs!$C$29*SQRT(Inputs!$C$22)))-Inputs!$C$29*SQRT(Inputs!$C$22)))-Inputs!$C$24*NORMSDIST(-((LN(Inputs!$C$24/($B18*Inputs!$C$23))+(Inputs!$C$25+Inputs!$C$29^2/2)*Inputs!$C$22)/(Inputs!$C$29*SQRT(Inputs!$C$22)))))+Inputs!$C$11/(F$5*Inputs!$C$23)*(Inputs!$C$24*NORMSDIST(((LN(Inputs!$C$24/(F$5*Inputs!$C$23))+(Inputs!$C$25+Inputs!$C$29^2/2)*Inputs!$C$22)/(Inputs!$C$29*SQRT(Inputs!$C$22))))-(F$5*Inputs!$C$23)*Inputs!$C$30*NORMSDIST(((LN(Inputs!$C$24/(F$5*Inputs!$C$23))+(Inputs!$C$25+Inputs!$C$29^2/2)*Inputs!$C$22)/(Inputs!$C$29*SQRT(Inputs!$C$22)))-Inputs!$C$29*SQRT(Inputs!$C$22))) -> 35.795011 | G18: =Inputs!$C$11*Inputs!$C$30-Inputs!$C$11/($B18*Inputs!$C$23)*(($B18*Inputs!$C$23)*Inputs!$C$30*NORMSDIST(-(((LN(Inputs!$C$24/($B18*Inputs!$C$23))+(Inputs!$C$25+Inputs!$C$29^2/2)*Inputs!$C$22)/(Inputs!$C$29*SQRT(Inputs!$C$22)))-Inputs!$C$29*SQRT(Inputs!$C$22)))-Inputs!$C$24*NORMSDIST(-((LN(Inputs!$C$24/($B18*Inputs!$C$23))+(Inputs!$C$25+Inputs!$C$29^2/2)*Inputs!$C$22)/(Inputs!$C$29*SQRT(Inputs!$C$22)))))+Inputs!$C$11/(G$5*Inputs!$C$23)*(Inputs!$C$24*NORMSDIST(((LN(Inputs!$C$24/(G$5*Inputs!$C$23))+(Inputs!$C$25+Inputs!$C$29^2/2)*Inputs!$C$22)/(Inputs!$C$29*SQRT(Inputs!$C$22))))-(G$5*Inputs!$C$23)*Inputs!$C$30*NORMSDIST(((LN(Inputs!$C$24/(G$5*Inputs!$C$23))+(Inputs!$C$25+Inputs!$C$29^2/2)*Inputs!$C$22)/(Inputs!$C$29*SQRT(Inputs!$C$22)))-Inputs!$C$29*SQRT(Inputs!$C$22))) -> 35.381136 | H18: =Inputs!$C$11*Inputs!$C$30-Inputs!$C$11/($B18*Inputs!$C$23)*(($B18*Inputs!$C$23)*Inputs!$C$30*NORMSDIST(-(((LN(Inputs!$C$24/($B18*Inputs!$C$23))+(Inputs!$C$25+Inputs!$C$29^2/2)*Inputs!$C$22)/(Inputs!$C$29*SQRT(Inputs!$C$22)))-Inputs!$C$29*SQRT(Inputs!$C$22)))-Inputs!$C$24*NORMSDIST(-((LN(Inputs!$C$24/($B18*Inputs!$C$23))+(Inputs!$C$25+Inputs!$C$29^2/2)*Inputs!$C$22)/(Inputs!$C$29*SQRT(Inputs!$C$22)))))+Inputs!$C$11/(H$5*Inputs!$C$23)*(Inputs!$C$24*NORMSDIST(((LN(Inputs!$C$24/(H$5*Inputs!$C$23))+(Inputs!$C$25+Inputs!$C$29^2/2)*Inputs!$C$22)/(Inputs!$C$29*SQRT(Inputs!$C$22))))-(H$5*Inputs!$C$23)*Inputs!$C$30*NORMSDIST(((LN(Inputs!$C$24/(H$5*Inputs!$C$23))+(Inputs!$C$25+Inputs!$C$29^2/2)*Inputs!$C$22)/(Inputs!$C$29*SQRT(Inputs!$C$22)))-Inputs!$C$29*SQRT(Inputs!$C$22))) -> 35.006808 | I18: =Inputs!$C$11*Inputs!$C$30-Inputs!$C$11/($B18*Inputs!$C$23)*(($B18*Inputs!$C$23)*Inputs!$C$30*NORMSDIST(-(((LN(Inputs!$C$24/($B18*Inputs!$C$23))+(Inputs!$C$25+Inputs!$C$29^2/2)*Inputs!$C$22)/(Inputs!$C$29*SQRT(Inputs!$C$22)))-Inputs!$C$29*SQRT(Inputs!$C$22)))-Inputs!$C$24*NORMSDIST(-((LN(Inputs!$C$24/($B18*Inputs!$C$23))+(Inputs!$C$25+Inputs!$C$29^2/2)*Inputs!$C$22)/(Inputs!$C$29*SQRT(Inputs!$C$22)))))+Inputs!$C$11/(I$5*Inputs!$C$23)*(Inputs!$C$24*NORMSDIST(((LN(Inputs!$C$24/(I$5*Inputs!$C$23))+(Inputs!$C$25+Inputs!$C$29^2/2)*Inputs!$C$22)/(Inputs!$C$29*SQRT(Inputs!$C$22))))-(I$5*Inputs!$C$23)*Inputs!$C$30*NORMSDIST(((LN(Inputs!$C$24/(I$5*Inputs!$C$23))+(Inputs!$C$25+Inputs!$C$29^2/2)*Inputs!$C$22)/(Inputs!$C$29*SQRT(Inputs!$C$22)))-Inputs!$C$29*SQRT(Inputs!$C$22))) -> 34.668528 | J18: =Inputs!$C$11*Inputs!$C$30-Inputs!$C$11/($B18*Inputs!$C$23)*(($B18*Inputs!$C$23)*Inputs!$C$30*NORMSDIST(-(((LN(Inputs!$C$24/($B18*Inputs!$C$23))+(Inputs!$C$25+Inputs!$C$29^2/2)*Inputs!$C$22)/(Inputs!$C$29*SQRT(Inputs!$C$22)))-Inputs!$C$29*SQRT(Inputs!$C$22)))-Inputs!$C$24*NORMSDIST(-((LN(Inputs!$C$24/($B18*Inputs!$C$23))+(Inputs!$C$25+Inputs!$C$29^2/2)*Inputs!$C$22)/(Inputs!$C$29*SQRT(Inputs!$C$22)))))+Inputs!$C$11/(J$5*Inputs!$C$23)*(Inputs!$C$24*NORMSDIST(((LN(Inputs!$C$24/(J$5*Inputs!$C$23))+(Inputs!$C$25+Inputs!$C$29^2/2)*Inputs!$C$22)/(Inputs!$C$29*SQRT(Inputs!$C$22))))-(J$5*Inputs!$C$23)*Inputs!$C$30*NORMSDIST(((LN(Inputs!$C$24/(J$5*Inputs!$C$23))+(Inputs!$C$25+Inputs!$C$29^2/2)*Inputs!$C$22)/(Inputs!$C$29*SQRT(Inputs!$C$22)))-Inputs!$C$29*SQRT(Inputs!$C$22))) -> 34.363068 | ... O18: =Inputs!$C$11*Inputs!$C$30-Inputs!$C$11/($B18*Inputs!$C$23)*(($B18*Inputs!$C$23)*Inputs!$C$30*NORMSDIST(-(((LN(Inputs!$C$24/($B18*Inputs!$C$23))+(Inputs!$C$25+Inputs!$C$29^2/2)*Inputs!$C$22)/(Inputs!$C$29*SQRT(Inputs!$C$22)))-Inputs!$C$29*SQRT(Inputs!$C$22)))-Inputs!$C$24*NORMSDIST(-((LN(Inputs!$C$24/($B18*Inputs!$C$23))+(Inputs!$C$25+Inputs!$C$29^2/2)*Inputs!$C$22)/(Inputs!$C$29*SQRT(Inputs!$C$22)))))+Inputs!$C$11/(O$5*Inputs!$C$23)*(Inputs!$C$24*NORMSDIST(((LN(Inputs!$C$24/(O$5*Inputs!$C$23))+(Inputs!$C$25+Inputs!$C$29^2/2)*Inputs!$C$22)/(Inputs!$C$29*SQRT(Inputs!$C$22))))-(O$5*Inputs!$C$23)*Inputs!$C$30*NORMSDIST(((LN(Inputs!$C$24/(O$5*Inputs!$C$23))+(Inputs!$C$25+Inputs!$C$29^2/2)*Inputs!$C$22)/(Inputs!$C$29*SQRT(Inputs!$C$22)))-Inputs!$C$29*SQRT(Inputs!$C$22))) -> 33.23194
B20: Rows: floor as % of Boeing's $182.01 close. Columns: cap as % of the same close. Actual terms: floor 81.9%, cap 113.7%.
B21: Flat volatility here; the notebook and the web page use the full Boeing surface with skew, which lowers the value of the actual collar by about $0.19.
B22: Shaded: bands where the collar is worth at least as much as a fixed exchange ratio (Pricer!C16).

Sheet Paths
B2: Paths
B3: Every trading day, 1 July 2024 to closing · model value from the Python engine (daily Boeing surface, actual closing date)
B5: Date | C5: Boeing | D5: Spirit | E5: VWAP 15d | F5: If closed that day | G5: Model value | H5: Spread | I5: Implied probability | J5: Below floor
B6: 45474 | C6: 186.7 | D6: 33.97 | E6: 180.525 | F6: =IF(E6="","",IF(E6<=Inputs!$C$12,Inputs!$C$14,IF(E6>=Inputs!$C$13,Inputs!$C$15,Inputs!$C$11/E6))*C6) -> 38.524166 | G6: 37.326 | H6: =IF(OR(G6="",D6=""),"",G6-D6) -> 3.356 | I6: =IF(H6="","",(D6-Inputs!$C$8)/(G6-Inputs!$C$8)) -> 0.61540225 | J6: =IF(C6<=Inputs!$C$12,1,0) -> 0
B7: 45475 | C7: 185.42 | D7: 33.88 | E7: 179.972 | F7: =IF(E7="","",IF(E7<=Inputs!$C$12,Inputs!$C$14,IF(E7>=Inputs!$C$13,Inputs!$C$15,Inputs!$C$11/E7))*C7) -> 38.377609 | H7: =IF(OR(G7="",D7=""),"",G7-D7) | I7: =IF(H7="","",(D7-Inputs!$C$8)/(G7-Inputs!$C$8)) | J7: =IF(C7<=Inputs!$C$12,1,0) -> 0
B8: 45476 | C8: 184.31 | D8: 33.82 | E8: 180.195 | F8: =IF(E8="","",IF(E8<=Inputs!$C$12,Inputs!$C$14,IF(E8>=Inputs!$C$13,Inputs!$C$15,Inputs!$C$11/E8))*C8) -> 38.100655 | G8: 37.012 | H8: =IF(OR(G8="",D8=""),"",G8-D8) -> 3.192 | I8: =IF(H8="","",(D8-Inputs!$C$8)/(G8-Inputs!$C$8)) -> 0.62054208 | J8: =IF(C8<=Inputs!$C$12,1,0) -> 0
B9: 45478 | C9: 184.83 | D9: 34.03 | E9: 179.964 | F9: =IF(E9="","",IF(E9<=Inputs!$C$12,Inputs!$C$14,IF(E9>=Inputs!$C$13,Inputs!$C$15,Inputs!$C$11/E9))*C9) -> 38.257193 | G9: 36.992 | H9: =IF(OR(G9="",D9=""),"",G9-D9) -> 2.962 | I9: =IF(H9="","",(D9-Inputs!$C$8)/(G9-Inputs!$C$8)) -> 0.6470448 | J9: =IF(C9<=Inputs!$C$12,1,0) -> 0
B10: 45481 | C10: 185.84 | D10: 34.37 | E10: 179.768 | F10: =IF(E10="","",IF(E10<=Inputs!$C$12,Inputs!$C$14,IF(E10>=Inputs!$C$13,Inputs!$C$15,Inputs!$C$11/E10))*C10) -> 38.508188 | G10: 37.069 | H10: =IF(OR(G10="",D10=""),"",G10-D10) -> 2.699 | I10: =IF(H10="","",(D10-Inputs!$C$8)/(G10-Inputs!$C$8)) -> 0.6813083 | J10: =IF(C10<=Inputs!$C$12,1,0) -> 0
B11: 45482 | C11: 183.24 | D11: 34.51 | E11: 179.696 | F11: =IF(E11="","",IF(E11<=Inputs!$C$12,Inputs!$C$14,IF(E11>=Inputs!$C$13,Inputs!$C$15,Inputs!$C$11/E11))*C11) -> 37.984652 | H11: =IF(OR(G11="",D11=""),"",G11-D11) | I11: =IF(H11="","",(D11-Inputs!$C$8)/(G11-Inputs!$C$8)) | J11: =IF(C11<=Inputs!$C$12,1,0) -> 0
B12: 45483 | C12: 183.73 | D12: 34.61 | E12: 180.352 | F12: =IF(E12="","",IF(E12<=Inputs!$C$12,Inputs!$C$14,IF(E12>=Inputs!$C$13,Inputs!$C$15,Inputs!$C$11/E12))*C12) -> 37.947694 | G12: 36.915 | H12: =IF(OR(G12="",D12=""),"",G12-D12) -> 2.305 | I12: =IF(H12="","",(D12-Inputs!$C$8)/(G12-Inputs!$C$8)) -> 0.72279014 | J12: =IF(C12<=Inputs!$C$12,1,0) -> 0
B13: 45484 | C13: 183.91 | D13: 34.49 | E13: 180.661 | F13: =IF(E13="","",IF(E13<=Inputs!$C$12,Inputs!$C$14,IF(E13>=Inputs!$C$13,Inputs!$C$15,Inputs!$C$11/E13))*C13) -> 37.919902 | H13: =IF(OR(G13="",D13=""),"",G13-D13) | I13: =IF(H13="","",(D13-Inputs!$C$8)/(G13-Inputs!$C$8)) | J13: =IF(C13<=Inputs!$C$12,1,0) -> 0
B14: 45485 | C14: 182.31 | D14: 34.56 | E14: 180.901 | F14: =IF(E14="","",IF(E14<=Inputs!$C$12,Inputs!$C$14,IF(E14>=Inputs!$C$13,Inputs!$C$15,Inputs!$C$11/E14))*C14) -> 37.540132 | G14: 36.827 | H14: =IF(OR(G14="",D14=""),"",G14-D14) -> 2.267 | I14: =IF(H14="","",(D14-Inputs!$C$8)/(G14-Inputs!$C$8)) -> 0.7244439 | J14: =IF(C14<=Inputs!$C$12,1,0) -> 0
B15: 45488 | C15: 179.11 | D15: 34.69 | E15: 181.454 | F15: =IF(E15="","",IF(E15<=Inputs!$C$12,Inputs!$C$14,IF(E15>=Inputs!$C$13,Inputs!$C$15,Inputs!$C$11/E15))*C15) -> 36.768809 | G15: 36.278 | H15: =IF(OR(G15="",D15=""),"",G15-D15) -> 1.588 | I15: =IF(H15="","",(D15-Inputs!$C$8)/(G15-Inputs!$C$8)) -> 0.79317531 | J15: =IF(C15<=Inputs!$C$12,1,0) -> 0
B16: 45489 | C16: 186.05 | D16: 35.88 | E16: 181.894 | F16: =IF(E16="","",IF(E16<=Inputs!$C$12,Inputs!$C$14,IF(E16>=Inputs!$C$13,Inputs!$C$15,Inputs!$C$11/E16))*C16) -> 38.101106 | H16: =IF(OR(G16="",D16=""),"",G16-D16) | I16: =IF(H16="","",(D16-Inputs!$C$8)/(G16-Inputs!$C$8)) | J16: =IF(C16<=Inputs!$C$12,1,0) -> 0
B17: 45490 | C17: 184.84 | D17: 35.65 | E17: 182.297 | F17: =IF(E17="","",IF(E17<=Inputs!$C$12,Inputs!$C$14,IF(E17>=Inputs!$C$13,Inputs!$C$15,Inputs!$C$11/E17))*C17) -> 37.769629 | G17: 37.07 | H17: =IF(OR(G17="",D17=""),"",G17-D17) -> 1.42 | I17: =IF(H17="","",(D17-Inputs!$C$8)/(G17-Inputs!$C$8)) -> 0.83234947 | J17: =IF(C17<=Inputs!$C$12,1,0) -> 0
B18: 45491 | C18: 180.23 | D18: 35.05 | E18: 182.797 | F18: =IF(E18="","",IF(E18<=Inputs!$C$12,Inputs!$C$14,IF(E18>=Inputs!$C$13,Inputs!$C$15,Inputs!$C$11/E18))*C18) -> 36.726902 | H18: =IF(OR(G18="",D18=""),"",G18-D18) | I18: =IF(H18="","",(D18-Inputs!$C$8)/(G18-Inputs!$C$8)) | J18: =IF(C18<=Inputs!$C$12,1,0) -> 0
B19: 45492 | C19: 179.67 | D19: 35.01 | E19: 183.601 | F19: =IF(E19="","",IF(E19<=Inputs!$C$12,Inputs!$C$14,IF(E19>=Inputs!$C$13,Inputs!$C$15,Inputs!$C$11/E19))*C19) -> 36.452457 | G19: 36.273 | H19: =IF(OR(G19="",D19=""),"",G19-D19) -> 1.263 | I19: =IF(H19="","",(D19-Inputs!$C$8)/(G19-Inputs!$C$8)) -> 0.83539685 | J19: =IF(C19<=Inputs!$C$12,1,0) -> 0
B20: 45495 | C20: 178.9 | D20: 35.04 | E20: 184.047 | F20: =IF(E20="","",IF(E20<=Inputs!$C$12,Inputs!$C$14,IF(E20>=Inputs!$C$13,Inputs!$C$15,Inputs!$C$11/E20))*C20) -> 36.208278 | G20: 36.211 | H20: =IF(OR(G20="",D20=""),"",G20-D20) -> 1.171 | I20: =IF(H20="","",(D20-Inputs!$C$8)/(G20-Inputs!$C$8)) -> 0.84614374 | J20: =IF(C20<=Inputs!$C$12,1,0) -> 0
B21: 45496 | C21: 186.48 | D21: 35.87 | E21: 184.059 | F21: =IF(E21="","",IF(E21<=Inputs!$C$12,Inputs!$C$14,IF(E21>=Inputs!$C$13,Inputs!$C$15,Inputs!$C$11/E21))*C21) -> 37.739964 | H21: =IF(OR(G21="",D21=""),"",G21-D21) | I21: =IF(H21="","",(D21-Inputs!$C$8)/(G21-Inputs!$C$8)) | J21: =IF(C21<=Inputs!$C$12,1,0) -> 0
B22: 45497 | C22: 180.07 | D22: 35.22 | E22: 183.907 | F22: =IF(E22="","",IF(E22<=Inputs!$C$12,Inputs!$C$14,IF(E22>=Inputs!$C$13,Inputs!$C$15,Inputs!$C$11/E22))*C22) -> 36.472823 | G22: 36.404 | H22: =IF(OR(G22="",D22=""),"",G22-D22) -> 1.184 | I22: =IF(H22="","",(D22-Inputs!$C$8)/(G22-Inputs!$C$8)) -> 0.84828293 | J22: =IF(C22<=Inputs!$C$12,1,0) -> 0
B23: 45498 | C23: 184.35 | D23: 35.51 | E23: 183.676 | F23: =IF(E23="","",IF(E23<=Inputs!$C$12,Inputs!$C$14,IF(E23>=Inputs!$C$13,Inputs!$C$15,Inputs!$C$11/E23))*C23) -> 37.386689 | H23: =IF(OR(G23="",D23=""),"",G23-D23) | I23: =IF(H23="","",(D23-Inputs!$C$8)/(G23-Inputs!$C$8)) | J23: =IF(C23<=Inputs!$C$12,1,0) -> 0
B24: 45499 | C24: 186.89 | D24: 35.57 | E24: 183.45 | F24: =IF(E24="","",IF(E24<=Inputs!$C$12,Inputs!$C$14,IF(E24>=Inputs!$C$13,Inputs!$C$15,Inputs!$C$11/E24))*C24) -> 37.948501 | G24: 37.352 | H24: =IF(OR(G24="",D24=""),"",G24-D24) -> 1.782 | I24: =IF(H24="","",(D24-Inputs!$C$8)/(G24-Inputs!$C$8)) -> 0.7963894 | J24: =IF(C24<=Inputs!$C$12,1,0) -> 0
B25: 45502 | C25: 185.43 | D25: 35.47 | E25: 183.469 | F25: =IF(E25="","",IF(E25<=Inputs!$C$12,Inputs!$C$14,IF(E25>=Inputs!$C$13,Inputs!$C$15,Inputs!$C$11/E25))*C25) -> 37.648145 | G25: 37.103 | H25: =IF(OR(G25="",D25=""),"",G25-D25) -> 1.633 | I25: =IF(H25="","",(D25-Inputs!$C$8)/(G25-Inputs!$C$8)) -> 0.80795014 | J25: =IF(C25<=Inputs!$C$12,1,0) -> 0
B26: 45503 | C26: 186.86 | D26: 36.26 | E26: 183.702 | F26: =IF(E26="","",IF(E26<=Inputs!$C$12,Inputs!$C$14,IF(E26>=Inputs!$C$13,Inputs!$C$15,Inputs!$C$11/E26))*C26) -> 37.89036 | H26: =IF(OR(G26="",D26=""),"",G26-D26) | I26: =IF(H26="","",(D26-Inputs!$C$8)/(G26-Inputs!$C$8)) | J26: =IF(C26<=Inputs!$C$12,1,0) -> 0
B27: 45504 | C27: 190.6 | D27: 36.25 | E27: 183.427 | F27: =IF(E27="","",IF(E27<=Inputs!$C$12,Inputs!$C$14,IF(E27>=Inputs!$C$13,Inputs!$C$15,Inputs!$C$11/E27))*C27) -> 38.706679 | H27: =IF(OR(G27="",D27=""),"",G27-D27) | I27: =IF(H27="","",(D27-Inputs!$C$8)/(G27-Inputs!$C$8)) | J27: =IF(C27<=Inputs!$C$12,1,0) -> 0
B28: 45505 | C28: 178.31 | D28: 35.28 | E28: 183.585 | F28: =IF(E28="","",IF(E28<=Inputs!$C$12,Inputs!$C$14,IF(E28>=Inputs!$C$13,Inputs!$C$15,Inputs!$C$11/E28))*C28) -> 36.179685 | H28: =IF(OR(G28="",D28=""),"",G28-D28) | I28: =IF(H28="","",(D28-Inputs!$C$8)/(G28-Inputs!$C$8)) | J28: =IF(C28<=Inputs!$C$12,1,0) -> 0
B29: 45506 | C29: 169.95 | D29: 34.32 | E29: 184.734 | F29: =IF(E29="","",IF(E29<=Inputs!$C$12,Inputs!$C$14,IF(E29>=Inputs!$C$13,Inputs!$C$15,Inputs!$C$11/E29))*C29) -> 34.268935 | H29: =IF(OR(G29="",D29=""),"",G29-D29) | I29: =IF(H29="","",(D29-Inputs!$C$8)/(G29-Inputs!$C$8)) | J29: =IF(C29<=Inputs!$C$12,1,0) -> 0
B30: 45509 | C30: 167.03 | D30: 33.55 | E30: 184.382 | F30: =IF(E30="","",IF(E30<=Inputs!$C$12,Inputs!$C$14,IF(E30>=Inputs!$C$13,Inputs!$C$15,Inputs!$C$11/E30))*C30) -> 33.744441 | H30: =IF(OR(G30="",D30=""),"",G30-D30) | I30: =IF(H30="","",(D30-Inputs!$C$8)/(G30-Inputs!$C$8)) | J30: =IF(C30<=Inputs!$C$12,1,0) -> 0
B31: 45510 | C31: 165.04 | D31: 33.45 | E31: 182.999 | F31: =IF(E31="","",IF(E31<=Inputs!$C$12,Inputs!$C$14,IF(E31>=Inputs!$C$13,Inputs!$C$15,Inputs!$C$11/E31))*C31) -> 33.594391 | H31: =IF(OR(G31="",D31=""),"",G31-D31) | I31: =IF(H31="","",(D31-Inputs!$C$8)/(G31-Inputs!$C$8)) | J31: =IF(C31<=Inputs!$C$12,1,0) -> 0
B32: 45511 | C32: 163.24 | D32: 33.22 | E32: 181.683 | F32: =IF(E32="","",IF(E32<=Inputs!$C$12,Inputs!$C$14,IF(E32>=Inputs!$C$13,Inputs!$C$15,Inputs!$C$11/E32))*C32) -> 33.468679 | H32: =IF(OR(G32="",D32=""),"",G32-D32) | I32: =IF(H32="","",(D32-Inputs!$C$8)/(G32-Inputs!$C$8)) | J32: =IF(C32<=Inputs!$C$12,1,0) -> 0
B33: 45512 | C33: 168.87 | D33: 33.77 | E33: 180.647 | F33: =IF(E33="","",IF(E33<=Inputs!$C$12,Inputs!$C$14,IF(E33>=Inputs!$C$13,Inputs!$C$15,Inputs!$C$11/E33))*C33) -> 34.821544 | H33: =IF(OR(G33="",D33=""),"",G33-D33) | I33: =IF(H33="","",(D33-Inputs!$C$8)/(G33-Inputs!$C$8)) | J33: =IF(C33<=Inputs!$C$12,1,0) -> 0
B34: 45513 | C34: 167.91 | D34: 33.85 | E34: 179.692 | F34: =IF(E34="","",IF(E34<=Inputs!$C$12,Inputs!$C$14,IF(E34>=Inputs!$C$13,Inputs!$C$15,Inputs!$C$11/E34))*C34) -> 34.807601 | H34: =IF(OR(G34="",D34=""),"",G34-D34) | I34: =IF(H34="","",(D34-Inputs!$C$8)/(G34-Inputs!$C$8)) | J34: =IF(C34<=Inputs!$C$12,1,0) -> 0
B35: 45516 | C35: 164.13 | D35: 33.85 | E35: 178.88 | F35: =IF(E35="","",IF(E35<=Inputs!$C$12,Inputs!$C$14,IF(E35>=Inputs!$C$13,Inputs!$C$15,Inputs!$C$11/E35))*C35) -> 34.178458 | G35: 34.014 | H35: =IF(OR(G35="",D35=""),"",G35-D35) -> 0.164 | I35: =IF(H35="","",(D35-Inputs!$C$8)/(G35-Inputs!$C$8)) -> 0.96970816 | J35: =IF(C35<=Inputs!$C$12,1,0) -> 0
B36: 45517 | C36: 168.76 | D36: 34.2 | E36: 178.508 | F36: =IF(E36="","",IF(E36<=Inputs!$C$12,Inputs!$C$14,IF(E36>=Inputs!$C$13,Inputs!$C$15,Inputs!$C$11/E36))*C36) -> 35.215845 | H36: =IF(OR(G36="",D36=""),"",G36-D36) | I36: =IF(H36="","",(D36-Inputs!$C$8)/(G36-Inputs!$C$8)) | J36: =IF(C36<=Inputs!$C$12,1,0) -> 0
B37: 45518 | C37: 168.5 | D37: 34.21 | E37: 177.88 | F37: =IF(E37="","",IF(E37<=Inputs!$C$12,Inputs!$C$14,IF(E37>=Inputs!$C$13,Inputs!$C$15,Inputs!$C$11/E37))*C37) -> 35.285726 | G37: 34.731 | H37: =IF(OR(G37="",D37=""),"",G37-D37) -> 0.521 | I37: =IF(H37="","",(D37-Inputs!$C$8)/(G37-Inputs!$C$8)) -> 0.91502202 | J37: =IF(C37<=Inputs!$C$12,1,0) -> 0
B38: 45519 | C38: 176.41 | D38: 34.69 | E38: 176.767 | F38: =IF(E38="","",IF(E38<=Inputs!$C$12,Inputs!$C$14,IF(E38>=Inputs!$C$13,Inputs!$C$15,Inputs!$C$11/E38))*C38) -> 37.17477 | H38: =IF(OR(G38="",D38=""),"",G38-D38) | I38: =IF(H38="","",(D38-Inputs!$C$8)/(G38-Inputs!$C$8)) | J38: =IF(C38<=Inputs!$C$12,1,0) -> 0
B39: 45520 | C39: 179.99 | D39: 35.27 | E39: 176.199 | F39: =IF(E39="","",IF(E39<=Inputs!$C$12,Inputs!$C$14,IF(E39>=Inputs!$C$13,Inputs!$C$15,Inputs!$C$11/E39))*C39) -> 38.05145 | G39: 36.256 | H39: =IF(OR(G39="",D39=""),"",G39-D39) -> 0.986 | I39: =IF(H39="","",(D39-Inputs!$C$8)/(G39-Inputs!$C$8)) -> 0.87121212 | J39: =IF(C39<=Inputs!$C$12,1,0) -> 0
B40: 45523 | C40: 179.64 | D40: 35.13 | E40: 175.644 | F40: =IF(E40="","",IF(E40<=Inputs!$C$12,Inputs!$C$14,IF(E40>=Inputs!$C$13,Inputs!$C$15,Inputs!$C$11/E40))*C40) -> 38.097458 | G40: 36.267 | H40: =IF(OR(G40="",D40=""),"",G40-D40) -> 1.137 | I40: =IF(H40="","",(D40-Inputs!$C$8)/(G40-Inputs!$C$8)) -> 0.8517021 | J40: =IF(C40<=Inputs!$C$12,1,0) -> 0
B41: 45524 | C41: 172.1 | D41: 34.63 | E41: 175.192 | F41: =IF(E41="","",IF(E41<=Inputs!$C$12,Inputs!$C$14,IF(E41>=Inputs!$C$13,Inputs!$C$15,Inputs!$C$11/E41))*C41) -> 36.592567 | H41: =IF(OR(G41="",D41=""),"",G41-D41) | I41: =IF(H41="","",(D41-Inputs!$C$8)/(G41-Inputs!$C$8)) | J41: =IF(C41<=Inputs!$C$12,1,0) -> 0
B42: 45525 | C42: 173.43 | D42: 34.84 | E42: 174.997 | F42: =IF(E42="","",IF(E42<=Inputs!$C$12,Inputs!$C$14,IF(E42>=Inputs!$C$13,Inputs!$C$15,Inputs!$C$11/E42))*C42) -> 36.916447 | G42: 35.513 | H42: =IF(OR(G42="",D42=""),"",G42-D42) -> 0.673 | I42: =IF(H42="","",(D42-Inputs!$C$8)/(G42-Inputs!$C$8)) -> 0.90264719 | J42: =IF(C42<=Inputs!$C$12,1,0) -> 0
B43: 45526 | C43: 172.76 | D43: 34.86 | E43: 174.342 | F43: =IF(E43="","",IF(E43<=Inputs!$C$12,Inputs!$C$14,IF(E43>=Inputs!$C$13,Inputs!$C$15,Inputs!$C$11/E43))*C43) -> 36.911989 | H43: =IF(OR(G43="",D43=""),"",G43-D43) | I43: =IF(H43="","",(D43-Inputs!$C$8)/(G43-Inputs!$C$8)) | J43: =IF(C43<=Inputs!$C$12,1,0) -> 0
B44: 45527 | C44: 174.96 | D44: 35.15 | E44: 171.803 | F44: =IF(E44="","",IF(E44<=Inputs!$C$12,Inputs!$C$14,IF(E44>=Inputs!$C$13,Inputs!$C$15,Inputs!$C$11/E44))*C44) -> 37.934495 | G44: 35.72 | H44: =IF(OR(G44="",D44=""),"",G44-D44) -> 0.57 | I44: =IF(H44="","",(D44-Inputs!$C$8)/(G44-Inputs!$C$8)) -> 0.91994382 | J44: =IF(C44<=Inputs!$C$12,1,0) -> 0
B45: 45530 | C45: 173.48 | D45: 34.84 | E45: 170.283 | F45: =IF(E45="","",IF(E45<=Inputs!$C$12,Inputs!$C$14,IF(E45>=Inputs!$C$13,Inputs!$C$15,Inputs!$C$11/E45))*C45) -> 37.949355 | G45: 35.514 | H45: =IF(OR(G45="",D45=""),"",G45-D45) -> 0.674 | I45: =IF(H45="","",(D45-Inputs!$C$8)/(G45-Inputs!$C$8)) -> 0.90251663 | J45: =IF(C45<=Inputs!$C$12,1,0) -> 0
B46: 45531 | C46: 173.05 | D46: 35 | E46: 170.444 | F46: =IF(E46="","",IF(E46<=Inputs!$C$12,Inputs!$C$14,IF(E46>=Inputs!$C$13,Inputs!$C$15,Inputs!$C$11/E46))*C46) -> 37.819533 | H46: =IF(OR(G46="",D46=""),"",G46-D46) | I46: =IF(H46="","",(D46-Inputs!$C$8)/(G46-Inputs!$C$8)) | J46: =IF(C46<=Inputs!$C$12,1,0) -> 0
B47: 45532 | C47: 170.71 | D47: 34.68 | E47: 171.17 | F47: =IF(E47="","",IF(E47<=Inputs!$C$12,Inputs!$C$14,IF(E47>=Inputs!$C$13,Inputs!$C$15,Inputs!$C$11/E47))*C47) -> 37.149895 | G47: 35.163 | H47: =IF(OR(G47="",D47=""),"",G47-D47) -> 0.483 | I47: =IF(H47="","",(D47-Inputs!$C$8)/(G47-Inputs!$C$8)) -> 0.92640561 | J47: =IF(C47<=Inputs!$C$12,1,0) -> 0
B48: 45533 | C48: 172.26 | D48: 34.94 | E48: 171.647 | F48: =IF(E48="","",IF(E48<=Inputs!$C$12,Inputs!$C$14,IF(E48>=Inputs!$C$13,Inputs!$C$15,Inputs!$C$11/E48))*C48) -> 37.38303 | H48: =IF(OR(G48="",D48=""),"",G48-D48) | I48: =IF(H48="","",(D48-Inputs!$C$8)/(G48-Inputs!$C$8)) | J48: =IF(C48<=Inputs!$C$12,1,0) -> 0
B49: 45534 | C49: 173.74 | D49: 35.21 | E49: 172.116 | F49: =IF(E49="","",IF(E49<=Inputs!$C$12,Inputs!$C$14,IF(E49>=Inputs!$C$13,Inputs!$C$15,Inputs!$C$11/E49))*C49) -> 37.601472 | G49: 35.554 | H49: =IF(OR(G49="",D49=""),"",G49-D49) -> 0.344 | I49: =IF(H49="","",(D49-Inputs!$C$8)/(G49-Inputs!$C$8)) -> 0.95053207 | J49: =IF(C49<=Inputs!$C$12,1,0) -> 0
B50: 45538 | C50: 161.02 | D50: 33.32 | E50: 172.546 | F50: =IF(E50="","",IF(E50<=Inputs!$C$12,Inputs!$C$14,IF(E50>=Inputs!$C$13,Inputs!$C$15,Inputs!$C$11/E50))*C50) -> 34.761716 | H50: =IF(OR(G50="",D50=""),"",G50-D50) | I50: =IF(H50="","",(D50-Inputs!$C$8)/(G50-Inputs!$C$8)) | J50: =IF(C50<=Inputs!$C$12,1,0) -> 0
B51: 45539 | C51: 163.22 | D51: 33.75 | E51: 172.793 | F51: =IF(E51="","",IF(E51<=Inputs!$C$12,Inputs!$C$14,IF(E51>=Inputs!$C$13,Inputs!$C$15,Inputs!$C$11/E51))*C51) -> 35.186292 | G51: 34.019 | H51: =IF(OR(G51="",D51=""),"",G51-D51) -> 0.269 | I51: =IF(H51="","",(D51-Inputs!$C$8)/(G51-Inputs!$C$8)) -> 0.95035984 | J51: =IF(C51<=Inputs!$C$12,1,0) -> 0
B52: 45540 | C52: 162.15 | D52: 33.69 | E52: 171.162 | F52: =IF(E52="","",IF(E52<=Inputs!$C$12,Inputs!$C$14,IF(E52>=Inputs!$C$13,Inputs!$C$15,Inputs!$C$11/E52))*C52) -> 35.288718 | H52: =IF(OR(G52="",D52=""),"",G52-D52) | I52: =IF(H52="","",(D52-Inputs!$C$8)/(G52-Inputs!$C$8)) | J52: =IF(C52<=Inputs!$C$12,1,0) -> 0
B53: 45541 | C53: 157.62 | D53: 32.86 | E53: 170.841 | F53: =IF(E53="","",IF(E53<=Inputs!$C$12,Inputs!$C$14,IF(E53>=Inputs!$C$13,Inputs!$C$15,Inputs!$C$11/E53))*C53) -> 34.367306 | G53: 33.25 | H53: =IF(OR(G53="",D53=""),"",G53-D53) -> 0.39 | I53: =IF(H53="","",(D53-Inputs!$C$8)/(G53-Inputs!$C$8)) -> 0.91612903 | J53: =IF(C53<=Inputs!$C$12,1,0) -> 0
B54: 45544 | C54: 162.91 | D54: 33.74 | E54: 170.485 | F54: =IF(E54="","",IF(E54<=Inputs!$C$12,Inputs!$C$14,IF(E54>=Inputs!$C$13,Inputs!$C$15,Inputs!$C$11/E54))*C54) -> 35.594906 | G54: 34.01 | H54: =IF(OR(G54="",D54=""),"",G54-D54) -> 0.27 | I54: =IF(H54="","",(D54-Inputs!$C$8)/(G54-Inputs!$C$8)) -> 0.95009242 | J54: =IF(C54<=Inputs!$C$12,1,0) -> 0
B55: 45545 | C55: 160.07 | D55: 33.39 | E55: 169.333 | F55: =IF(E55="","",IF(E55<=Inputs!$C$12,Inputs!$C$14,IF(E55>=Inputs!$C$13,Inputs!$C$15,Inputs!$C$11/E55))*C55) -> 35.212318 | H55: =IF(OR(G55="",D55=""),"",G55-D55) | I55: =IF(H55="","",(D55-Inputs!$C$8)/(G55-Inputs!$C$8)) | J55: =IF(C55<=Inputs!$C$12,1,0) -> 0
B56: 45546 | C56: 161.33 | D56: 33.71 | E56: 167.975 | F56: =IF(E56="","",IF(E56<=Inputs!$C$12,Inputs!$C$14,IF(E56>=Inputs!$C$13,Inputs!$C$15,Inputs!$C$11/E56))*C56) -> 35.77641 | G56: 33.75 | H56: =IF(OR(G56="",D56=""),"",G56-D56) -> 0.04 | I56: =IF(H56="","",(D56-Inputs!$C$8)/(G56-Inputs!$C$8)) -> 0.99223301 | J56: =IF(C56<=Inputs!$C$12,1,0) -> 0
B57: 45547 | C57: 162.77 | D57: 33.7 | E57: 167.002 | F57: =IF(E57="","",IF(E57<=Inputs!$C$12,Inputs!$C$14,IF(E57>=Inputs!$C$13,Inputs!$C$15,Inputs!$C$11/E57))*C57) -> 36.306047 | G57: 33.996 | H57: =IF(OR(G57="",D57=""),"",G57-D57) -> 0.296 | I57: =IF(H57="","",(D57-Inputs!$C$8)/(G57-Inputs!$C$8)) -> 0.94514455 | J57: =IF(C57<=Inputs!$C$12,1,0) -> 0
B58: 45548 | C58: 156.77 | D58: 33.27 | E58: 165.811 | F58: =IF(E58="","",IF(E58<=Inputs!$C$12,Inputs!$C$14,IF(E58>=Inputs!$C$13,Inputs!$C$15,Inputs!$C$11/E58))*C58) -> 35.218909 | G58: 33.068 | H58: =IF(OR(G58="",D58=""),"",G58-D58) -> -0.202 | I58: =IF(H58="","",(D58-Inputs!$C$8)/(G58-Inputs!$C$8)) -> 1.0452104 | J58: =IF(C58<=Inputs!$C$12,1,0) -> 0
B59: 45551 | C59: 155.55 | D59: 32.87 | E59: 165.247 | F59: =IF(E59="","",IF(E59<=Inputs!$C$12,Inputs!$C$14,IF(E59>=Inputs!$C$13,Inputs!$C$15,Inputs!$C$11/E59))*C59) -> 35.064101 | G59: 32.939 | H59: =IF(OR(G59="",D59=""),"",G59-D59) -> 0.069 | I59: =IF(H59="","",(D59-Inputs!$C$8)/(G59-Inputs!$C$8)) -> 0.98409772 | J59: =IF(C59<=Inputs!$C$12,1,0) -> 0
B60: 45552 | C60: 156.39 | D60: 33.05 | E60: 163.812 | F60: =IF(E60="","",IF(E60<=Inputs!$C$12,Inputs!$C$14,IF(E60>=Inputs!$C$13,Inputs!$C$15,Inputs!$C$11/E60))*C60) -> 35.562276 | G60: 32.992 | H60: =IF(OR(G60="",D60=""),"",G60-D60) -> -0.058 | I60: =IF(H60="","",(D60-Inputs!$C$8)/(G60-Inputs!$C$8)) -> 1.0132058 | J60: =IF(C60<=Inputs!$C$12,1,0) -> 0
B61: 45553 | C61: 155.11 | D61: 32.93 | E61: 162.669 | F61: =IF(E61="","",IF(E61<=Inputs!$C$12,Inputs!$C$14,IF(E61>=Inputs!$C$13,Inputs!$C$15,Inputs!$C$11/E61))*C61) -> 35.519045 | G61: 32.844 | H61: =IF(OR(G61="",D61=""),"",G61-D61) -> -0.086 | I61: =IF(H61="","",(D61-Inputs!$C$8)/(G61-Inputs!$C$8)) -> 1.0202639 | J61: =IF(C61<=Inputs!$C$12,1,0) -> 0
B62: 45554 | C62: 154.59 | D62: 32.79 | E62: 161.888 | F62: =IF(E62="","",IF(E62<=Inputs!$C$12,Inputs!$C$14,IF(E62>=Inputs!$C$13,Inputs!$C$15,Inputs!$C$11/E62))*C62) -> 35.57075 | G62: 32.913 | H62: =IF(OR(G62="",D62=""),"",G62-D62) -> 0.123 | I62: =IF(H62="","",(D62-Inputs!$C$8)/(G62-Inputs!$C$8)) -> 0.97148157 | J62: =IF(C62<=Inputs!$C$12,1,0) -> 0
B63: 45555 | C63: 153.29 | D63: 33.12 | E63: 161.239 | F63: =IF(E63="","",IF(E63<=Inputs!$C$12,Inputs!$C$14,IF(E63>=Inputs!$C$13,Inputs!$C$15,Inputs!$C$11/E63))*C63) -> 35.413594 | G63: 32.686 | H63: =IF(OR(G63="",D63=""),"",G63-D63) -> -0.434 | I63: =IF(H63="","",(D63-Inputs!$C$8)/(G63-Inputs!$C$8)) -> 1.1062163 | J63: =IF(C63<=Inputs!$C$12,1,0) -> 0
B64: 45558 | C64: 156.3 | D64: 33.48 | E64: 160.428 | F64: =IF(E64="","",IF(E64<=Inputs!$C$12,Inputs!$C$14,IF(E64>=Inputs!$C$13,Inputs!$C$15,Inputs!$C$11/E64))*C64) -> 36.291514 | G64: 33.163 | H64: =IF(OR(G64="",D64=""),"",G64-D64) -> -0.317 | I64: =IF(H64="","",(D64-Inputs!$C$8)/(G64-Inputs!$C$8)) -> 1.0694718 | J64: =IF(C64<=Inputs!$C$12,1,0) -> 0
B65: 45559 | C65: 155.81 | D65: 33.22 | E65: 159.36 | F65: =IF(E65="","",IF(E65<=Inputs!$C$12,Inputs!$C$14,IF(E65>=Inputs!$C$13,Inputs!$C$15,Inputs!$C$11/E65))*C65) -> 36.420196 | G65: 33.083 | H65: =IF(OR(G65="",D65=""),"",G65-D65) -> -0.137 | I65: =IF(H65="","",(D65-Inputs!$C$8)/(G65-Inputs!$C$8)) -> 1.0305599 | J65: =IF(C65<=Inputs!$C$12,1,0) -> 0
B66: 45560 | C66: 152.22 | D66: 32.84 | E66: 158.627 | F66: =IF(E66="","",IF(E66<=Inputs!$C$12,Inputs!$C$14,IF(E66>=Inputs!$C$13,Inputs!$C$15,Inputs!$C$11/E66))*C66) -> 35.745459 | G66: 32.518 | H66: =IF(OR(G66="",D66=""),"",G66-D66) -> -0.322 | I66: =IF(H66="","",(D66-Inputs!$C$8)/(G66-Inputs!$C$8)) -> 1.0821848 | J66: =IF(C66<=Inputs!$C$12,1,0) -> 0
B67: 45561 | C67: 154.58 | D67: 33.08 | E67: 157.848 | F67: =IF(E67="","",IF(E67<=Inputs!$C$12,Inputs!$C$14,IF(E67>=Inputs!$C$13,Inputs!$C$15,Inputs!$C$11/E67))*C67) -> 36.478796 | G67: 32.869 | H67: =IF(OR(G67="",D67=""),"",G67-D67) -> -0.211 | I67: =IF(H67="","",(D67-Inputs!$C$8)/(G67-Inputs!$C$8)) -> 1.0494261 | J67: =IF(C67<=Inputs!$C$12,1,0) -> 0
... B99: 45607 | C99: 148.96 | D99: 31.01 | E99: 153.207 | F99: =IF(E99="","",IF(E99<=Inputs!$C$12,Inputs!$C$14,IF(E99>=Inputs!$C$13,Inputs!$C$15,Inputs!$C$11/E99))*C99) -> 36.217405 | G99: 32.635 | H99: =IF(OR(G99="",D99=""),"",G99-D99) -> 1.625 | I99: =IF(H99="","",(D99-Inputs!$C$8)/(G99-Inputs!$C$8)) -> 0.59727385 | J99: =IF(C99<=Inputs!$C$12,1,0) -> 1
B100: 45608 | C100: 145.17 | D100: 31.04 | E100: 153.094 | F100: =IF(E100="","",IF(E100<=Inputs!$C$12,Inputs!$C$14,IF(E100>=Inputs!$C$13,Inputs!$C$15,Inputs!$C$11/E100))*C100) -> 35.321975 | H100: =IF(OR(G100="",D100=""),"",G100-D100) | I100: =IF(H100="","",(D100-Inputs!$C$8)/(G100-Inputs!$C$8)) | J100: =IF(C100<=Inputs!$C$12,1,0) -> 1
B101: 45609 | C101: 139.97 | D101: 30.41 | E101: 152.662 | F101: =IF(E101="","",IF(E101<=Inputs!$C$12,Inputs!$C$14,IF(E101>=Inputs!$C$13,Inputs!$C$15,Inputs!$C$11/E101))*C101) -> 34.153113 | G101: 31.268 | H101: =IF(OR(G101="",D101=""),"",G101-D101) -> 0.858 | I101: =IF(H101="","",(D101-Inputs!$C$8)/(G101-Inputs!$C$8)) -> 0.67841079 | J101: =IF(C101<=Inputs!$C$12,1,0) -> 1
B102: 45610 | C102: 138.14 | D102: 30.22 | E102: 152.165 | F102: =IF(E102="","",IF(E102<=Inputs!$C$12,Inputs!$C$14,IF(E102>=Inputs!$C$13,Inputs!$C$15,Inputs!$C$11/E102))*C102) -> 33.816679 | G102: 30.921 | H102: =IF(OR(G102="",D102=""),"",G102-D102) -> 0.701 | I102: =IF(H102="","",(D102-Inputs!$C$8)/(G102-Inputs!$C$8)) -> 0.69797501 | J102: =IF(C102<=Inputs!$C$12,1,0) -> 1
B103: 45611 | C103: 140.19 | D103: 30.7 | E103: 151.255 | F103: =IF(E103="","",IF(E103<=Inputs!$C$12,Inputs!$C$14,IF(E103>=Inputs!$C$13,Inputs!$C$15,Inputs!$C$11/E103))*C103) -> 34.524991 | G103: 31.263 | H103: =IF(OR(G103="",D103=""),"",G103-D103) -> 0.563 | I103: =IF(H103="","",(D103-Inputs!$C$8)/(G103-Inputs!$C$8)) -> 0.7885843 | J103: =IF(C103<=Inputs!$C$12,1,0) -> 1
B104: 45614 | C104: 143.87 | D104: 31.34 | E104: 150.613 | F104: =IF(E104="","",IF(E104<=Inputs!$C$12,Inputs!$C$14,IF(E104>=Inputs!$C$13,Inputs!$C$15,Inputs!$C$11/E104))*C104) -> 35.582304 | G104: 32.016 | H104: =IF(OR(G104="",D104=""),"",G104-D104) -> 0.676 | I104: =IF(H104="","",(D104-Inputs!$C$8)/(G104-Inputs!$C$8)) -> 0.80210773 | J104: =IF(C104<=Inputs!$C$12,1,0) -> 1
B105: 45615 | C105: 145.6 | D105: 31.84 | E105: 150.115 | F105: =IF(E105="","",IF(E105<=Inputs!$C$12,Inputs!$C$14,IF(E105>=Inputs!$C$13,Inputs!$C$15,Inputs!$C$11/E105))*C105) -> 36.129634 | G105: 32.202 | H105: =IF(OR(G105="",D105=""),"",G105-D105) -> 0.362 | I105: =IF(H105="","",(D105-Inputs!$C$8)/(G105-Inputs!$C$8)) -> 0.89950028 | J105: =IF(C105<=Inputs!$C$12,1,0) -> 1
B106: 45616 | C106: 146.08 | D106: 31.93 | E106: 149.707 | F106: =IF(E106="","",IF(E106<=Inputs!$C$12,Inputs!$C$14,IF(E106>=Inputs!$C$13,Inputs!$C$15,Inputs!$C$11/E106))*C106) -> 36.347532 | G106: 32.199 | H106: =IF(OR(G106="",D106=""),"",G106-D106) -> 0.269 | I106: =IF(H106="","",(D106-Inputs!$C$8)/(G106-Inputs!$C$8)) -> 0.92525702 | J106: =IF(C106<=Inputs!$C$12,1,0) -> 1
B107: 45617 | C107: 143.41 | D107: 31.38 | E107: 148.992 | F107: =IF(E107="","",IF(E107<=Inputs!$C$12,Inputs!$C$14,IF(E107>=Inputs!$C$13,Inputs!$C$15,Inputs!$C$11/E107))*C107) -> 35.8525 | G107: 31.86 | H107: =IF(OR(G107="",D107=""),"",G107-D107) -> 0.48 | I107: =IF(H107="","",(D107-Inputs!$C$8)/(G107-Inputs!$C$8)) -> 0.85276074 | J107: =IF(C107<=Inputs!$C$12,1,0) -> 1
B108: 45618 | C108: 149.29 | D108: 32.5 | E108: 147.78 | F108: =IF(E108="","",IF(E108<=Inputs!$C$12,Inputs!$C$14,IF(E108>=Inputs!$C$13,Inputs!$C$15,Inputs!$C$11/E108))*C108) -> 37.3225 | G108: 32.719 | H108: =IF(OR(G108="",D108=""),"",G108-D108) -> 0.219 | I108: =IF(H108="","",(D108-Inputs!$C$8)/(G108-Inputs!$C$8)) -> 0.94683176 | J108: =IF(C108<=Inputs!$C$12,1,0) -> 0
B109: 45621 | C109: 153.1 | D109: 32.6 | E109: 147.278 | F109: =IF(E109="","",IF(E109<=Inputs!$C$12,Inputs!$C$14,IF(E109>=Inputs!$C$13,Inputs!$C$15,Inputs!$C$11/E109))*C109) -> 38.275 | G109: 33.266 | H109: =IF(OR(G109="",D109=""),"",G109-D109) -> 0.666 | I109: =IF(H109="","",(D109-Inputs!$C$8)/(G109-Inputs!$C$8)) -> 0.85726532 | J109: =IF(C109<=Inputs!$C$12,1,0) -> 0
B110: 45622 | C110: 150.76 | D110: 32.35 | E110: 146.729 | F110: =IF(E110="","",IF(E110<=Inputs!$C$12,Inputs!$C$14,IF(E110>=Inputs!$C$13,Inputs!$C$15,Inputs!$C$11/E110))*C110) -> 37.69 | G110: 32.963 | H110: =IF(OR(G110="",D110=""),"",G110-D110) -> 0.613 | I110: =IF(H110="","",(D110-Inputs!$C$8)/(G110-Inputs!$C$8)) -> 0.85950034 | J110: =IF(C110<=Inputs!$C$12,1,0) -> 0
B111: 45623 | C111: 152.4 | D111: 32.53 | E111: 146.655 | F111: =IF(E111="","",IF(E111<=Inputs!$C$12,Inputs!$C$14,IF(E111>=Inputs!$C$13,Inputs!$C$15,Inputs!$C$11/E111))*C111) -> 38.1 | G111: 33.261 | H111: =IF(OR(G111="",D111=""),"",G111-D111) -> 0.731 | I111: =IF(H111="","",(D111-Inputs!$C$8)/(G111-Inputs!$C$8)) -> 0.8431667 | J111: =IF(C111<=Inputs!$C$12,1,0) -> 0
B112: 45625 | C112: 155.44 | D112: 32.36 | E112: 146.106 | F112: =IF(E112="","",IF(E112<=Inputs!$C$12,Inputs!$C$14,IF(E112>=Inputs!$C$13,Inputs!$C$15,Inputs!$C$11/E112))*C112) -> 38.86 | G112: 33.622 | H112: =IF(OR(G112="",D112=""),"",G112-D112) -> 1.262 | I112: =IF(H112="","",(D112-Inputs!$C$8)/(G112-Inputs!$C$8)) -> 0.74870569 | J112: =IF(C112<=Inputs!$C$12,1,0) -> 0
... B129: 45650 | C129: 179.34 | D129: 33.57 | E129: 167.175 | F129: =IF(E129="","",IF(E129<=Inputs!$C$12,Inputs!$C$14,IF(E129>=Inputs!$C$13,Inputs!$C$15,Inputs!$C$11/E129))*C129) -> 39.96061 | G129: 36.599 | H129: =IF(OR(G129="",D129=""),"",G129-D129) -> 3.029 | I129: =IF(H129="","",(D129-Inputs!$C$8)/(G129-Inputs!$C$8)) -> 0.62132767 | J129: =IF(C129<=Inputs!$C$12,1,0) -> 0
B130: 45652 | C130: 180.38 | D130: 33.87 | E130: 168.161 | F130: =IF(E130="","",IF(E130<=Inputs!$C$12,Inputs!$C$14,IF(E130>=Inputs!$C$13,Inputs!$C$15,Inputs!$C$11/E130))*C130) -> 39.956678 | H130: =IF(OR(G130="",D130=""),"",G130-D130) | I130: =IF(H130="","",(D130-Inputs!$C$8)/(G130-Inputs!$C$8)) | J130: =IF(C130<=Inputs!$C$12,1,0) -> 0
B131: 45653 | C131: 180.72 | D131: 33.98 | E131: 168.863 | F131: =IF(E131="","",IF(E131<=Inputs!$C$12,Inputs!$C$14,IF(E131>=Inputs!$C$13,Inputs!$C$15,Inputs!$C$11/E131))*C131) -> 39.865571 | G131: 36.784 | H131: =IF(OR(G131="",D131=""),"",G131-D131) -> 2.804 | I131: =IF(H131="","",(D131-Inputs!$C$8)/(G131-Inputs!$C$8)) -> 0.65738025 | J131: =IF(C131<=Inputs!$C$12,1,0) -> 0
B132: 45656 | C132: 176.55 | D132: 33.87 | E132: 169.842 | F132: =IF(E132="","",IF(E132<=Inputs!$C$12,Inputs!$C$14,IF(E132>=Inputs!$C$13,Inputs!$C$15,Inputs!$C$11/E132))*C132) -> 38.721209 | G132: 36.247 | H132: =IF(OR(G132="",D132=""),"",G132-D132) -> 2.377 | I132: =IF(H132="","",(D132-Inputs!$C$8)/(G132-Inputs!$C$8)) -> 0.68915915 | J132: =IF(C132<=Inputs!$C$12,1,0) -> 0
B133: 45657 | C133: 177 | D133: 34.08 | E133: 170.749 | F133: =IF(E133="","",IF(E133<=Inputs!$C$12,Inputs!$C$14,IF(E133>=Inputs!$C$13,Inputs!$C$15,Inputs!$C$11/E133))*C133) -> 38.613696 | G133: 36.303 | H133: =IF(OR(G133="",D133=""),"",G133-D133) -> 2.223 | I133: =IF(H133="","",(D133-Inputs!$C$8)/(G133-Inputs!$C$8)) -> 0.71141114 | J133: =IF(C133<=Inputs!$C$12,1,0) -> 0
B134: 45659 | C134: 171.87 | D134: 33.54 | E134: 171.831 | F134: =IF(E134="","",IF(E134<=Inputs!$C$12,Inputs!$C$14,IF(E134>=Inputs!$C$13,Inputs!$C$15,Inputs!$C$11/E134))*C134) -> 37.258455 | G134: 35.687 | H134: =IF(OR(G134="",D134=""),"",G134-D134) -> 2.147 | I134: =IF(H134="","",(D134-Inputs!$C$8)/(G134-Inputs!$C$8)) -> 0.69705094 | J134: =IF(C134<=Inputs!$C$12,1,0) -> 0
B135: 45660 | C135: 169.9 | D135: 33.07 | E135: 173.127 | F135: =IF(E135="","",IF(E135<=Inputs!$C$12,Inputs!$C$14,IF(E135>=Inputs!$C$13,Inputs!$C$15,Inputs!$C$11/E135))*C135) -> 36.555679 | G135: 35.427 | H135: =IF(OR(G135="",D135=""),"",G135-D135) -> 2.357 | I135: =IF(H135="","",(D135-Inputs!$C$8)/(G135-Inputs!$C$8)) -> 0.65475319 | J135: =IF(C135<=Inputs!$C$12,1,0) -> 0
B136: 45663 | C136: 170.78 | D136: 33.3 | E136: 174.263 | F136: =IF(E136="","",IF(E136<=Inputs!$C$12,Inputs!$C$14,IF(E136>=Inputs!$C$13,Inputs!$C$15,Inputs!$C$11/E136))*C136) -> 36.505483 | G136: 35.559 | H136: =IF(OR(G136="",D136=""),"",G136-D136) -> 2.259 | I136: =IF(H136="","",(D136-Inputs!$C$8)/(G136-Inputs!$C$8)) -> 0.67538439 | J136: =IF(C136<=Inputs!$C$12,1,0) -> 0
B137: 45664 | C137: 172.51 | D137: 33.62 | E137: 174.662 | F137: =IF(E137="","",IF(E137<=Inputs!$C$12,Inputs!$C$14,IF(E137>=Inputs!$C$13,Inputs!$C$15,Inputs!$C$11/E137))*C137) -> 36.791045 | G137: 35.757 | H137: =IF(OR(G137="",D137=""),"",G137-D137) -> 2.137 | I137: =IF(H137="","",(D137-Inputs!$C$8)/(G137-Inputs!$C$8)) -> 0.70141121 | J137: =IF(C137<=Inputs!$C$12,1,0) -> 0
B138: 45665 | C138: 171.76 | D138: 33.91 | E138: 174.946 | F138: =IF(E138="","",IF(E138<=Inputs!$C$12,Inputs!$C$14,IF(E138>=Inputs!$C$13,Inputs!$C$15,Inputs!$C$11/E138))*C138) -> 36.571628 | G138: 35.728 | H138: =IF(OR(G138="",D138=""),"",G138-D138) -> 1.818 | I138: =IF(H138="","",(D138-Inputs!$C$8)/(G138-Inputs!$C$8)) -> 0.74494949 | J138: =IF(C138<=Inputs!$C$12,1,0) -> 0
B139: 45667 | C139: 172 | D139: 34.21 | E139: 175.207 | F139: =IF(E139="","",IF(E139<=Inputs!$C$12,Inputs!$C$14,IF(E139>=Inputs!$C$13,Inputs!$C$15,Inputs!$C$11/E139))*C139) -> 36.568174 | G139: 35.654 | H139: =IF(OR(G139="",D139=""),"",G139-D139) -> 1.444 | I139: =IF(H139="","",(D139-Inputs!$C$8)/(G139-Inputs!$C$8)) -> 0.79529345 | J139: =IF(C139<=Inputs!$C$12,1,0) -> 0
B140: 45670 | C140: 170.57 | D140: 34.13 | E140: 175.392 | F140: =IF(E140="","",IF(E140<=Inputs!$C$12,Inputs!$C$14,IF(E140>=Inputs!$C$13,Inputs!$C$15,Inputs!$C$11/E140))*C140) -> 36.225897 | G140: 35.527 | H140: =IF(OR(G140="",D140=""),"",G140-D140) -> 1.397 | I140: =IF(H140="","",(D140-Inputs!$C$8)/(G140-Inputs!$C$8)) -> 0.79832539 | J140: =IF(C140<=Inputs!$C$12,1,0) -> 0
B141: 45671 | C141: 167.02 | D141: 33.85 | E141: 175.345 | F141: =IF(E141="","",IF(E141<=Inputs!$C$12,Inputs!$C$14,IF(E141>=Inputs!$C$13,Inputs!$C$15,Inputs!$C$11/E141))*C141) -> 35.481451 | G141: 35.069 | H141: =IF(OR(G141="",D141=""),"",G141-D141) -> 1.219 | I141: =IF(H141="","",(D141-Inputs!$C$8)/(G141-Inputs!$C$8)) -> 0.81156284 | J141: =IF(C141<=Inputs!$C$12,1,0) -> 0
B142: 45672 | C142: 166.2 | D142: 33.78 | E142: 175.296 | F142: =IF(E142="","",IF(E142<=Inputs!$C$12,Inputs!$C$14,IF(E142>=Inputs!$C$13,Inputs!$C$15,Inputs!$C$11/E142))*C142) -> 35.317121 | G142: 35.01 | H142: =IF(OR(G142="",D142=""),"",G142-D142) -> 1.23 | I142: =IF(H142="","",(D142-Inputs!$C$8)/(G142-Inputs!$C$8)) -> 0.80811232 | J142: =IF(C142<=Inputs!$C$12,1,0) -> 0
... B294: 45894 | C294: 226.87 | D294: 40.14 | E294: 227.634 | F294: =IF(E294="","",IF(E294<=Inputs!$C$12,Inputs!$C$14,IF(E294>=Inputs!$C$13,Inputs!$C$15,Inputs!$C$11/E294))*C294) -> 40.8366 | G294: 41.558 | H294: =IF(OR(G294="",D294=""),"",G294-D294) -> 1.418 | I294: =IF(H294="","",(D294-Inputs!$C$8)/(G294-Inputs!$C$8)) -> 0.89056953 | J294: =IF(C294<=Inputs!$C$12,1,0) -> 0
B295: 45895 | C295: 234.83 | D295: 41.5 | E295: 228.523 | F295: =IF(E295="","",IF(E295<=Inputs!$C$12,Inputs!$C$14,IF(E295>=Inputs!$C$13,Inputs!$C$15,Inputs!$C$11/E295))*C295) -> 42.2694 | H295: =IF(OR(G295="",D295=""),"",G295-D295) | I295: =IF(H295="","",(D295-Inputs!$C$8)/(G295-Inputs!$C$8)) | J295: =IF(C295<=Inputs!$C$12,1,0) -> 0
B296: 45896 | C296: 235.62 | D296: 41.74 | E296: 228.98 | F296: =IF(E296="","",IF(E296<=Inputs!$C$12,Inputs!$C$14,IF(E296>=Inputs!$C$13,Inputs!$C$15,Inputs!$C$11/E296))*C296) -> 42.4116 | H296: =IF(OR(G296="",D296=""),"",G296-D296) | I296: =IF(H296="","",(D296-Inputs!$C$8)/(G296-Inputs!$C$8)) | J296: =IF(C296<=Inputs!$C$12,1,0) -> 0
B297: 45897 | C297: 236.16 | D297: 41.8 | E297: 229.567 | F297: =IF(E297="","",IF(E297<=Inputs!$C$12,Inputs!$C$14,IF(E297>=Inputs!$C$13,Inputs!$C$15,Inputs!$C$11/E297))*C297) -> 42.5088 | G297: 42.887 | H297: =IF(OR(G297="",D297=""),"",G297-D297) -> 1.087 | I297: =IF(H297="","",(D297-Inputs!$C$8)/(G297-Inputs!$C$8)) -> 0.92391685 | J297: =IF(C297<=Inputs!$C$12,1,0) -> 0
B298: 45898 | C298: 234.68 | D298: 41.59 | E298: 230.011 | F298: =IF(E298="","",IF(E298<=Inputs!$C$12,Inputs!$C$14,IF(E298>=Inputs!$C$13,Inputs!$C$15,Inputs!$C$11/E298))*C298) -> 42.2424 | G298: 42.804 | H298: =IF(OR(G298="",D298=""),"",G298-D298) -> 1.214 | I298: =IF(H298="","",(D298-Inputs!$C$8)/(G298-Inputs!$C$8)) -> 0.91453112 | J298: =IF(C298<=Inputs!$C$12,1,0) -> 0
B299: 45902 | C299: 237.38 | D299: 41.91 | E299: 230.396 | F299: =IF(E299="","",IF(E299<=Inputs!$C$12,Inputs!$C$14,IF(E299>=Inputs!$C$13,Inputs!$C$15,Inputs!$C$11/E299))*C299) -> 42.7284 | G299: 43.184 | H299: =IF(OR(G299="",D299=""),"",G299-D299) -> 1.274 | I299: =IF(H299="","",(D299-Inputs!$C$8)/(G299-Inputs!$C$8)) -> 0.91264399 | J299: =IF(C299<=Inputs!$C$12,1,0) -> 0
B300: 45903 | C300: 232.38 | D300: 41.27 | E300: 230.721 | F300: =IF(E300="","",IF(E300<=Inputs!$C$12,Inputs!$C$14,IF(E300>=Inputs!$C$13,Inputs!$C$15,Inputs!$C$11/E300))*C300) -> 41.8284 | G300: 42.365 | H300: =IF(OR(G300="",D300=""),"",G300-D300) -> 1.095 | I300: =IF(H300="","",(D300-Inputs!$C$8)/(G300-Inputs!$C$8)) -> 0.92045042 | J300: =IF(C300<=Inputs!$C$12,1,0) -> 0
...

Sheet Checks
B2: Checks
B3: Reconciliation with the Python engine (Boeing_Spirit_Collar_Analysis.ipynb)
B5: Item | C5: Excel | D5: Python | E5: Difference | F5: OK
B6: Put at $149, signing day (closing 30 Jun 2025) | C6: =Pricer!G6 -> 7.0738109 | D6: 7.073811 | E6: =C6-D6 -> -8.722104e-08 | F6: =IF(ABS(E6)<0.005,"OK","CHECK") -> OK
B7: Call at $206.94, signing day | C7: =Pricer!G7 -> 17.596581 | D7: 17.596581 | E7: =C7-D7 -> -4.0891452e-07 | F7: =IF(ABS(E7)<0.005,"OK","CHECK") -> OK
B8: Collar value, signing day | C8: =Pricer!C15 -> 36.834446 | D8: 36.834445 | E8: =C8-D8 -> 6.7672234e-07 | F8: =IF(ABS(E8)<0.005,"OK","CHECK") -> OK
B9: Fixed exchange ratio value | C9: =Pricer!C16 -> 37.313325 | D9: 37.313325 | E9: =C9-D9 -> -2.0465908e-07 | F9: =IF(ABS(E9)<0.005,"OK","CHECK") -> OK
B10: Fixed value, no collar | C10: =Pricer!C17 -> 35.436873 | D10: 35.436873 | E10: =C10-D10 -> -1.0147831e-07 | F10: =IF(ABS(E10)<0.005,"OK","CHECK") -> OK
B11: Days Boeing at or below the floor | C11: =Paths!C371 -> 16 | D11: 16 | E11: =C11-D11 -> 0 | F11: =IF(ABS(E11)<0.005,"OK","CHECK") -> OK
B12: Days Boeing at or above the cap | C12: =Paths!C372 -> 98 | D12: 98 | E12: =C12-D12 -> 0 | F12: =IF(ABS(E12)<0.005,"OK","CHECK") -> OK
B13: Lowest value if the deal had closed that day | C13: =Paths!C374 -> 29.438011 | D13: 29.438037 | E13: =C13-D13 -> -2.6041698e-05 | F13: =IF(ABS(E13)<0.005,"OK","CHECK") -> OK
B14: Average merger-arbitrage spread | C14: =Paths!C375 -> 1.3347922 | D14: 1.334796 | E14: =C14-D14 -> -3.8313253e-06 | F14: =IF(ABS(E14)<0.005,"OK","CHECK") -> OK
B15: Median implied probability (break at $28.60) | C15: =Paths!C377 -> 0.85180544 | D15: 0.851778 | E15: =C15-D15 -> 2.744401e-05 | F15: =IF(ABS(E15)<0.005,"OK","CHECK") -> OK
B16: Value delivered at closing (0.1955 × Boeing) | C16: =Inputs!C34*Inputs!C35 -> 40.325785 | D16: 40.325785 | E16: =C16-D16 -> 0 | F16: =IF(ABS(E16)<0.005,"OK","CHECK") -> OK
B19: Python values are copied in as inputs (blue); every Excel value is a formula on this workbook's own inputs.
